Workbook
Name Deadline: 'Executive Dashboard'!$N$7
Name ProjectStart: Lists!$M$2
Name StatusDate: 'Executive Dashboard'!$H$7

Sheet Executive Dashboard
A1: ALTIJARA MAGAZINE TRANSFORMATION · EXECUTIVE DASHBOARD
A2: Client: O2 Nations · Solo Full-Stack Developer · Build 12–25 Oct · QA & Deployment Prep 26–31 Oct · Final deadline 1 Nov 2026
B3: Production (do not touch): | E3: https://altijaramagazine.com/ | J3: Staging (all work here): | M3: https://chocolate-jellyfish-822708.hostingersite.com/
B4: Go to ▸ | C4: Master | D4: P1 | E4: P2 | F4: P3 | G4: P4 | H4: P5 | I4: P6 | J4: QA | K4: Deploy | L4: Risks | M4: Req Map
B6: CONTROL PANEL (yellow cells are editable — everything else is calculated)
B7: Status date override | F7: Effective status date | H7: =IF(D7="",TODAY(),D7) -> 46306 | L7: Final deadline | N7: 46327
B9: PROGRESS OVERVIEW
B10: OVERALL COMPLETION | E10: PLANNED BY STATUS DATE | H10: SCHEDULE VARIANCE | K10: DAYS TO 1 NOV | N10: SCHEDULE HEALTH
B11: =IFERROR(SUMPRODUCT(('Master Tracker'!$A$6:$A$400<>"")*'Master Tracker'!$U$6:$U$400)/COUNTIF('Master Tracker'!$A$6:$A$400,"?*"),0) -> 0.018018018 | E11: =IFERROR(SUMPRODUCT(('Master Tracker'!$A$6:$A$400<>"")*'Master Tracker'!$V$6:$V$400)/COUNTIF('Master Tracker'!$A$6:$A$400,"?*"),0) -> 0 | H11: =B11-E11 -> 0.018018018 | K11: =Deadline-StatusDate -> 21 | N11: =IF(OR(N16>0,L16>0),"AT RISK",IF(B11-E11<-0.05,"BEHIND","ON TRACK")) -> ON TRACK
B12: average task completion | E12: baseline schedule | H12: actual − planned | K12: calendar days | N12: overdue, blocked & variance
B13: ="Overall "&REPT("█",ROUND(B11*60,0))&REPT("░",60-ROUND(B11*60,0))&" "&TEXT(B11,"0%")&" | Planned "&TEXT(E11,"0%") -> Overall █░░░░░░░░░░░░░░░░░░░░░░░░░░░░░░░░░░░░░░░░░░░░░░░░░░░░░░░░░░░ 2% | Planned 0%
B15: TOTAL TASKS | D15: COMPLETED | F15: IN PROGRESS | H15: NOT STARTED | J15: REVIEW / TESTING | L15: BLOCKED | N15: OVERDUE | P15: OPEN P0
B16: =COUNTIF('Master Tracker'!$A$6:$A$400,"?*") -> 111 | D16: =COUNTIFS('Master Tracker'!$G$6:$G$400,"Completed",'Master Tracker'!$A$6:$A$400,"?*") -> 2 | F16: =COUNTIFS('Master Tracker'!$G$6:$G$400,"In Progress",'Master Tracker'!$A$6:$A$400,"?*") -> 0 | H16: =COUNTIFS('Master Tracker'!$G$6:$G$400,"Not Started",'Master Tracker'!$A$6:$A$400,"?*") -> 109 | J16: =COUNTIFS('Master Tracker'!$G$6:$G$400,"In Review",'Master Tracker'!$A$6:$A$400,"?*")+COUNTIFS('Master Tracker'!$G$6:$G$400,"Testing",'Master Tracker'!$A$6:$A$400,"?*") -> 0 | L16: =COUNTIFS('Master Tracker'!$G$6:$G$400,"Blocked",'Master Tracker'!$A$6:$A$400,"?*") -> 0 | N16: =COUNTIF('Master Tracker'!$X$6:$X$400,"OVERDUE") -> 0 | P16: =COUNTIFS('Master Tracker'!$F$6:$F$400,"P0",'Master Tracker'!$G$6:$G$400,"<>Completed",'Master Tracker'!$A$6:$A$400,"?*") -> 71
B17: in scope | D17: =IF($B$16=0,"",TEXT(D16/$B$16,"0%")&" of tasks") -> 2% of tasks | F17: =IF($B$16=0,"",TEXT(F16/$B$16,"0%")&" of tasks") -> 0% of tasks | H17: =IF($B$16=0,"",TEXT(H16/$B$16,"0%")&" of tasks") -> 98% of tasks | J17: =IF($B$16=0,"",TEXT(J16/$B$16,"0%")&" of tasks") -> 0% of tasks | L17: =IF($B$16=0,"",TEXT(L16/$B$16,"0%")&" of tasks") -> 0% of tasks | N17: =IF($B$16=0,"",TEXT(N16/$B$16,"0%")&" of tasks") -> 0% of tasks | P17: =IF($B$16=0,"",TEXT(P16/$B$16,"0%")&" of tasks") -> 64% of tasks
B19: PHASE PROGRESS (click a phase name to open its tracker)
B20: Phase | C20: Phase name | F20: Window | G20: Tasks | H20: Done | I20: Blocked | J20: Overdue | K20: In Prog. | L20: Open P0 | M20: Planned % | N20: Actual % | O20: Progress | Q20: Health
B21: P1 | C21: Theme Foundation & Asset Pipeline | F21: =TEXT(_xlfn.MINIFS('Master Tracker'!$H$6:$H$400,'Master Tracker'!$B$6:$B$400,"Phase 1"),"dd mmm")&" – "&TEXT(_xlfn.MAXIFS('Master Tracker'!$I$6:$I$400,'Master Tracker'!$B$6:$B$400,"Phase 1"),"dd mmm") -> 12 Oct – 14 Oct | G21: =COUNTIFS('Master Tracker'!$B$6:$B$400,"Phase 1",'Master Tracker'!$A$6:$A$400,"?*") -> 17 | H21: =COUNTIFS('Master Tracker'!$B$6:$B$400,"Phase 1",'Master Tracker'!$G$6:$G$400,"Completed") -> 2 | I21: =COUNTIFS('Master Tracker'!$B$6:$B$400,"Phase 1",'Master Tracker'!$G$6:$G$400,"Blocked") -> 0 | J21: =COUNTIFS('Master Tracker'!$B$6:$B$400,"Phase 1",'Master Tracker'!$X$6:$X$400,"OVERDUE") -> 0 | K21: =COUNTIFS('Master Tracker'!$B$6:$B$400,"Phase 1",'Master Tracker'!$G$6:$G$400,"In Progress") -> 0 | L21: =COUNTIFS('Master Tracker'!$B$6:$B$400,"Phase 1",'Master Tracker'!$F$6:$F$400,"P0",'Master Tracker'!$G$6:$G$400,"<>Completed",'Master Tracker'!$A$6:$A$400,"?*") -> 12 | M21: =IFERROR(SUMPRODUCT(('Master Tracker'!$B$6:$B$400="Phase 1")*'Master Tracker'!$V$6:$V$400)/G21,0) -> 0 | N21: =IFERROR(SUMPRODUCT(('Master Tracker'!$B$6:$B$400="Phase 1")*'Master Tracker'!$U$6:$U$400)/G21,0) -> 0.11764706 | O21: =REPT("█",ROUND(N21*14,0))&REPT("░",14-ROUND(N21*14,0)) -> ██░░░░░░░░░░░░ | Q21: =IF(G21=0,"—",IF(H21=G21,"Complete",IF(I21>0,"Blocked",IF(J21>0,"Behind",IF(N21+0.1<M21,"Behind",IF(N21>0,"On Track","Not Started")))))) -> On Track
B22: P2 | C22: Homepage & Dynamic Section Manager | F22: =TEXT(_xlfn.MINIFS('Master Tracker'!$H$6:$H$400,'Master Tracker'!$B$6:$B$400,"Phase 2"),"dd mmm")&" – "&TEXT(_xlfn.MAXIFS('Master Tracker'!$I$6:$I$400,'Master Tracker'!$B$6:$B$400,"Phase 2"),"dd mmm") -> 15 Oct – 17 Oct | G22: =COUNTIFS('Master Tracker'!$B$6:$B$400,"Phase 2",'Master Tracker'!$A$6:$A$400,"?*") -> 24 | H22: =COUNTIFS('Master Tracker'!$B$6:$B$400,"Phase 2",'Master Tracker'!$G$6:$G$400,"Completed") -> 0 | I22: =COUNTIFS('Master Tracker'!$B$6:$B$400,"Phase 2",'Master Tracker'!$G$6:$G$400,"Blocked") -> 0 | J22: =COUNTIFS('Master Tracker'!$B$6:$B$400,"Phase 2",'Master Tracker'!$X$6:$X$400,"OVERDUE") -> 0 | K22: =COUNTIFS('Master Tracker'!$B$6:$B$400,"Phase 2",'Master Tracker'!$G$6:$G$400,"In Progress") -> 0 | L22: =COUNTIFS('Master Tracker'!$B$6:$B$400,"Phase 2",'Master Tracker'!$F$6:$F$400,"P0",'Master Tracker'!$G$6:$G$400,"<>Completed",'Master Tracker'!$A$6:$A$400,"?*") -> 11 | M22: =IFERROR(SUMPRODUCT(('Master Tracker'!$B$6:$B$400="Phase 2")*'Master Tracker'!$V$6:$V$400)/G22,0) -> 0 | N22: =IFERROR(SUMPRODUCT(('Master Tracker'!$B$6:$B$400="Phase 2")*'Master Tracker'!$U$6:$U$400)/G22,0) -> 0 | O22: =REPT("█",ROUND(N22*14,0))&REPT("░",14-ROUND(N22*14,0)) -> ░░░░░░░░░░░░░░ | Q22: =IF(G22=0,"—",IF(H22=G22,"Complete",IF(I22>0,"Blocked",IF(J22>0,"Behind",IF(N22+0.1<M22,"Behind",IF(N22>0,"On Track","Not Started")))))) -> Not Started
B23: P3 | C23: Editorial & Taxonomy Templates | F23: =TEXT(_xlfn.MINIFS('Master Tracker'!$H$6:$H$400,'Master Tracker'!$B$6:$B$400,"Phase 3"),"dd mmm")&" – "&TEXT(_xlfn.MAXIFS('Master Tracker'!$I$6:$I$400,'Master Tracker'!$B$6:$B$400,"Phase 3"),"dd mmm") -> 18 Oct – 20 Oct | G23: =COUNTIFS('Master Tracker'!$B$6:$B$400,"Phase 3",'Master Tracker'!$A$6:$A$400,"?*") -> 16 | H23: =COUNTIFS('Master Tracker'!$B$6:$B$400,"Phase 3",'Master Tracker'!$G$6:$G$400,"Completed") -> 0 | I23: =COUNTIFS('Master Tracker'!$B$6:$B$400,"Phase 3",'Master Tracker'!$G$6:$G$400,"Blocked") -> 0 | J23: =COUNTIFS('Master Tracker'!$B$6:$B$400,"Phase 3",'Master Tracker'!$X$6:$X$400,"OVERDUE") -> 0 | K23: =COUNTIFS('Master Tracker'!$B$6:$B$400,"Phase 3",'Master Tracker'!$G$6:$G$400,"In Progress") -> 0 | L23: =COUNTIFS('Master Tracker'!$B$6:$B$400,"Phase 3",'Master Tracker'!$F$6:$F$400,"P0",'Master Tracker'!$G$6:$G$400,"<>Completed",'Master Tracker'!$A$6:$A$400,"?*") -> 8 | M23: =IFERROR(SUMPRODUCT(('Master Tracker'!$B$6:$B$400="Phase 3")*'Master Tracker'!$V$6:$V$400)/G23,0) -> 0 | N23: =IFERROR(SUMPRODUCT(('Master Tracker'!$B$6:$B$400="Phase 3")*'Master Tracker'!$U$6:$U$400)/G23,0) -> 0 | O23: =REPT("█",ROUND(N23*14,0))&REPT("░",14-ROUND(N23*14,0)) -> ░░░░░░░░░░░░░░ | Q23: =IF(G23=0,"—",IF(H23=G23,"Complete",IF(I23>0,"Blocked",IF(J23>0,"Behind",IF(N23+0.1<M23,"Behind",IF(N23>0,"On Track","Not Started")))))) -> Not Started
B24: P4 | C24: Digital Issues Archive & CPT Engine | F24: =TEXT(_xlfn.MINIFS('Master Tracker'!$H$6:$H$400,'Master Tracker'!$B$6:$B$400,"Phase 4"),"dd mmm")&" – "&TEXT(_xlfn.MAXIFS('Master Tracker'!$I$6:$I$400,'Master Tracker'!$B$6:$B$400,"Phase 4"),"dd mmm") -> 12 Oct – 22 Oct | G24: =COUNTIFS('Master Tracker'!$B$6:$B$400,"Phase 4",'Master Tracker'!$A$6:$A$400,"?*") -> 12 | H24: =COUNTIFS('Master Tracker'!$B$6:$B$400,"Phase 4",'Master Tracker'!$G$6:$G$400,"Completed") -> 0 | I24: =COUNTIFS('Master Tracker'!$B$6:$B$400,"Phase 4",'Master Tracker'!$G$6:$G$400,"Blocked") -> 0 | J24: =COUNTIFS('Master Tracker'!$B$6:$B$400,"Phase 4",'Master Tracker'!$X$6:$X$400,"OVERDUE") -> 0 | K24: =COUNTIFS('Master Tracker'!$B$6:$B$400,"Phase 4",'Master Tracker'!$G$6:$G$400,"In Progress") -> 0 | L24: =COUNTIFS('Master Tracker'!$B$6:$B$400,"Phase 4",'Master Tracker'!$F$6:$F$400,"P0",'Master Tracker'!$G$6:$G$400,"<>Completed",'Master Tracker'!$A$6:$A$400,"?*") -> 9 | M24: =IFERROR(SUMPRODUCT(('Master Tracker'!$B$6:$B$400="Phase 4")*'Master Tracker'!$V$6:$V$400)/G24,0) -> 0 | N24: =IFERROR(SUMPRODUCT(('Master Tracker'!$B$6:$B$400="Phase 4")*'Master Tracker'!$U$6:$U$400)/G24,0) -> 0 | O24: =REPT("█",ROUND(N24*14,0))&REPT("░",14-ROUND(N24*14,0)) -> ░░░░░░░░░░░░░░ | Q24: =IF(G24=0,"—",IF(H24=G24,"Complete",IF(I24>0,"Blocked",IF(J24>0,"Behind",IF(N24+0.1<M24,"Behind",IF(N24>0,"On Track","Not Started")))))) -> Not Started
B25: P5 | C25: Auth, Subscriptions, AdOps & Leads | F25: =TEXT(_xlfn.MINIFS('Master Tracker'!$H$6:$H$400,'Master Tracker'!$B$6:$B$400,"Phase 5"),"dd mmm")&" – "&TEXT(_xlfn.MAXIFS('Master Tracker'!$I$6:$I$400,'Master Tracker'!$B$6:$B$400,"Phase 5"),"dd mmm") -> 12 Oct – 25 Oct | G25: =COUNTIFS('Master Tracker'!$B$6:$B$400,"Phase 5",'Master Tracker'!$A$6:$A$400,"?*") -> 20 | H25: =COUNTIFS('Master Tracker'!$B$6:$B$400,"Phase 5",'Master Tracker'!$G$6:$G$400,"Completed") -> 0 | I25: =COUNTIFS('Master Tracker'!$B$6:$B$400,"Phase 5",'Master Tracker'!$G$6:$G$400,"Blocked") -> 0 | J25: =COUNTIFS('Master Tracker'!$B$6:$B$400,"Phase 5",'Master Tracker'!$X$6:$X$400,"OVERDUE") -> 0 | K25: =COUNTIFS('Master Tracker'!$B$6:$B$400,"Phase 5",'Master Tracker'!$G$6:$G$400,"In Progress") -> 0 | L25: =COUNTIFS('Master Tracker'!$B$6:$B$400,"Phase 5",'Master Tracker'!$F$6:$F$400,"P0",'Master Tracker'!$G$6:$G$400,"<>Completed",'Master Tracker'!$A$6:$A$400,"?*") -> 11 | M25: =IFERROR(SUMPRODUCT(('Master Tracker'!$B$6:$B$400="Phase 5")*'Master Tracker'!$V$6:$V$400)/G25,0) -> 0 | N25: =IFERROR(SUMPRODUCT(('Master Tracker'!$B$6:$B$400="Phase 5")*'Master Tracker'!$U$6:$U$400)/G25,0) -> 0 | O25: =REPT("█",ROUND(N25*14,0))&REPT("░",14-ROUND(N25*14,0)) -> ░░░░░░░░░░░░░░ | Q25: =IF(G25=0,"—",IF(H25=G25,"Complete",IF(I25>0,"Blocked",IF(J25>0,"Behind",IF(N25+0.1<M25,"Behind",IF(N25>0,"On Track","Not Started")))))) -> Not Started
B26: P6 | C26: Database Cleanup, Crawl Audit & Cutover | F26: =TEXT(_xlfn.MINIFS('Master Tracker'!$H$6:$H$400,'Master Tracker'!$B$6:$B$400,"Phase 6"),"dd mmm")&" – "&TEXT(_xlfn.MAXIFS('Master Tracker'!$I$6:$I$400,'Master Tracker'!$B$6:$B$400,"Phase 6"),"dd mmm") -> 12 Oct – 01 Nov | G26: =COUNTIFS('Master Tracker'!$B$6:$B$400,"Phase 6",'Master Tracker'!$A$6:$A$400,"?*") -> 22 | H26: =COUNTIFS('Master Tracker'!$B$6:$B$400,"Phase 6",'Master Tracker'!$G$6:$G$400,"Completed") -> 0 | I26: =COUNTIFS('Master Tracker'!$B$6:$B$400,"Phase 6",'Master Tracker'!$G$6:$G$400,"Blocked") -> 0 | J26: =COUNTIFS('Master Tracker'!$B$6:$B$400,"Phase 6",'Master Tracker'!$X$6:$X$400,"OVERDUE") -> 0 | K26: =COUNTIFS('Master Tracker'!$B$6:$B$400,"Phase 6",'Master Tracker'!$G$6:$G$400,"In Progress") -> 0 | L26: =COUNTIFS('Master Tracker'!$B$6:$B$400,"Phase 6",'Master Tracker'!$F$6:$F$400,"P0",'Master Tracker'!$G$6:$G$400,"<>Completed",'Master Tracker'!$A$6:$A$400,"?*") -> 20 | M26: =IFERROR(SUMPRODUCT(('Master Tracker'!$B$6:$B$400="Phase 6")*'Master Tracker'!$V$6:$V$400)/G26,0) -> 0 | N26: =IFERROR(SUMPRODUCT(('Master Tracker'!$B$6:$B$400="Phase 6")*'Master Tracker'!$U$6:$U$400)/G26,0) -> 0 | O26: =REPT("█",ROUND(N26*14,0))&REPT("░",14-ROUND(N26*14,0)) -> ░░░░░░░░░░░░░░ | Q26: =IF(G26=0,"—",IF(H26=G26,"Complete",IF(I26>0,"Blocked",IF(J26>0,"Behind",IF(N26+0.1<M26,"Behind",IF(N26>0,"On Track","Not Started")))))) -> Not Started
B27: TOTAL | G27: =SUM(G21:G26) -> 111 | H27: =SUM(H21:H26) -> 2 | I27: =SUM(I21:I26) -> 0 | J27: =SUM(J21:J26) -> 0 | K27: =SUM(K21:K26) -> 0 | L27: =SUM(L21:L26) -> 71 | M27: =E11 -> 0 | N27: =B11 -> 0.018018018
B29: PRIORITY BREAKDOWN | J29: STATUS MIX | N29: OPEN EXTERNAL DEPENDENCIES
B30: Priority | E30: Tasks | F30: Completed | G30: Open | H30: % Done | J30: Status | K30: Count | L30: % | N30: Type | P30: Open | Q30: Next due
B31: P0 · Must-have for launch | E31: =COUNTIFS('Master Tracker'!$F$6:$F$400,"P0",'Master Tracker'!$A$6:$A$400,"?*") -> 73 | F31: =COUNTIFS('Master Tracker'!$F$6:$F$400,"P0",'Master Tracker'!$G$6:$G$400,"Completed") -> 2 | G31: =E31-F31 -> 71 | H31: =IFERROR(F31/E31,0) -> 0.02739726 | J31: Not Started | K31: =COUNTIFS('Master Tracker'!$G$6:$G$400,"Not Started",'Master Tracker'!$A$6:$A$400,"?*") -> 109 | L31: =IFERROR(K31/$B$16,0) -> 0.98198198 | N31: Credentials | P31: =COUNTIFS('Master Tracker'!$S$6:$S$400,"Credentials",'Master Tracker'!$G$6:$G$400,"<>Completed",'Master Tracker'!$A$6:$A$400,"?*") -> 6 | Q31: =IF(P31=0,"—",_xlfn.MINIFS('Master Tracker'!$I$6:$I$400,'Master Tracker'!$S$6:$S$400,"Credentials",'Master Tracker'!$G$6:$G$400,"<>Completed")) -> 46308
B32: P1 · Important | E32: =COUNTIFS('Master Tracker'!$F$6:$F$400,"P1",'Master Tracker'!$A$6:$A$400,"?*") -> 34 | F32: =COUNTIFS('Master Tracker'!$F$6:$F$400,"P1",'Master Tracker'!$G$6:$G$400,"Completed") -> 0 | G32: =E32-F32 -> 34 | H32: =IFERROR(F32/E32,0) -> 0 | J32: In Progress | K32: =COUNTIFS('Master Tracker'!$G$6:$G$400,"In Progress",'Master Tracker'!$A$6:$A$400,"?*") -> 0 | L32: =IFERROR(K32/$B$16,0) -> 0 | N32: Payment Approval | P32: =COUNTIFS('Master Tracker'!$S$6:$S$400,"Payment Approval",'Master Tracker'!$G$6:$G$400,"<>Completed",'Master Tracker'!$A$6:$A$400,"?*") -> 3 | Q32: =IF(P32=0,"—",_xlfn.MINIFS('Master Tracker'!$I$6:$I$400,'Master Tracker'!$S$6:$S$400,"Payment Approval",'Master Tracker'!$G$6:$G$400,"<>Completed")) -> 46317
B33: P2 · Nice-to-have / deferrable | E33: =COUNTIFS('Master Tracker'!$F$6:$F$400,"P2",'Master Tracker'!$A$6:$A$400,"?*") -> 4 | F33: =COUNTIFS('Master Tracker'!$F$6:$F$400,"P2",'Master Tracker'!$G$6:$G$400,"Completed") -> 0 | G33: =E33-F33 -> 4 | H33: =IFERROR(F33/E33,0) -> 0 | J33: Blocked | K33: =COUNTIFS('Master Tracker'!$G$6:$G$400,"Blocked",'Master Tracker'!$A$6:$A$400,"?*") -> 0 | L33: =IFERROR(K33/$B$16,0) -> 0 | N33: Historical Assets | P33: =COUNTIFS('Master Tracker'!$S$6:$S$400,"Historical Assets",'Master Tracker'!$G$6:$G$400,"<>Completed",'Master Tracker'!$A$6:$A$400,"?*") -> 1 | Q33: =IF(P33=0,"—",_xlfn.MINIFS('Master Tracker'!$I$6:$I$400,'Master Tracker'!$S$6:$S$400,"Historical Assets",'Master Tracker'!$G$6:$G$400,"<>Completed")) -> 46315
J34: In Review | K34: =COUNTIFS('Master Tracker'!$G$6:$G$400,"In Review",'Master Tracker'!$A$6:$A$400,"?*") -> 0 | L34: =IFERROR(K34/$B$16,0) -> 0 | N34: Server Access | P34: =COUNTIFS('Master Tracker'!$S$6:$S$400,"Server Access",'Master Tracker'!$G$6:$G$400,"<>Completed",'Master Tracker'!$A$6:$A$400,"?*") -> 9 | Q34: =IF(P34=0,"—",_xlfn.MINIFS('Master Tracker'!$I$6:$I$400,'Master Tracker'!$S$6:$S$400,"Server Access",'Master Tracker'!$G$6:$G$400,"<>Completed")) -> 46307
B35: =IF(N16+L16=0,"✓ No overdue or blocked tasks.","⚠ "&N16&" overdue and "&L16&" blocked task(s). See the lists below and the Master Tracker Alert column.") -> ✓ No overdue or blocked tasks. | J35: Testing | K35: =COUNTIFS('Master Tracker'!$G$6:$G$400,"Testing",'Master Tracker'!$A$6:$A$400,"?*") -> 0 | L35: =IFERROR(K35/$B$16,0) -> 0 | N35: Client Content | P35: =COUNTIFS('Master Tracker'!$S$6:$S$400,"Client Content",'Master Tracker'!$G$6:$G$400,"<>Completed",'Master Tracker'!$A$6:$A$400,"?*") -> 4 | Q35: =IF(P35=0,"—",_xlfn.MINIFS('Master Tracker'!$I$6:$I$400,'Master Tracker'!$S$6:$S$400,"Client Content",'Master Tracker'!$G$6:$G$400,"<>Completed")) -> 46320
J36: Completed | K36: =COUNTIFS('Master Tracker'!$G$6:$G$400,"Completed",'Master Tracker'!$A$6:$A$400,"?*") -> 2 | L36: =IFERROR(K36/$B$16,0) -> 0.018018018
J37: Overdue | K37: =N16 -> 0 | L37: =IFERROR(K37/$B$16,0) -> 0
B40: CHARTS (update automatically from the Master Tracker)
B58: UPCOMING DEADLINES (next open tasks by due date) | K58: CRITICAL BLOCKERS (Blocked status or blocker text)
B59: ID | C59: Task | F59: Phase | G59: Due | H59: Days | I59: Status | K59: ID | L59: Task | N59: Status | O59: Blocker / Issue
B60: =IF($S60="","",INDEX('Master Tracker'!$A$6:$A$400,$S60)) -> P1-03 | C60: =IF($S60="","",INDEX('Master Tracker'!$D$6:$D$400,$S60)) -> Theme setup: supports, menus, image sizes | F60: =IF($S60="","",INDEX('Master Tracker'!$B$6:$B$400,$S60)) -> Phase 1 | G60: =IF($S60="","",INDEX('Master Tracker'!$I$6:$I$400,$S60)) -> 46307 | H60: =IF($S60="","",INDEX('Master Tracker'!$W$6:$W$400,$S60)) -> 1 | I60: =IF($S60="","",INDEX('Master Tracker'!$G$6:$G$400,$S60)) -> Not Started | K60: =IF($T60="","",INDEX('Master Tracker'!$A:$A,$T60)) | L60: =IF($T60="","",INDEX('Master Tracker'!$D:$D,$T60)) | N60: =IF($T60="","",INDEX('Master Tracker'!$G:$G,$T60)) | O60: =IF($T60="","",INDEX('Master Tracker'!$P:$P,$T60)) | S60: =IFERROR(MATCH(SMALL('Master Tracker'!$AA$6:$AA$400,1),'Master Tracker'!$AA$6:$AA$400,0),"") -> 3 | T60: =IFERROR(SMALL('Master Tracker'!$AB$6:$AB$400,1),"")
B61: =IF($S61="","",INDEX('Master Tracker'!$A$6:$A$400,$S61)) -> P1-04 | C61: =IF($S61="","",INDEX('Master Tracker'!$D$6:$D$400,$S61)) -> Asset enqueue, versioning & conditional loading | F61: =IF($S61="","",INDEX('Master Tracker'!$B$6:$B$400,$S61)) -> Phase 1 | G61: =IF($S61="","",INDEX('Master Tracker'!$I$6:$I$400,$S61)) -> 46307 | H61: =IF($S61="","",INDEX('Master Tracker'!$W$6:$W$400,$S61)) -> 1 | I61: =IF($S61="","",INDEX('Master Tracker'!$G$6:$G$400,$S61)) -> Not Started | K61: =IF($T61="","",INDEX('Master Tracker'!$A:$A,$T61)) | L61: =IF($T61="","",INDEX('Master Tracker'!$D:$D,$T61)) | N61: =IF($T61="","",INDEX('Master Tracker'!$G:$G,$T61)) | O61: =IF($T61="","",INDEX('Master Tracker'!$P:$P,$T61)) | S61: =IFERROR(MATCH(SMALL('Master Tracker'!$AA$6:$AA$400,2),'Master Tracker'!$AA$6:$AA$400,0),"") -> 4 | T61: =IFERROR(SMALL('Master Tracker'!$AB$6:$AB$400,2),"")
B62: =IF($S62="","",INDEX('Master Tracker'!$A$6:$A$400,$S62)) -> P1-05 | C62: =IF($S62="","",INDEX('Master Tracker'!$D$6:$D$400,$S62)) -> Base template hierarchy | F62: =IF($S62="","",INDEX('Master Tracker'!$B$6:$B$400,$S62)) -> Phase 1 | G62: =IF($S62="","",INDEX('Master Tracker'!$I$6:$I$400,$S62)) -> 46307 | H62: =IF($S62="","",INDEX('Master Tracker'!$W$6:$W$400,$S62)) -> 1 | I62: =IF($S62="","",INDEX('Master Tracker'!$G$6:$G$400,$S62)) -> Not Started | K62: =IF($T62="","",INDEX('Master Tracker'!$A:$A,$T62)) | L62: =IF($T62="","",INDEX('Master Tracker'!$D:$D,$T62)) | N62: =IF($T62="","",INDEX('Master Tracker'!$G:$G,$T62)) | O62: =IF($T62="","",INDEX('Master Tracker'!$P:$P,$T62)) | S62: =IFERROR(MATCH(SMALL('Master Tracker'!$AA$6:$AA$400,3),'Master Tracker'!$AA$6:$AA$400,0),"") -> 5 | T62: =IFERROR(SMALL('Master Tracker'!$AB$6:$AB$400,3),"")
B63: =IF($S63="","",INDEX('Master Tracker'!$A$6:$A$400,$S63)) -> P1-06 | C63: =IF($S63="","",INDEX('Master Tracker'!$D$6:$D$400,$S63)) -> Reusable template-part components | F63: =IF($S63="","",INDEX('Master Tracker'!$B$6:$B$400,$S63)) -> Phase 1 | G63: =IF($S63="","",INDEX('Master Tracker'!$I$6:$I$400,$S63)) -> 46307 | H63: =IF($S63="","",INDEX('Master Tracker'!$W$6:$W$400,$S63)) -> 1 | I63: =IF($S63="","",INDEX('Master Tracker'!$G$6:$G$400,$S63)) -> Not Started | K63: =IF($T63="","",INDEX('Master Tracker'!$A:$A,$T63)) | L63: =IF($T63="","",INDEX('Master Tracker'!$D:$D,$T63)) | N63: =IF($T63="","",INDEX('Master Tracker'!$G:$G,$T63)) | O63: =IF($T63="","",INDEX('Master Tracker'!$P:$P,$T63)) | S63: =IFERROR(MATCH(SMALL('Master Tracker'!$AA$6:$AA$400,4),'Master Tracker'!$AA$6:$AA$400,0),"") -> 6 | T63: =IFERROR(SMALL('Master Tracker'!$AB$6:$AB$400,4),"")
B64: =IF($S64="","",INDEX('Master Tracker'!$A$6:$A$400,$S64)) -> P6-01 | C64: =IF($S64="","",INDEX('Master Tracker'!$D$6:$D$400,$S64)) -> Full production backup (files + DB) before any work | F64: =IF($S64="","",INDEX('Master Tracker'!$B$6:$B$400,$S64)) -> Phase 6 | G64: =IF($S64="","",INDEX('Master Tracker'!$I$6:$I$400,$S64)) -> 46307 | H64: =IF($S64="","",INDEX('Master Tracker'!$W$6:$W$400,$S64)) -> 1 | I64: =IF($S64="","",INDEX('Master Tracker'!$G$6:$G$400,$S64)) -> Not Started | K64: =IF($T64="","",INDEX('Master Tracker'!$A:$A,$T64)) | L64: =IF($T64="","",INDEX('Master Tracker'!$D:$D,$T64)) | N64: =IF($T64="","",INDEX('Master Tracker'!$G:$G,$T64)) | O64: =IF($T64="","",INDEX('Master Tracker'!$P:$P,$T64)) | S64: =IFERROR(MATCH(SMALL('Master Tracker'!$AA$6:$AA$400,5),'Master Tracker'!$AA$6:$AA$400,0),"") -> 90 | T64: =IFERROR(SMALL('Master Tracker'!$AB$6:$AB$400,5),"")
B65: =IF($S65="","",INDEX('Master Tracker'!$A$6:$A$400,$S65)) -> P6-02 | C65: =IF($S65="","",INDEX('Master Tracker'!$D$6:$D$400,$S65)) -> Verify staging mirrors production | F65: =IF($S65="","",INDEX('Master Tracker'!$B$6:$B$400,$S65)) -> Phase 6 | G65: =IF($S65="","",INDEX('Master Tracker'!$I$6:$I$400,$S65)) -> 46307 | H65: =IF($S65="","",INDEX('Master Tracker'!$W$6:$W$400,$S65)) -> 1 | I65: =IF($S65="","",INDEX('Master Tracker'!$G$6:$G$400,$S65)) -> Not Started | K65: =IF($T65="","",INDEX('Master Tracker'!$A:$A,$T65)) | L65: =IF($T65="","",INDEX('Master Tracker'!$D:$D,$T65)) | N65: =IF($T65="","",INDEX('Master Tracker'!$G:$G,$T65)) | O65: =IF($T65="","",INDEX('Master Tracker'!$P:$P,$T65)) | S65: =IFERROR(MATCH(SMALL('Master Tracker'!$AA$6:$AA$400,6),'Master Tracker'!$AA$6:$AA$400,0),"") -> 91 | T65: =IFERROR(SMALL('Master Tracker'!$AB$6:$AB$400,6),"")
B66: =IF($S66="","",INDEX('Master Tracker'!$A$6:$A$400,$S66)) -> P1-07 | C66: =IF($S66="","",INDEX('Master Tracker'!$D$6:$D$400,$S66)) -> CSS architecture & design tokens | F66: =IF($S66="","",INDEX('Master Tracker'!$B$6:$B$400,$S66)) -> Phase 1 | G66: =IF($S66="","",INDEX('Master Tracker'!$I$6:$I$400,$S66)) -> 46308 | H66: =IF($S66="","",INDEX('Master Tracker'!$W$6:$W$400,$S66)) -> 2 | I66: =IF($S66="","",INDEX('Master Tracker'!$G$6:$G$400,$S66)) -> Not Started | K66: =IF($T66="","",INDEX('Master Tracker'!$A:$A,$T66)) | L66: =IF($T66="","",INDEX('Master Tracker'!$D:$D,$T66)) | N66: =IF($T66="","",INDEX('Master Tracker'!$G:$G,$T66)) | O66: =IF($T66="","",INDEX('Master Tracker'!$P:$P,$T66)) | S66: =IFERROR(MATCH(SMALL('Master Tracker'!$AA$6:$AA$400,7),'Master Tracker'!$AA$6:$AA$400,0),"") -> 7 | T66: =IFERROR(SMALL('Master Tracker'!$AB$6:$AB$400,7),"")
B67: =IF($S67="","",INDEX('Master Tracker'!$A$6:$A$400,$S67)) -> P1-08 | C67: =IF($S67="","",INDEX('Master Tracker'!$D$6:$D$400,$S67)) -> Vanilla JS module architecture | F67: =IF($S67="","",INDEX('Master Tracker'!$B$6:$B$400,$S67)) -> Phase 1 | G67: =IF($S67="","",INDEX('Master Tracker'!$I$6:$I$400,$S67)) -> 46308 | H67: =IF($S67="","",INDEX('Master Tracker'!$W$6:$W$400,$S67)) -> 2 | I67: =IF($S67="","",INDEX('Master Tracker'!$G$6:$G$400,$S67)) -> Not Started | K67: =IF($T67="","",INDEX('Master Tracker'!$A:$A,$T67)) | L67: =IF($T67="","",INDEX('Master Tracker'!$D:$D,$T67)) | N67: =IF($T67="","",INDEX('Master Tracker'!$G:$G,$T67)) | O67: =IF($T67="","",INDEX('Master Tracker'!$P:$P,$T67)) | S67: =IFERROR(MATCH(SMALL('Master Tracker'!$AA$6:$AA$400,8),'Master Tracker'!$AA$6:$AA$400,0),"") -> 8 | T67: =IFERROR(SMALL('Master Tracker'!$AB$6:$AB$400,8),"")
B68: =IF($S68="","",INDEX('Master Tracker'!$A$6:$A$400,$S68)) -> P1-09 | C68: =IF($S68="","",INDEX('Master Tracker'!$D$6:$D$400,$S68)) -> RTL layout & Arabic typography | F68: =IF($S68="","",INDEX('Master Tracker'!$B$6:$B$400,$S68)) -> Phase 1 | G68: =IF($S68="","",INDEX('Master Tracker'!$I$6:$I$400,$S68)) -> 46308 | H68: =IF($S68="","",INDEX('Master Tracker'!$W$6:$W$400,$S68)) -> 2 | I68: =IF($S68="","",INDEX('Master Tracker'!$G$6:$G$400,$S68)) -> Not Started | K68: =IF($T68="","",INDEX('Master Tracker'!$A:$A,$T68)) | L68: =IF($T68="","",INDEX('Master Tracker'!$D:$D,$T68)) | N68: =IF($T68="","",INDEX('Master Tracker'!$G:$G,$T68)) | O68: =IF($T68="","",INDEX('Master Tracker'!$P:$P,$T68)) | S68: =IFERROR(MATCH(SMALL('Master Tracker'!$AA$6:$AA$400,9),'Master Tracker'!$AA$6:$AA$400,0),"") -> 9 | T68: =IFERROR(SMALL('Master Tracker'!$AB$6:$AB$400,9),"")
B69: =IF($S69="","",INDEX('Master Tracker'!$A$6:$A$400,$S69)) -> P1-10 | C69: =IF($S69="","",INDEX('Master Tracker'!$D$6:$D$400,$S69)) -> Responsive grid & breakpoints | F69: =IF($S69="","",INDEX('Master Tracker'!$B$6:$B$400,$S69)) -> Phase 1 | G69: =IF($S69="","",INDEX('Master Tracker'!$I$6:$I$400,$S69)) -> 46308 | H69: =IF($S69="","",INDEX('Master Tracker'!$W$6:$W$400,$S69)) -> 2 | I69: =IF($S69="","",INDEX('Master Tracker'!$G$6:$G$400,$S69)) -> Not Started | K69: =IF($T69="","",INDEX('Master Tracker'!$A:$A,$T69)) | L69: =IF($T69="","",INDEX('Master Tracker'!$D:$D,$T69)) | N69: =IF($T69="","",INDEX('Master Tracker'!$G:$G,$T69)) | O69: =IF($T69="","",INDEX('Master Tracker'!$P:$P,$T69)) | S69: =IFERROR(MATCH(SMALL('Master Tracker'!$AA$6:$AA$400,10),'Master Tracker'!$AA$6:$AA$400,0),"") -> 10 | T69: =IFERROR(SMALL('Master Tracker'!$AB$6:$AB$400,10),"")
K70: =IF(COUNT(T60:T69)=0,"✓ No blockers recorded",IF(COUNT('Master Tracker'!AB6:AB400)>10,"+ more blockers — filter Master Tracker by Status = Blocked","")) -> ✓ No blockers recorded
B72: HOW TO USE
B73: 1. Update Status, Completion %, Actual Hours and Completion Date only in the Master Tracker (white / yellow cells). Every other sheet updates automatically.
B74: 2. Columns headed with ƒ (gray cells) are formulas — do not type over them. Yellow cells are editable inputs.
B75: 3. Overall completion = average of all tasks: Completed = 100%, Not Started = 0%, otherwise the Completion % you enter (capped at 99%).
B76: 4. Planned % = how far each task is through its Start→Due window on the status date. Change dates in the Master Tracker to re-baseline.
B77: 5. Source note: built from the project brief. The 13-page Engineering Directive PDF was not available when generated — reconcile acceptance criteria against it (Risk R-01).
B78: 6. Spare blank rows at the bottom of the Master Tracker are pre-wired for new tasks: give them an ID like P3-17 and a Phase, and they flow into every view.

Sheet Master Tracker
A1: MASTER PROJECT TRACKER · single source of truth
A2: Edit tasks here only — dashboard, phase sheets and requirement map recalculate automatically.
A3: Legend: | B3: Editable | C3: ƒ Calculated | D3: Status colors → | E3: Completed · In Progress · In Review / Testing · Blocked / Overdue · Not Started | G3: ← Dashboard | I3: Staging ↗ | K3: Live ↗
A5: Task ID | B5: Phase ▾ | C5: Module ▾ | D5: Task Name | E5: Detailed Description | F5: Priority ▾ | G5: Status ▾ | H5: Start Date ▾ | I5: Due Date ▾ | J5: Completion % ▾ | K5: Dependencies ▾ | L5: Environment ▾ | M5: Related WordPress Files | N5: Testing Checklist | O5: Acceptance Criteria | P5: Blocker / Issue ▾ | Q5: Notes ▾ | R5: Completion Date ▾ | S5: External Requirement ▾ | T5: Test Result ▾ | U5: ƒ Effective % | V5: ƒ Planned % | W5: ƒ Days Left | X5: ƒ Overdue | Y5: ƒ Dependency Check | Z5: ƒ Phase Key | AA5: ƒ Upcoming Key | AB5: ƒ Blocker Key | AC5: ƒ Alert
A6: P1-01 | B6: Phase 1 | C6: Staging Setup | D6: Staging environment readiness audit | E6: Confirm Hostinger staging access (hPanel, SFTP/SSH, phpMyAdmin), PHP 8.1+, WordPress & plugin versions, memory limits; enable WP_DEBUG_LOG; block indexing (noindex + password/IP protection); disable or trap outgoing mail so staging never emails real readers. | F6: P0 | G6: Completed | H6: 46307 | I6: 46307 | J6: 0 | K6: P6-02 | L6: Staging (Hostinger) | M6: wp-config.php, .htaccess | N6: Log in via hPanel, SFTP and phpMyAdmin; confirm noindex header; send test mail is trapped | O6: Staging is reachable only by the team, not indexed, debug logging active, versions documented in Notes | S6: Server Access | T6: Not Tested | U6: =IF(A6="",0,IF(G6="Completed",1,IF(G6="Not Started",0,MIN(0.99,N(J6))))) -> 1 | V6: =IF(OR(A6="",H6="",I6=""),0,MAX(0,MIN(1,(StatusDate-H6+1)/(I6-H6+1)))) -> 0 | W6: =IF(OR(A6="",I6="",G6="Completed"),"",I6-StatusDate) | X6: =IF(A6="","",IF(AND(G6<>"Completed",I6<>"",I6<StatusDate),"OVERDUE","")) | Y6: =IF(OR(A6="",K6=""),"",IF(SUMPRODUCT(($A$6:$A$400<>"")*ISNUMBER(SEARCH($A$6:$A$400,K6))*($G$6:$G$400<>"Completed"))=0,"✓ Ready","⏳ "&SUMPRODUCT(($A$6:$A$400<>"")*ISNUMBER(SEARCH($A$6:$A$400,K6))*($G$6:$G$400<>"Completed"))&" open")) -> ⏳ 1 open | Z6: =IF(A6="","",B6&"|"&COUNTIFS($B$6:B6,B6,$A$6:A6,"?*")) -> Phase 1|1 | AA6: =IF(OR(A6="",I6="",G6="Completed"),"",IF(I6>=StatusDate,I6+ROW()/100000,"")) | AB6: =IF(A6="","",IF(AND(G6<>"Completed",OR(G6="Blocked",AND(TRIM(P6)<>"",P6<>"None"))),ROW(),"")) | AC6: =IF(A6="","",IF(G6="Completed","Done",IF(G6="Blocked","Blocked",IF(X6="OVERDUE","Overdue",IF(AND(W6<>"",W6<=2),"Due soon",IF(AND(Y6<>"",LEFT(Y6,1)="⏳",G6<>"Not Started"),"Dependency open",IF(AND(S6<>"None",S6<>"",G6<>"Completed"),"External req.","On track"))))))) -> Done
A7: P1-02 | B7: Phase 1 | C7: Theme Scaffold | D7: Create custom theme structure + Git repo | E7: Create /wp-content/themes/altijara/ with style.css header (Text Domain altijara, RTL), functions.php loader, inc/, template-parts/, assets/{css,js,fonts,img}, languages/. Initialise a remote Git repository for the theme as the backup of all staging work (no local environment). | F7: P0 | G7: Completed | H7: 46307 | I7: 46307 | J7: 0 | K7: P1-01 | L7: Staging (Hostinger) | M7: style.css, functions.php, inc/, template-parts/, assets/ | N7: Theme listed in Appearance > Themes; activates with no PHP notices; first commit pushed | O7: Folder structure in place, theme activates cleanly on staging, repository holds initial commit | S7: None | T7: Not Tested | U7: =IF(A7="",0,IF(G7="Completed",1,IF(G7="Not Started",0,MIN(0.99,N(J7))))) -> 1 | V7: =IF(OR(A7="",H7="",I7=""),0,MAX(0,MIN(1,(StatusDate-H7+1)/(I7-H7+1)))) -> 0 | W7: =IF(OR(A7="",I7="",G7="Completed"),"",I7-StatusDate) | X7: =IF(A7="","",IF(AND(G7<>"Completed",I7<>"",I7<StatusDate),"OVERDUE","")) | Y7: =IF(OR(A7="",K7=""),"",IF(SUMPRODUCT(($A$6:$A$400<>"")*ISNUMBER(SEARCH($A$6:$A$400,K7))*($G$6:$G$400<>"Completed"))=0,"✓ Ready","⏳ "&SUMPRODUCT(($A$6:$A$400<>"")*ISNUMBER(SEARCH($A$6:$A$400,K7))*($G$6:$G$400<>"Completed"))&" open")) -> ✓ Ready | Z7: =IF(A7="","",B7&"|"&COUNTIFS($B$6:B7,B7,$A$6:A7,"?*")) -> Phase 1|2 | AA7: =IF(OR(A7="",I7="",G7="Completed"),"",IF(I7>=StatusDate,I7+ROW()/100000,"")) | AB7: =IF(A7="","",IF(AND(G7<>"Completed",OR(G7="Blocked",AND(TRIM(P7)<>"",P7<>"None"))),ROW(),"")) | AC7: =IF(A7="","",IF(G7="Completed","Done",IF(G7="Blocked","Blocked",IF(X7="OVERDUE","Overdue",IF(AND(W7<>"",W7<=2),"Due soon",IF(AND(Y7<>"",LEFT(Y7,1)="⏳",G7<>"Not Started"),"Dependency open",IF(AND(S7<>"None",S7<>"",G7<>"Completed"),"External req.","On track"))))))) -> Done
A8: P1-03 | B8: Phase 1 | C8: Theme Initialization | D8: Theme setup: supports, menus, image sizes | E8: inc/setup.php: add_theme_support (title-tag, post-thumbnails, html5, custom-logo, responsive-embeds, align-wide, editor-styles); register_nav_menus (primary, top-bar, footer, mobile); add_image_size (hero, card, thumb, issue-cover); load_theme_textdomain; content_width. | F8: P0 | G8: Not Started | H8: 46307 | I8: 46307 | J8: 0 | K8: P1-02 | L8: Staging (Hostinger) | M8: inc/setup.php, functions.php | N8: Menus appear in Appearance > Menus; new upload generates all image sizes; single <title> tag | O8: All supports, menus and image sizes registered; no duplicate title tags | S8: None | T8: Not Tested | U8: =IF(A8="",0,IF(G8="Completed",1,IF(G8="Not Started",0,MIN(0.99,N(J8))))) -> 0 | V8: =IF(OR(A8="",H8="",I8=""),0,MAX(0,MIN(1,(StatusDate-H8+1)/(I8-H8+1)))) -> 0 | W8: =IF(OR(A8="",I8="",G8="Completed"),"",I8-StatusDate) -> 1 | X8: =IF(A8="","",IF(AND(G8<>"Completed",I8<>"",I8<StatusDate),"OVERDUE","")) | Y8: =IF(OR(A8="",K8=""),"",IF(SUMPRODUCT(($A$6:$A$400<>"")*ISNUMBER(SEARCH($A$6:$A$400,K8))*($G$6:$G$400<>"Completed"))=0,"✓ Ready","⏳ "&SUMPRODUCT(($A$6:$A$400<>"")*ISNUMBER(SEARCH($A$6:$A$400,K8))*($G$6:$G$400<>"Completed"))&" open")) -> ✓ Ready | Z8: =IF(A8="","",B8&"|"&COUNTIFS($B$6:B8,B8,$A$6:A8,"?*")) -> Phase 1|3 | AA8: =IF(OR(A8="",I8="",G8="Completed"),"",IF(I8>=StatusDate,I8+ROW()/100000,"")) -> 46307 | AB8: =IF(A8="","",IF(AND(G8<>"Completed",OR(G8="Blocked",AND(TRIM(P8)<>"",P8<>"None"))),ROW(),"")) | AC8: =IF(A8="","",IF(G8="Completed","Done",IF(G8="Blocked","Blocked",IF(X8="OVERDUE","Overdue",IF(AND(W8<>"",W8<=2),"Due soon",IF(AND(Y8<>"",LEFT(Y8,1)="⏳",G8<>"Not Started"),"Dependency open",IF(AND(S8<>"None",S8<>"",G8<>"Completed"),"External req.","On track"))))))) -> Due soon
A9: P1-04 | B9: Phase 1 | C9: Asset Pipeline | D9: Asset enqueue, versioning & conditional loading | E9: inc/enqueue.php: enqueue CSS/JS with filemtime() cache-busting, per-template conditional loading, defer/module attributes, preload primary Arabic font, remove emoji script, no jQuery dependency on the front end. | F9: P0 | G9: Not Started | H9: 46307 | I9: 46307 | J9: 0 | K9: P1-02 | L9: Staging (Hostinger) | M9: inc/enqueue.php, assets/css/*, assets/js/* | N9: View source: versioned URLs, deferred scripts; Network tab shows no 404s and no jQuery on homepage | O9: All assets versioned and loaded only where needed; zero console errors | S9: None | T9: Not Tested | U9: =IF(A9="",0,IF(G9="Completed",1,IF(G9="Not Started",0,MIN(0.99,N(J9))))) -> 0 | V9: =IF(OR(A9="",H9="",I9=""),0,MAX(0,MIN(1,(StatusDate-H9+1)/(I9-H9+1)))) -> 0 | W9: =IF(OR(A9="",I9="",G9="Completed"),"",I9-StatusDate) -> 1 | X9: =IF(A9="","",IF(AND(G9<>"Completed",I9<>"",I9<StatusDate),"OVERDUE","")) | Y9: =IF(OR(A9="",K9=""),"",IF(SUMPRODUCT(($A$6:$A$400<>"")*ISNUMBER(SEARCH($A$6:$A$400,K9))*($G$6:$G$400<>"Completed"))=0,"✓ Ready","⏳ "&SUMPRODUCT(($A$6:$A$400<>"")*ISNUMBER(SEARCH($A$6:$A$400,K9))*($G$6:$G$400<>"Completed"))&" open")) -> ✓ Ready | Z9: =IF(A9="","",B9&"|"&COUNTIFS($B$6:B9,B9,$A$6:A9,"?*")) -> Phase 1|4 | AA9: =IF(OR(A9="",I9="",G9="Completed"),"",IF(I9>=StatusDate,I9+ROW()/100000,"")) -> 46307 | AB9: =IF(A9="","",IF(AND(G9<>"Completed",OR(G9="Blocked",AND(TRIM(P9)<>"",P9<>"None"))),ROW(),"")) | AC9: =IF(A9="","",IF(G9="Completed","Done",IF(G9="Blocked","Blocked",IF(X9="OVERDUE","Overdue",IF(AND(W9<>"",W9<=2),"Due soon",IF(AND(Y9<>"",LEFT(Y9,1)="⏳",G9<>"Not Started"),"Dependency open",IF(AND(S9<>"None",S9<>"",G9<>"Completed"),"External req.","On track"))))))) -> Due soon
A10: P1-05 | B10: Phase 1 | C10: PHP Templates | D10: Base template hierarchy | E10: Create header.php, footer.php, index.php, front-page.php, single.php, page.php, archive.php, category.php, tag.php, author.php, search.php, 404.php skeletons sharing a common layout wrapper. | F10: P0 | G10: Not Started | H10: 46307 | I10: 46307 | J10: 0 | K10: P1-03 | L10: Staging (Hostinger) | M10: header.php, footer.php, index.php, front-page.php, single.php, page.php, archive.php, category.php, tag.php, author.php, search.php, 404.php | N10: Visit each route type; Query Monitor confirms expected template file | O10: Every WordPress route resolves to a theme template with header/footer; no fallback errors | S10: None | T10: Not Tested | U10: =IF(A10="",0,IF(G10="Completed",1,IF(G10="Not Started",0,MIN(0.99,N(J10))))) -> 0 | V10: =IF(OR(A10="",H10="",I10=""),0,MAX(0,MIN(1,(StatusDate-H10+1)/(I10-H10+1)))) -> 0 | W10: =IF(OR(A10="",I10="",G10="Completed"),"",I10-StatusDate) -> 1 | X10: =IF(A10="","",IF(AND(G10<>"Completed",I10<>"",I10<StatusDate),"OVERDUE","")) | Y10: =IF(OR(A10="",K10=""),"",IF(SUMPRODUCT(($A$6:$A$400<>"")*ISNUMBER(SEARCH($A$6:$A$400,K10))*($G$6:$G$400<>"Completed"))=0,"✓ Ready","⏳ "&SUMPRODUCT(($A$6:$A$400<>"")*ISNUMBER(SEARCH($A$6:$A$400,K10))*($G$6:$G$400<>"Completed"))&" open")) -> ⏳ 1 open | Z10: =IF(A10="","",B10&"|"&COUNTIFS($B$6:B10,B10,$A$6:A10,"?*")) -> Phase 1|5 | AA10: =IF(OR(A10="",I10="",G10="Completed"),"",IF(I10>=StatusDate,I10+ROW()/100000,"")) -> 46307 | AB10: =IF(A10="","",IF(AND(G10<>"Completed",OR(G10="Blocked",AND(TRIM(P10)<>"",P10<>"None"))),ROW(),"")) | AC10: =IF(A10="","",IF(G10="Completed","Done",IF(G10="Blocked","Blocked",IF(X10="OVERDUE","Overdue",IF(AND(W10<>"",W10<=2),"Due soon",IF(AND(Y10<>"",LEFT(Y10,1)="⏳",G10<>"Not Started"),"Dependency open",IF(AND(S10<>"None",S10<>"",G10<>"Completed"),"External req.","On track"))))))) -> Due soon
A11: P1-06 | B11: Phase 1 | C11: Components | D11: Reusable template-part components | E11: template-parts/components: card-hero, card-large, card-medium, card-list, card-mini, section-header, post-meta, category-badge, pagination, ad-slot, empty-state. All accept $args via get_template_part() and escape output (esc_html/esc_url/esc_attr). | F11: P0 | G11: Not Started | H11: 46307 | I11: 46307 | J11: 0 | K11: P1-05 | L11: Staging (Hostinger) | M11: template-parts/components/*.php | N11: Render every component on a test page with real posts; test missing image/excerpt; check escaping | O11: Components reused by homepage and archives with no duplicated markup; all output escaped | S11: None | T11: Not Tested | U11: =IF(A11="",0,IF(G11="Completed",1,IF(G11="Not Started",0,MIN(0.99,N(J11))))) -> 0 | V11: =IF(OR(A11="",H11="",I11=""),0,MAX(0,MIN(1,(StatusDate-H11+1)/(I11-H11+1)))) -> 0 | W11: =IF(OR(A11="",I11="",G11="Completed"),"",I11-StatusDate) -> 1 | X11: =IF(A11="","",IF(AND(G11<>"Completed",I11<>"",I11<StatusDate),"OVERDUE","")) | Y11: =IF(OR(A11="",K11=""),"",IF(SUMPRODUCT(($A$6:$A$400<>"")*ISNUMBER(SEARCH($A$6:$A$400,K11))*($G$6:$G$400<>"Completed"))=0,"✓ Ready","⏳ "&SUMPRODUCT(($A$6:$A$400<>"")*ISNUMBER(SEARCH($A$6:$A$400,K11))*($G$6:$G$400<>"Completed"))&" open")) -> ⏳ 1 open | Z11: =IF(A11="","",B11&"|"&COUNTIFS($B$6:B11,B11,$A$6:A11,"?*")) -> Phase 1|6 | AA11: =IF(OR(A11="",I11="",G11="Completed"),"",IF(I11>=StatusDate,I11+ROW()/100000,"")) -> 46307 | AB11: =IF(A11="","",IF(AND(G11<>"Completed",OR(G11="Blocked",AND(TRIM(P11)<>"",P11<>"None"))),ROW(),"")) | AC11: =IF(A11="","",IF(G11="Completed","Done",IF(G11="Blocked","Blocked",IF(X11="OVERDUE","Overdue",IF(AND(W11<>"",W11<=2),"Due soon",IF(AND(Y11<>"",LEFT(Y11,1)="⏳",G11<>"Not Started"),"Dependency open",IF(AND(S11<>"None",S11<>"",G11<>"Completed"),"External req.","On track"))))))) -> Due soon
A12: P1-07 | B12: Phase 1 | C12: CSS Architecture | D12: CSS architecture & design tokens | E12: assets/css: tokens.css (colors, spacing, type scale as custom properties), base, layout, components, utilities, templates. Use CSS logical properties for native RTL. No CSS framework. Minification delegated to LiteSpeed (no local build tooling). | F12: P0 | G12: Not Started | H12: 46307 | I12: 46308 | J12: 0 | K12: P1-04 | L12: Staging (Hostinger) | M12: assets/css/tokens.css, base.css, layout.css, components.css, utilities.css | N12: Inspect computed styles use tokens; RTL correct without separate override file; CSS size checked | O12: Single token source; consistent styling; total CSS within agreed budget (target < 100 KB uncompressed) | S12: None | T12: Not Tested | U12: =IF(A12="",0,IF(G12="Completed",1,IF(G12="Not Started",0,MIN(0.99,N(J12))))) -> 0 | V12: =IF(OR(A12="",H12="",I12=""),0,MAX(0,MIN(1,(StatusDate-H12+1)/(I12-H12+1)))) -> 0 | W12: =IF(OR(A12="",I12="",G12="Completed"),"",I12-StatusDate) -> 2 | X12: =IF(A12="","",IF(AND(G12<>"Completed",I12<>"",I12<StatusDate),"OVERDUE","")) | Y12: =IF(OR(A12="",K12=""),"",IF(SUMPRODUCT(($A$6:$A$400<>"")*ISNUMBER(SEARCH($A$6:$A$400,K12))*($G$6:$G$400<>"Completed"))=0,"✓ Ready","⏳ "&SUMPRODUCT(($A$6:$A$400<>"")*ISNUMBER(SEARCH($A$6:$A$400,K12))*($G$6:$G$400<>"Completed"))&" open")) -> ⏳ 1 open | Z12: =IF(A12="","",B12&"|"&COUNTIFS($B$6:B12,B12,$A$6:A12,"?*")) -> Phase 1|7 | AA12: =IF(OR(A12="",I12="",G12="Completed"),"",IF(I12>=StatusDate,I12+ROW()/100000,"")) -> 46308 | AB12: =IF(A12="","",IF(AND(G12<>"Completed",OR(G12="Blocked",AND(TRIM(P12)<>"",P12<>"None"))),ROW(),"")) | AC12: =IF(A12="","",IF(G12="Completed","Done",IF(G12="Blocked","Blocked",IF(X12="OVERDUE","Overdue",IF(AND(W12<>"",W12<=2),"Due soon",IF(AND(Y12<>"",LEFT(Y12,1)="⏳",G12<>"Not Started"),"Dependency open",IF(AND(S12<>"None",S12<>"",G12<>"Completed"),"External req.","On track"))))))) -> Due soon
A13: P1-08 | B13: Phase 1 | C13: Vanilla JS | D13: Vanilla JS module architecture | E13: assets/js/main.js bootstraps data-attribute driven modules (nav, drawer, search overlay, sticky header); IntersectionObserver utilities; respects prefers-reduced-motion; no jQuery. | F13: P0 | G13: Not Started | H13: 46308 | I13: 46308 | J13: 0 | K13: P1-04 | L13: Staging (Hostinger) | M13: assets/js/main.js, assets/js/modules/*.js | N13: Console clean on Chrome & Safari; page usable with JS disabled | O13: All interactions implemented in Vanilla JS; zero console errors; scripts deferred | S13: None | T13: Not Tested | U13: =IF(A13="",0,IF(G13="Completed",1,IF(G13="Not Started",0,MIN(0.99,N(J13))))) -> 0 | V13: =IF(OR(A13="",H13="",I13=""),0,MAX(0,MIN(1,(StatusDate-H13+1)/(I13-H13+1)))) -> 0 | W13: =IF(OR(A13="",I13="",G13="Completed"),"",I13-StatusDate) -> 2 | X13: =IF(A13="","",IF(AND(G13<>"Completed",I13<>"",I13<StatusDate),"OVERDUE","")) | Y13: =IF(OR(A13="",K13=""),"",IF(SUMPRODUCT(($A$6:$A$400<>"")*ISNUMBER(SEARCH($A$6:$A$400,K13))*($G$6:$G$400<>"Completed"))=0,"✓ Ready","⏳ "&SUMPRODUCT(($A$6:$A$400<>"")*ISNUMBER(SEARCH($A$6:$A$400,K13))*($G$6:$G$400<>"Completed"))&" open")) -> ⏳ 1 open | Z13: =IF(A13="","",B13&"|"&COUNTIFS($B$6:B13,B13,$A$6:A13,"?*")) -> Phase 1|8 | AA13: =IF(OR(A13="",I13="",G13="Completed"),"",IF(I13>=StatusDate,I13+ROW()/100000,"")) -> 46308 | AB13: =IF(A13="","",IF(AND(G13<>"Completed",OR(G13="Blocked",AND(TRIM(P13)<>"",P13<>"None"))),ROW(),"")) | AC13: =IF(A13="","",IF(G13="Completed","Done",IF(G13="Blocked","Blocked",IF(X13="OVERDUE","Overdue",IF(AND(W13<>"",W13<=2),"Due soon",IF(AND(Y13<>"",LEFT(Y13,1)="⏳",G13<>"Not Started"),"Dependency open",IF(AND(S13<>"None",S13<>"",G13<>"Completed"),"External req.","On track"))))))) -> Due soon
A14: P1-09 | B14: Phase 1 | C14: RTL Typography | D14: RTL layout & Arabic typography | E14: html dir='rtl' lang='ar'; self-hosted Arabic WOFF2 fonts (font-display: swap, subset); Arabic-appropriate line-height & type scale; bidi isolation for mixed Arabic/English strings; numerals policy. | F14: P0 | G14: Not Started | H14: 46308 | I14: 46308 | J14: 0 | K14: P1-07 | L14: Staging (Hostinger) | M14: assets/fonts/*, assets/css/base.css, header.php | N14: Headlines/body render in Arabic font on iOS, Android, desktop; no invisible text flash; mixed strings align | O14: Correct RTL direction site-wide; fonts self-hosted; no layout shift from font swap | S14: None | T14: Not Tested | U14: =IF(A14="",0,IF(G14="Completed",1,IF(G14="Not Started",0,MIN(0.99,N(J14))))) -> 0 | V14: =IF(OR(A14="",H14="",I14=""),0,MAX(0,MIN(1,(StatusDate-H14+1)/(I14-H14+1)))) -> 0 | W14: =IF(OR(A14="",I14="",G14="Completed"),"",I14-StatusDate) -> 2 | X14: =IF(A14="","",IF(AND(G14<>"Completed",I14<>"",I14<StatusDate),"OVERDUE","")) | Y14: =IF(OR(A14="",K14=""),"",IF(SUMPRODUCT(($A$6:$A$400<>"")*ISNUMBER(SEARCH($A$6:$A$400,K14))*($G$6:$G$400<>"Completed"))=0,"✓ Ready","⏳ "&SUMPRODUCT(($A$6:$A$400<>"")*ISNUMBER(SEARCH($A$6:$A$400,K14))*($G$6:$G$400<>"Completed"))&" open")) -> ⏳ 1 open | Z14: =IF(A14="","",B14&"|"&COUNTIFS($B$6:B14,B14,$A$6:A14,"?*")) -> Phase 1|9 | AA14: =IF(OR(A14="",I14="",G14="Completed"),"",IF(I14>=StatusDate,I14+ROW()/100000,"")) -> 46308 | AB14: =IF(A14="","",IF(AND(G14<>"Completed",OR(G14="Blocked",AND(TRIM(P14)<>"",P14<>"None"))),ROW(),"")) | AC14: =IF(A14="","",IF(G14="Completed","Done",IF(G14="Blocked","Blocked",IF(X14="OVERDUE","Overdue",IF(AND(W14<>"",W14<=2),"Due soon",IF(AND(Y14<>"",LEFT(Y14,1)="⏳",G14<>"Not Started"),"Dependency open",IF(AND(S14<>"None",S14<>"",G14<>"Completed"),"External req.","On track"))))))) -> Due soon
A15: P1-10 | B15: Phase 1 | C15: Responsive Design | D15: Responsive grid & breakpoints | E15: Mobile-first container and CSS grid; breakpoints 360/576/768/1024/1280+; fluid type with clamp(); responsive images with srcset/sizes. | F15: P0 | G15: Not Started | H15: 46308 | I15: 46308 | J15: 0 | K15: P1-07 | L15: Staging (Hostinger) | M15: assets/css/layout.css | N15: Test 360, 414, 768, 1024, 1440 px widths; no horizontal scroll | O15: All layouts usable at 360 px; no overflow; correctly sized images | S15: None | T15: Not Tested | U15: =IF(A15="",0,IF(G15="Completed",1,IF(G15="Not Started",0,MIN(0.99,N(J15))))) -> 0 | V15: =IF(OR(A15="",H15="",I15=""),0,MAX(0,MIN(1,(StatusDate-H15+1)/(I15-H15+1)))) -> 0 | W15: =IF(OR(A15="",I15="",G15="Completed"),"",I15-StatusDate) -> 2 | X15: =IF(A15="","",IF(AND(G15<>"Completed",I15<>"",I15<StatusDate),"OVERDUE","")) | Y15: =IF(OR(A15="",K15=""),"",IF(SUMPRODUCT(($A$6:$A$400<>"")*ISNUMBER(SEARCH($A$6:$A$400,K15))*($G$6:$G$400<>"Completed"))=0,"✓ Ready","⏳ "&SUMPRODUCT(($A$6:$A$400<>"")*ISNUMBER(SEARCH($A$6:$A$400,K15))*($G$6:$G$400<>"Completed"))&" open")) -> ⏳ 1 open | Z15: =IF(A15="","",B15&"|"&COUNTIFS($B$6:B15,B15,$A$6:A15,"?*")) -> Phase 1|10 | AA15: =IF(OR(A15="",I15="",G15="Completed"),"",IF(I15>=StatusDate,I15+ROW()/100000,"")) -> 46308 | AB15: =IF(A15="","",IF(AND(G15<>"Completed",OR(G15="Blocked",AND(TRIM(P15)<>"",P15<>"None"))),ROW(),"")) | AC15: =IF(A15="","",IF(G15="Completed","Done",IF(G15="Blocked","Blocked",IF(X15="OVERDUE","Overdue",IF(AND(W15<>"",W15<=2),"Due soon",IF(AND(Y15<>"",LEFT(Y15,1)="⏳",G15<>"Not Started"),"Dependency open",IF(AND(S15<>"None",S15<>"",G15<>"Completed"),"External req.","On track"))))))) -> Due soon
A16: P1-11 | B16: Phase 1 | C16: Header & Navigation | D16: Header, navigation, mobile drawer & search | E16: Top bar with Arabic date, custom logo, primary menu with dropdowns, off-canvas mobile drawer, search overlay, sticky header; keyboard and screen-reader accessible. | F16: P0 | G16: Not Started | H16: 46308 | I16: 46309 | J16: 0 | K16: P1-06, P1-08, P1-15 | L16: Staging (Hostinger) | M16: header.php, template-parts/header/*.php, assets/js/modules/nav.js | N16: Drawer opens/closes, Esc closes, focus trapped; search submits; menu edited in WP admin updates header | O16: Navigation works on touch and keyboard; fully managed from WordPress menus | S16: None | T16: Not Tested | U16: =IF(A16="",0,IF(G16="Completed",1,IF(G16="Not Started",0,MIN(0.99,N(J16))))) -> 0 | V16: =IF(OR(A16="",H16="",I16=""),0,MAX(0,MIN(1,(StatusDate-H16+1)/(I16-H16+1)))) -> 0 | W16: =IF(OR(A16="",I16="",G16="Completed"),"",I16-StatusDate) -> 3 | X16: =IF(A16="","",IF(AND(G16<>"Completed",I16<>"",I16<StatusDate),"OVERDUE","")) | Y16: =IF(OR(A16="",K16=""),"",IF(SUMPRODUCT(($A$6:$A$400<>"")*ISNUMBER(SEARCH($A$6:$A$400,K16))*($G$6:$G$400<>"Completed"))=0,"✓ Ready","⏳ "&SUMPRODUCT(($A$6:$A$400<>"")*ISNUMBER(SEARCH($A$6:$A$400,K16))*($G$6:$G$400<>"Completed"))&" open")) -> ⏳ 3 open | Z16: =IF(A16="","",B16&"|"&COUNTIFS($B$6:B16,B16,$A$6:A16,"?*")) -> Phase 1|11 | AA16: =IF(OR(A16="",I16="",G16="Completed"),"",IF(I16>=StatusDate,I16+ROW()/100000,"")) -> 46309 | AB16: =IF(A16="","",IF(AND(G16<>"Completed",OR(G16="Blocked",AND(TRIM(P16)<>"",P16<>"None"))),ROW(),"")) | AC16: =IF(A16="","",IF(G16="Completed","Done",IF(G16="Blocked","Blocked",IF(X16="OVERDUE","Overdue",IF(AND(W16<>"",W16<=2),"Due soon",IF(AND(Y16<>"",LEFT(Y16,1)="⏳",G16<>"Not Started"),"Dependency open",IF(AND(S16<>"None",S16<>"",G16<>"Completed"),"External req.","On track"))))))) -> On track
A17: P1-12 | B17: Phase 1 | C17: Footer | D17: Footer with editable menus & social links | E17: Footer menus, social links via Customizer, newsletter/CTA slot, copyright, back-to-top. | F17: P1 | G17: Not Started | H17: 46309 | I17: 46309 | J17: 0 | K17: P1-06 | L17: Staging (Hostinger) | M17: footer.php, template-parts/footer/*.php | N17: All links resolve; social URLs editable in Customizer | O17: Footer content editable without code | S17: None | T17: Not Tested | U17: =IF(A17="",0,IF(G17="Completed",1,IF(G17="Not Started",0,MIN(0.99,N(J17))))) -> 0 | V17: =IF(OR(A17="",H17="",I17=""),0,MAX(0,MIN(1,(StatusDate-H17+1)/(I17-H17+1)))) -> 0 | W17: =IF(OR(A17="",I17="",G17="Completed"),"",I17-StatusDate) -> 3 | X17: =IF(A17="","",IF(AND(G17<>"Completed",I17<>"",I17<StatusDate),"OVERDUE","")) | Y17: =IF(OR(A17="",K17=""),"",IF(SUMPRODUCT(($A$6:$A$400<>"")*ISNUMBER(SEARCH($A$6:$A$400,K17))*($G$6:$G$400<>"Completed"))=0,"✓ Ready","⏳ "&SUMPRODUCT(($A$6:$A$400<>"")*ISNUMBER(SEARCH($A$6:$A$400,K17))*($G$6:$G$400<>"Completed"))&" open")) -> ⏳ 1 open | Z17: =IF(A17="","",B17&"|"&COUNTIFS($B$6:B17,B17,$A$6:A17,"?*")) -> Phase 1|12 | AA17: =IF(OR(A17="",I17="",G17="Completed"),"",IF(I17>=StatusDate,I17+ROW()/100000,"")) -> 46309 | AB17: =IF(A17="","",IF(AND(G17<>"Completed",OR(G17="Blocked",AND(TRIM(P17)<>"",P17<>"None"))),ROW(),"")) | AC17: =IF(A17="","",IF(G17="Completed","Done",IF(G17="Blocked","Blocked",IF(X17="OVERDUE","Overdue",IF(AND(W17<>"",W17<=2),"Due soon",IF(AND(Y17<>"",LEFT(Y17,1)="⏳",G17<>"Not Started"),"Dependency open",IF(AND(S17<>"None",S17<>"",G17<>"Completed"),"External req.","On track"))))))) -> On track
... A64: P4-02 | B64: Phase 4 | C64: CPT Engine | D64: Issue fields: number, date, year, decade, PDF, access | E64: Meta fields: issue number, publication month/year, year & decade (auto-derived), PDF attachment, page count, access level (free / members / subscribers), featured articles. | F64: P0 | G64: Not Started | H64: 46316 | I64: 46316 | J64: 0 | K64: P4-01 | L64: Staging (Hostinger) | M64: inc/issue-meta.php | N64: Save issue; decade auto-calculates; invalid values rejected | O64: All issue metadata editable and validated | S64: None | T64: Not Tested | U64: =IF(A64="",0,IF(G64="Completed",1,IF(G64="Not Started",0,MIN(0.99,N(J64))))) -> 0 | V64: =IF(OR(A64="",H64="",I64=""),0,MAX(0,MIN(1,(StatusDate-H64+1)/(I64-H64+1)))) -> 0 | W64: =IF(OR(A64="",I64="",G64="Completed"),"",I64-StatusDate) -> 10 | X64: =IF(A64="","",IF(AND(G64<>"Completed",I64<>"",I64<StatusDate),"OVERDUE","")) | Y64: =IF(OR(A64="",K64=""),"",IF(SUMPRODUCT(($A$6:$A$400<>"")*ISNUMBER(SEARCH($A$6:$A$400,K64))*($G$6:$G$400<>"Completed"))=0,"✓ Ready","⏳ "&SUMPRODUCT(($A$6:$A$400<>"")*ISNUMBER(SEARCH($A$6:$A$400,K64))*($G$6:$G$400<>"Completed"))&" open")) -> ⏳ 1 open | Z64: =IF(A64="","",B64&"|"&COUNTIFS($B$6:B64,B64,$A$6:A64,"?*")) -> Phase 4|2 | AA64: =IF(OR(A64="",I64="",G64="Completed"),"",IF(I64>=StatusDate,I64+ROW()/100000,"")) -> 46316.001 | AB64: =IF(A64="","",IF(AND(G64<>"Completed",OR(G64="Blocked",AND(TRIM(P64)<>"",P64<>"None"))),ROW(),"")) | AC64: =IF(A64="","",IF(G64="Completed","Done",IF(G64="Blocked","Blocked",IF(X64="OVERDUE","Overdue",IF(AND(W64<>"",W64<=2),"Due soon",IF(AND(Y64<>"",LEFT(Y64,1)="⏳",G64<>"Not Started"),"Dependency open",IF(AND(S64<>"None",S64<>"",G64<>"Completed"),"External req.","On track"))))))) -> On track
A65: P4-03 | B65: Phase 4 | C65: Historical Assets | D65: Collect 48 historical issue PDFs, covers & manifest | E65: Request from client: all 48 PDFs, cover images and a manifest (issue number, date, title). Track missing items. | F65: P0 | G65: Not Started | H65: 46307 | I65: 46315 | J65: 0 | L65: External / Third-party | M65: url: shared drive | N65: Count received files = 48 PDFs + 48 covers; manifest complete | O65: All historical assets received and checked | S65: Historical Assets | T65: Not Tested | U65: =IF(A65="",0,IF(G65="Completed",1,IF(G65="Not Started",0,MIN(0.99,N(J65))))) -> 0 | V65: =IF(OR(A65="",H65="",I65=""),0,MAX(0,MIN(1,(StatusDate-H65+1)/(I65-H65+1)))) -> 0 | W65: =IF(OR(A65="",I65="",G65="Completed"),"",I65-StatusDate) -> 9 | X65: =IF(A65="","",IF(AND(G65<>"Completed",I65<>"",I65<StatusDate),"OVERDUE","")) | Y65: =IF(OR(A65="",K65=""),"",IF(SUMPRODUCT(($A$6:$A$400<>"")*ISNUMBER(SEARCH($A$6:$A$400,K65))*($G$6:$G$400<>"Completed"))=0,"✓ Ready","⏳ "&SUMPRODUCT(($A$6:$A$400<>"")*ISNUMBER(SEARCH($A$6:$A$400,K65))*($G$6:$G$400<>"Completed"))&" open")) | Z65: =IF(A65="","",B65&"|"&COUNTIFS($B$6:B65,B65,$A$6:A65,"?*")) -> Phase 4|3 | AA65: =IF(OR(A65="",I65="",G65="Completed"),"",IF(I65>=StatusDate,I65+ROW()/100000,"")) -> 46315.001 | AB65: =IF(A65="","",IF(AND(G65<>"Completed",OR(G65="Blocked",AND(TRIM(P65)<>"",P65<>"None"))),ROW(),"")) | AC65: =IF(A65="","",IF(G65="Completed","Done",IF(G65="Blocked","Blocked",IF(X65="OVERDUE","Overdue",IF(AND(W65<>"",W65<=2),"Due soon",IF(AND(Y65<>"",LEFT(Y65,1)="⏳",G65<>"Not Started"),"Dependency open",IF(AND(S65<>"None",S65<>"",G65<>"Completed"),"External req.","On track"))))))) -> External req.
A66: P4-04 | B66: Phase 4 | C66: Migration | D66: Historical issue migration (import 48 issues) | E66: CSV manifest + idempotent importer (WP-CLI via Hostinger SSH or one-time admin tool) creating issues, attaching covers and PDFs; re-runnable without duplicates. | F66: P0 | G66: Not Started | H66: 46316 | I66: 46316 | J66: 0 | K66: P4-02, P4-03 | L66: Staging (Hostinger) | M66: inc/issue-import.php, issues-manifest.csv | N66: Run import twice; still 48 issues; spot-check 10 | O66: All 48 issues imported with correct metadata, covers and PDFs | S66: Server Access | T66: Not Tested | U66: =IF(A66="",0,IF(G66="Completed",1,IF(G66="Not Started",0,MIN(0.99,N(J66))))) -> 0 | V66: =IF(OR(A66="",H66="",I66=""),0,MAX(0,MIN(1,(StatusDate-H66+1)/(I66-H66+1)))) -> 0 | W66: =IF(OR(A66="",I66="",G66="Completed"),"",I66-StatusDate) -> 10 | X66: =IF(A66="","",IF(AND(G66<>"Completed",I66<>"",I66<StatusDate),"OVERDUE","")) | Y66: =IF(OR(A66="",K66=""),"",IF(SUMPRODUCT(($A$6:$A$400<>"")*ISNUMBER(SEARCH($A$6:$A$400,K66))*($G$6:$G$400<>"Completed"))=0,"✓ Ready","⏳ "&SUMPRODUCT(($A$6:$A$400<>"")*ISNUMBER(SEARCH($A$6:$A$400,K66))*($G$6:$G$400<>"Completed"))&" open")) -> ⏳ 2 open | Z66: =IF(A66="","",B66&"|"&COUNTIFS($B$6:B66,B66,$A$6:A66,"?*")) -> Phase 4|4 | AA66: =IF(OR(A66="",I66="",G66="Completed"),"",IF(I66>=StatusDate,I66+ROW()/100000,"")) -> 46316.001 | AB66: =IF(A66="","",IF(AND(G66<>"Completed",OR(G66="Blocked",AND(TRIM(P66)<>"",P66<>"None"))),ROW(),"")) | AC66: =IF(A66="","",IF(G66="Completed","Done",IF(G66="Blocked","Blocked",IF(X66="OVERDUE","Overdue",IF(AND(W66<>"",W66<=2),"Due soon",IF(AND(Y66<>"",LEFT(Y66,1)="⏳",G66<>"Not Started"),"Dependency open",IF(AND(S66<>"None",S66<>"",G66<>"Completed"),"External req.","On track"))))))) -> External req.
A67: P4-05 | B67: Phase 4 | C67: Cover Images | D67: Cover image optimization | E67: Generate WebP and required sizes for covers; consistent aspect ratio. | F67: P1 | G67: Not Started | H67: 46316 | I67: 46316 | J67: 0 | K67: P4-04 | L67: Staging (Hostinger) | M67: inc/media.php | N67: Check archive weight and image dimensions | O67: Covers sharp and lightweight | S67: None | T67: Not Tested | U67: =IF(A67="",0,IF(G67="Completed",1,IF(G67="Not Started",0,MIN(0.99,N(J67))))) -> 0 | V67: =IF(OR(A67="",H67="",I67=""),0,MAX(0,MIN(1,(StatusDate-H67+1)/(I67-H67+1)))) -> 0 | W67: =IF(OR(A67="",I67="",G67="Completed"),"",I67-StatusDate) -> 10 | X67: =IF(A67="","",IF(AND(G67<>"Completed",I67<>"",I67<StatusDate),"OVERDUE","")) | Y67: =IF(OR(A67="",K67=""),"",IF(SUMPRODUCT(($A$6:$A$400<>"")*ISNUMBER(SEARCH($A$6:$A$400,K67))*($G$6:$G$400<>"Completed"))=0,"✓ Ready","⏳ "&SUMPRODUCT(($A$6:$A$400<>"")*ISNUMBER(SEARCH($A$6:$A$400,K67))*($G$6:$G$400<>"Completed"))&" open")) -> ⏳ 1 open | Z67: =IF(A67="","",B67&"|"&COUNTIFS($B$6:B67,B67,$A$6:A67,"?*")) -> Phase 4|5 | AA67: =IF(OR(A67="",I67="",G67="Completed"),"",IF(I67>=StatusDate,I67+ROW()/100000,"")) -> 46316.001 | AB67: =IF(A67="","",IF(AND(G67<>"Completed",OR(G67="Blocked",AND(TRIM(P67)<>"",P67<>"None"))),ROW(),"")) | AC67: =IF(A67="","",IF(G67="Completed","Done",IF(G67="Blocked","Blocked",IF(X67="OVERDUE","Overdue",IF(AND(W67<>"",W67<=2),"Due soon",IF(AND(Y67<>"",LEFT(Y67,1)="⏳",G67<>"Not Started"),"Dependency open",IF(AND(S67<>"None",S67<>"",G67<>"Completed"),"External req.","On track"))))))) -> On track
A68: P4-06 | B68: Phase 4 | C68: Issue Archive | D68: Issue archive template | E68: archive-magazine_issue.php: cover grid, newest first, issue number/date, pagination. | F68: P0 | G68: Not Started | H68: 46316 | I68: 46316 | J68: 0 | K68: P4-01 | L68: Staging (Hostinger) | M68: archive-magazine_issue.php, template-parts/issue/card.php | N68: Open archive; check ordering and pagination | O68: Archive lists all issues correctly | S68: None | T68: Not Tested | U68: =IF(A68="",0,IF(G68="Completed",1,IF(G68="Not Started",0,MIN(0.99,N(J68))))) -> 0 | V68: =IF(OR(A68="",H68="",I68=""),0,MAX(0,MIN(1,(StatusDate-H68+1)/(I68-H68+1)))) -> 0 | W68: =IF(OR(A68="",I68="",G68="Completed"),"",I68-StatusDate) -> 10 | X68: =IF(A68="","",IF(AND(G68<>"Completed",I68<>"",I68<StatusDate),"OVERDUE","")) | Y68: =IF(OR(A68="",K68=""),"",IF(SUMPRODUCT(($A$6:$A$400<>"")*ISNUMBER(SEARCH($A$6:$A$400,K68))*($G$6:$G$400<>"Completed"))=0,"✓ Ready","⏳ "&SUMPRODUCT(($A$6:$A$400<>"")*ISNUMBER(SEARCH($A$6:$A$400,K68))*($G$6:$G$400<>"Completed"))&" open")) -> ⏳ 1 open | Z68: =IF(A68="","",B68&"|"&COUNTIFS($B$6:B68,B68,$A$6:A68,"?*")) -> Phase 4|6 | AA68: =IF(OR(A68="",I68="",G68="Completed"),"",IF(I68>=StatusDate,I68+ROW()/100000,"")) -> 46316.001 | AB68: =IF(A68="","",IF(AND(G68<>"Completed",OR(G68="Blocked",AND(TRIM(P68)<>"",P68<>"None"))),ROW(),"")) | AC68: =IF(A68="","",IF(G68="Completed","Done",IF(G68="Blocked","Blocked",IF(X68="OVERDUE","Overdue",IF(AND(W68<>"",W68<=2),"Due soon",IF(AND(Y68<>"",LEFT(Y68,1)="⏳",G68<>"Not Started"),"Dependency open",IF(AND(S68<>"None",S68<>"",G68<>"Completed"),"External req.","On track"))))))) -> On track
A69: P4-07 | B69: Phase 4 | C69: Issue Archive | D69: Year & decade filtering | E69: Filter issues by decade then year (query vars + optional AJAX), crawlable URLs. | F69: P1 | G69: Not Started | H69: 46316 | I69: 46316 | J69: 0 | K69: P4-06 | L69: Staging (Hostinger) | M69: archive-magazine_issue.php, assets/js/modules/issue-filter.js | N69: Filter each decade/year; counts match manifest | O69: Filters return correct issues | S69: None | T69: Not Tested | U69: =IF(A69="",0,IF(G69="Completed",1,IF(G69="Not Started",0,MIN(0.99,N(J69))))) -> 0 | V69: =IF(OR(A69="",H69="",I69=""),0,MAX(0,MIN(1,(StatusDate-H69+1)/(I69-H69+1)))) -> 0 | W69: =IF(OR(A69="",I69="",G69="Completed"),"",I69-StatusDate) -> 10 | X69: =IF(A69="","",IF(AND(G69<>"Completed",I69<>"",I69<StatusDate),"OVERDUE","")) | Y69: =IF(OR(A69="",K69=""),"",IF(SUMPRODUCT(($A$6:$A$400<>"")*ISNUMBER(SEARCH($A$6:$A$400,K69))*($G$6:$G$400<>"Completed"))=0,"✓ Ready","⏳ "&SUMPRODUCT(($A$6:$A$400<>"")*ISNUMBER(SEARCH($A$6:$A$400,K69))*($G$6:$G$400<>"Completed"))&" open")) -> ⏳ 1 open | Z69: =IF(A69="","",B69&"|"&COUNTIFS($B$6:B69,B69,$A$6:A69,"?*")) -> Phase 4|7 | AA69: =IF(OR(A69="",I69="",G69="Completed"),"",IF(I69>=StatusDate,I69+ROW()/100000,"")) -> 46316.001 | AB69: =IF(A69="","",IF(AND(G69<>"Completed",OR(G69="Blocked",AND(TRIM(P69)<>"",P69<>"None"))),ROW(),"")) | AC69: =IF(A69="","",IF(G69="Completed","Done",IF(G69="Blocked","Blocked",IF(X69="OVERDUE","Overdue",IF(AND(W69<>"",W69<=2),"Due soon",IF(AND(Y69<>"",LEFT(Y69,1)="⏳",G69<>"Not Started"),"Dependency open",IF(AND(S69<>"None",S69<>"",G69<>"Completed"),"External req.","On track"))))))) -> On track
A70: P4-08 | B70: Phase 4 | C70: Single Issue | D70: Single issue page | E70: single-magazine_issue.php: large cover, issue details, highlights/table of contents, read & download actions, previous/next issue. | F70: P0 | G70: Not Started | H70: 46317 | I70: 46317 | J70: 0 | K70: P4-02 | L70: Staging (Hostinger) | M70: single-magazine_issue.php | N70: Open 5 issues incl. oldest and newest | O70: Single issue page complete for every issue | S70: None | T70: Not Tested | U70: =IF(A70="",0,IF(G70="Completed",1,IF(G70="Not Started",0,MIN(0.99,N(J70))))) -> 0 | V70: =IF(OR(A70="",H70="",I70=""),0,MAX(0,MIN(1,(StatusDate-H70+1)/(I70-H70+1)))) -> 0 | W70: =IF(OR(A70="",I70="",G70="Completed"),"",I70-StatusDate) -> 11 | X70: =IF(A70="","",IF(AND(G70<>"Completed",I70<>"",I70<StatusDate),"OVERDUE","")) | Y70: =IF(OR(A70="",K70=""),"",IF(SUMPRODUCT(($A$6:$A$400<>"")*ISNUMBER(SEARCH($A$6:$A$400,K70))*($G$6:$G$400<>"Completed"))=0,"✓ Ready","⏳ "&SUMPRODUCT(($A$6:$A$400<>"")*ISNUMBER(SEARCH($A$6:$A$400,K70))*($G$6:$G$400<>"Completed"))&" open")) -> ⏳ 1 open | Z70: =IF(A70="","",B70&"|"&COUNTIFS($B$6:B70,B70,$A$6:A70,"?*")) -> Phase 4|8 | AA70: =IF(OR(A70="",I70="",G70="Completed"),"",IF(I70>=StatusDate,I70+ROW()/100000,"")) -> 46317.001 | AB70: =IF(A70="","",IF(AND(G70<>"Completed",OR(G70="Blocked",AND(TRIM(P70)<>"",P70<>"None"))),ROW(),"")) | AC70: =IF(A70="","",IF(G70="Completed","Done",IF(G70="Blocked","Blocked",IF(X70="OVERDUE","Overdue",IF(AND(W70<>"",W70<=2),"Due soon",IF(AND(Y70<>"",LEFT(Y70,1)="⏳",G70<>"Not Started"),"Dependency open",IF(AND(S70<>"None",S70<>"",G70<>"Completed"),"External req.","On track"))))))) -> On track
A71: P4-09 | B71: Phase 4 | C71: Flipbook | D71: Flipbook reader | E71: Self-hosted PDF.js based flipbook, lazy-loaded only on issue pages, page navigation, zoom, fullscreen; mobile fallback to scroll view. | F71: P1 | G71: Not Started | H71: 46317 | I71: 46317 | J71: 0 | K71: P4-08 | L71: Staging (Hostinger) | M71: assets/js/modules/flipbook.js, assets/vendor/pdfjs/* | N71: Open large PDF on mobile & desktop; measure load time | O71: Readable flipbook on desktop & mobile without blocking page load | S71: None | T71: Not Tested | U71: =IF(A71="",0,IF(G71="Completed",1,IF(G71="Not Started",0,MIN(0.99,N(J71))))) -> 0 | V71: =IF(OR(A71="",H71="",I71=""),0,MAX(0,MIN(1,(StatusDate-H71+1)/(I71-H71+1)))) -> 0 | W71: =IF(OR(A71="",I71="",G71="Completed"),"",I71-StatusDate) -> 11 | X71: =IF(A71="","",IF(AND(G71<>"Completed",I71<>"",I71<StatusDate),"OVERDUE","")) | Y71: =IF(OR(A71="",K71=""),"",IF(SUMPRODUCT(($A$6:$A$400<>"")*ISNUMBER(SEARCH($A$6:$A$400,K71))*($G$6:$G$400<>"Completed"))=0,"✓ Ready","⏳ "&SUMPRODUCT(($A$6:$A$400<>"")*ISNUMBER(SEARCH($A$6:$A$400,K71))*($G$6:$G$400<>"Completed"))&" open")) -> ⏳ 1 open | Z71: =IF(A71="","",B71&"|"&COUNTIFS($B$6:B71,B71,$A$6:A71,"?*")) -> Phase 4|9 | AA71: =IF(OR(A71="",I71="",G71="Completed"),"",IF(I71>=StatusDate,I71+ROW()/100000,"")) -> 46317.001 | AB71: =IF(A71="","",IF(AND(G71<>"Completed",OR(G71="Blocked",AND(TRIM(P71)<>"",P71<>"None"))),ROW(),"")) | AC71: =IF(A71="","",IF(G71="Completed","Done",IF(G71="Blocked","Blocked",IF(X71="OVERDUE","Overdue",IF(AND(W71<>"",W71<=2),"Due soon",IF(AND(Y71<>"",LEFT(Y71,1)="⏳",G71<>"Not Started"),"Dependency open",IF(AND(S71<>"None",S71<>"",G71<>"Completed"),"External req.","On track"))))))) -> On track
A72: P4-10 | B72: Phase 4 | C72: PDF Downloads | D72: Secure PDF downloads | E72: Download endpoint with nonce and access check, download counter, correct filename/headers. | F72: P0 | G72: Not Started | H72: 46317 | I72: 46317 | J72: 0 | K72: P4-08 | L72: Staging (Hostinger) | M72: inc/pdf-download.php | N72: Download as guest/member/subscriber; check headers | O72: Downloads work and respect access rules | S72: None | T72: Not Tested | U72: =IF(A72="",0,IF(G72="Completed",1,IF(G72="Not Started",0,MIN(0.99,N(J72))))) -> 0 | V72: =IF(OR(A72="",H72="",I72=""),0,MAX(0,MIN(1,(StatusDate-H72+1)/(I72-H72+1)))) -> 0 | W72: =IF(OR(A72="",I72="",G72="Completed"),"",I72-StatusDate) -> 11 | X72: =IF(A72="","",IF(AND(G72<>"Completed",I72<>"",I72<StatusDate),"OVERDUE","")) | Y72: =IF(OR(A72="",K72=""),"",IF(SUMPRODUCT(($A$6:$A$400<>"")*ISNUMBER(SEARCH($A$6:$A$400,K72))*($G$6:$G$400<>"Completed"))=0,"✓ Ready","⏳ "&SUMPRODUCT(($A$6:$A$400<>"")*ISNUMBER(SEARCH($A$6:$A$400,K72))*($G$6:$G$400<>"Completed"))&" open")) -> ⏳ 1 open | Z72: =IF(A72="","",B72&"|"&COUNTIFS($B$6:B72,B72,$A$6:A72,"?*")) -> Phase 4|10 | AA72: =IF(OR(A72="",I72="",G72="Completed"),"",IF(I72>=StatusDate,I72+ROW()/100000,"")) -> 46317.001 | AB72: =IF(A72="","",IF(AND(G72<>"Completed",OR(G72="Blocked",AND(TRIM(P72)<>"",P72<>"None"))),ROW(),"")) | AC72: =IF(A72="","",IF(G72="Completed","Done",IF(G72="Blocked","Blocked",IF(X72="OVERDUE","Overdue",IF(AND(W72<>"",W72<=2),"Due soon",IF(AND(Y72<>"",LEFT(Y72,1)="⏳",G72<>"Not Started"),"Dependency open",IF(AND(S72<>"None",S72<>"",G72<>"Completed"),"External req.","On track"))))))) -> On track
A73: P4-11 | B73: Phase 4 | C73: Access Control | D73: Issue access restrictions | E73: Gate reader and downloads by access level/subscription tier; block direct /uploads PDF access (.htaccess/LiteSpeed rule) or serve via PHP. | F73: P0 | G73: Not Started | H73: 46317 | I73: 46317 | J73: 0 | K73: P4-10, P5-07 | L73: Staging (Hostinger) | M73: inc/pdf-download.php, .htaccess | N73: Try direct PDF URL logged-out; test each tier | O73: Restricted PDFs cannot be accessed without entitlement | S73: Server Access | T73: Not Tested | U73: =IF(A73="",0,IF(G73="Completed",1,IF(G73="Not Started",0,MIN(0.99,N(J73))))) -> 0 | V73: =IF(OR(A73="",H73="",I73=""),0,MAX(0,MIN(1,(StatusDate-H73+1)/(I73-H73+1)))) -> 0 | W73: =IF(OR(A73="",I73="",G73="Completed"),"",I73-StatusDate) -> 11 | X73: =IF(A73="","",IF(AND(G73<>"Completed",I73<>"",I73<StatusDate),"OVERDUE","")) | Y73: =IF(OR(A73="",K73=""),"",IF(SUMPRODUCT(($A$6:$A$400<>"")*ISNUMBER(SEARCH($A$6:$A$400,K73))*($G$6:$G$400<>"Completed"))=0,"✓ Ready","⏳ "&SUMPRODUCT(($A$6:$A$400<>"")*ISNUMBER(SEARCH($A$6:$A$400,K73))*($G$6:$G$400<>"Completed"))&" open")) -> ⏳ 2 open | Z73: =IF(A73="","",B73&"|"&COUNTIFS($B$6:B73,B73,$A$6:A73,"?*")) -> Phase 4|11 | AA73: =IF(OR(A73="",I73="",G73="Completed"),"",IF(I73>=StatusDate,I73+ROW()/100000,"")) -> 46317.001 | AB73: =IF(A73="","",IF(AND(G73<>"Completed",OR(G73="Blocked",AND(TRIM(P73)<>"",P73<>"None"))),ROW(),"")) | AC73: =IF(A73="","",IF(G73="Completed","Done",IF(G73="Blocked","Blocked",IF(X73="OVERDUE","Overdue",IF(AND(W73<>"",W73<=2),"Due soon",IF(AND(Y73<>"",LEFT(Y73,1)="⏳",G73<>"Not Started"),"Dependency open",IF(AND(S73<>"None",S73<>"",G73<>"Completed"),"External req.","On track"))))))) -> External req.
A74: P4-12 | B74: Phase 4 | C74: Phase QA | D74: Verify all 48 issues | E74: Checklist pass: 48/48 issues present, cover, PDF opens, metadata correct, filters accurate. | F74: P0 | G74: Not Started | H74: 46317 | I74: 46317 | J74: 0 | K74: P4-04, P4-07, P4-09 | L74: Staging (Hostinger) | M74: issues-manifest.csv | N74: Tick all 48 against manifest | O74: 48/48 issues verified | S74: None | T74: Not Tested | U74: =IF(A74="",0,IF(G74="Completed",1,IF(G74="Not Started",0,MIN(0.99,N(J74))))) -> 0 | V74: =IF(OR(A74="",H74="",I74=""),0,MAX(0,MIN(1,(StatusDate-H74+1)/(I74-H74+1)))) -> 0 | W74: =IF(OR(A74="",I74="",G74="Completed"),"",I74-StatusDate) -> 11 | X74: =IF(A74="","",IF(AND(G74<>"Completed",I74<>"",I74<StatusDate),"OVERDUE","")) | Y74: =IF(OR(A74="",K74=""),"",IF(SUMPRODUCT(($A$6:$A$400<>"")*ISNUMBER(SEARCH($A$6:$A$400,K74))*($G$6:$G$400<>"Completed"))=0,"✓ Ready","⏳ "&SUMPRODUCT(($A$6:$A$400<>"")*ISNUMBER(SEARCH($A$6:$A$400,K74))*($G$6:$G$400<>"Completed"))&" open")) -> ⏳ 3 open | Z74: =IF(A74="","",B74&"|"&COUNTIFS($B$6:B74,B74,$A$6:A74,"?*")) -> Phase 4|12 | AA74: =IF(OR(A74="",I74="",G74="Completed"),"",IF(I74>=StatusDate,I74+ROW()/100000,"")) -> 46317.001 | AB74: =IF(A74="","",IF(AND(G74<>"Completed",OR(G74="Blocked",AND(TRIM(P74)<>"",P74<>"None"))),ROW(),"")) | AC74: =IF(A74="","",IF(G74="Completed","Done",IF(G74="Blocked","Blocked",IF(X74="OVERDUE","Overdue",IF(AND(W74<>"",W74<=2),"Due soon",IF(AND(Y74<>"",LEFT(Y74,1)="⏳",G74<>"Not Started"),"Dependency open",IF(AND(S74<>"None",S74<>"",G74<>"Completed"),"External req.","On track"))))))) -> On track
A75: P5-01 | B75: Phase 5 | C75: Credentials | D75: Request Google OAuth credentials | E75: Google Cloud project, OAuth consent screen, client ID/secret, authorised redirect URIs for staging and production. | F75: P1 | G75: Not Started | H75: 46307 | I75: 46315 | J75: 0 | L75: External / Third-party | M75: — | N75: Credentials received and stored securely (not in Git) | O75: Valid client ID/secret for both domains | S75: Credentials | T75: Not Tested | U75: =IF(A75="",0,IF(G75="Completed",1,IF(G75="Not Started",0,MIN(0.99,N(J75))))) -> 0 | V75: =IF(OR(A75="",H75="",I75=""),0,MAX(0,MIN(1,(StatusDate-H75+1)/(I75-H75+1)))) -> 0 | W75: =IF(OR(A75="",I75="",G75="Completed"),"",I75-StatusDate) -> 9 | X75: =IF(A75="","",IF(AND(G75<>"Completed",I75<>"",I75<StatusDate),"OVERDUE","")) | Y75: =IF(OR(A75="",K75=""),"",IF(SUMPRODUCT(($A$6:$A$400<>"")*ISNUMBER(SEARCH($A$6:$A$400,K75))*($G$6:$G$400<>"Completed"))=0,"✓ Ready","⏳ "&SUMPRODUCT(($A$6:$A$400<>"")*ISNUMBER(SEARCH($A$6:$A$400,K75))*($G$6:$G$400<>"Completed"))&" open")) | Z75: =IF(A75="","",B75&"|"&COUNTIFS($B$6:B75,B75,$A$6:A75,"?*")) -> Phase 5|1 | AA75: =IF(OR(A75="",I75="",G75="Completed"),"",IF(I75>=StatusDate,I75+ROW()/100000,"")) -> 46315.001 | AB75: =IF(A75="","",IF(AND(G75<>"Completed",OR(G75="Blocked",AND(TRIM(P75)<>"",P75<>"None"))),ROW(),"")) | AC75: =IF(A75="","",IF(G75="Completed","Done",IF(G75="Blocked","Blocked",IF(X75="OVERDUE","Overdue",IF(AND(W75<>"",W75<=2),"Due soon",IF(AND(Y75<>"",LEFT(Y75,1)="⏳",G75<>"Not Started"),"Dependency open",IF(AND(S75<>"None",S75<>"",G75<>"Completed"),"External req.","On track"))))))) -> External req.
A76: P5-02 | B76: Phase 5 | C76: Credentials | D76: Request Sign in with Apple credentials | E76: Apple Developer Program membership (client), Services ID, key, team ID, domain verification for both domains. | F76: P1 | G76: Not Started | H76: 46307 | I76: 46315 | J76: 0 | L76: External / Third-party | M76: — | N76: Credentials received; domain verification file placed | O76: Valid Apple credentials for both domains | S76: Credentials | T76: Not Tested | U76: =IF(A76="",0,IF(G76="Completed",1,IF(G76="Not Started",0,MIN(0.99,N(J76))))) -> 0 | V76: =IF(OR(A76="",H76="",I76=""),0,MAX(0,MIN(1,(StatusDate-H76+1)/(I76-H76+1)))) -> 0 | W76: =IF(OR(A76="",I76="",G76="Completed"),"",I76-StatusDate) -> 9 | X76: =IF(A76="","",IF(AND(G76<>"Completed",I76<>"",I76<StatusDate),"OVERDUE","")) | Y76: =IF(OR(A76="",K76=""),"",IF(SUMPRODUCT(($A$6:$A$400<>"")*ISNUMBER(SEARCH($A$6:$A$400,K76))*($G$6:$G$400<>"Completed"))=0,"✓ Ready","⏳ "&SUMPRODUCT(($A$6:$A$400<>"")*ISNUMBER(SEARCH($A$6:$A$400,K76))*($G$6:$G$400<>"Completed"))&" open")) | Z76: =IF(A76="","",B76&"|"&COUNTIFS($B$6:B76,B76,$A$6:A76,"?*")) -> Phase 5|2 | AA76: =IF(OR(A76="",I76="",G76="Completed"),"",IF(I76>=StatusDate,I76+ROW()/100000,"")) -> 46315.001 | AB76: =IF(A76="","",IF(AND(G76<>"Completed",OR(G76="Blocked",AND(TRIM(P76)<>"",P76<>"None"))),ROW(),"")) | AC76: =IF(A76="","",IF(G76="Completed","Done",IF(G76="Blocked","Blocked",IF(X76="OVERDUE","Overdue",IF(AND(W76<>"",W76<=2),"Due soon",IF(AND(Y76<>"",LEFT(Y76,1)="⏳",G76<>"Not Started"),"Dependency open",IF(AND(S76<>"None",S76<>"",G76<>"Completed"),"External req.","On track"))))))) -> External req.
A77: P5-03 | B77: Phase 5 | C77: Payments | D77: Confirm payment provider & obtain API keys | E77: Client confirms gateway; obtain sandbox + live API keys, webhook signing secret, merchant approval and supported currencies. | F77: P0 | G77: Not Started | H77: 46307 | I77: 46317 | J77: 0 | L77: External / Third-party | M77: — | N77: Sandbox transaction possible; live approval date known | O77: Sandbox keys in hand; live approval confirmed before cutover | S77: Payment Approval | T77: Not Tested | U77: =IF(A77="",0,IF(G77="Completed",1,IF(G77="Not Started",0,MIN(0.99,N(J77))))) -> 0 | V77: =IF(OR(A77="",H77="",I77=""),0,MAX(0,MIN(1,(StatusDate-H77+1)/(I77-H77+1)))) -> 0 | W77: =IF(OR(A77="",I77="",G77="Completed"),"",I77-StatusDate) -> 11 | X77: =IF(A77="","",IF(AND(G77<>"Completed",I77<>"",I77<StatusDate),"OVERDUE","")) | Y77: =IF(OR(A77="",K77=""),"",IF(SUMPRODUCT(($A$6:$A$400<>"")*ISNUMBER(SEARCH($A$6:$A$400,K77))*($G$6:$G$400<>"Completed"))=0,"✓ Ready","⏳ "&SUMPRODUCT(($A$6:$A$400<>"")*ISNUMBER(SEARCH($A$6:$A$400,K77))*($G$6:$G$400<>"Completed"))&" open")) | Z77: =IF(A77="","",B77&"|"&COUNTIFS($B$6:B77,B77,$A$6:A77,"?*")) -> Phase 5|3 | AA77: =IF(OR(A77="",I77="",G77="Completed"),"",IF(I77>=StatusDate,I77+ROW()/100000,"")) -> 46317.001 | AB77: =IF(A77="","",IF(AND(G77<>"Completed",OR(G77="Blocked",AND(TRIM(P77)<>"",P77<>"None"))),ROW(),"")) | AC77: =IF(A77="","",IF(G77="Completed","Done",IF(G77="Blocked","Blocked",IF(X77="OVERDUE","Overdue",IF(AND(W77<>"",W77<=2),"Due soon",IF(AND(Y77<>"",LEFT(Y77,1)="⏳",G77<>"Not Started"),"Dependency open",IF(AND(S77<>"None",S77<>"",G77<>"Completed"),"External req.","On track"))))))) -> External req.
A78: P5-04 | B78: Phase 5 | C78: Authentication | D78: Login, registration & password reset | E78: Custom templates using wp_signon/wp_insert_user; email verification; password reset flow; redirects; Arabic validation messages; wp-login.php styled fallback. | F78: P0 | G78: Not Started | H78: 46318 | I78: 46318 | J78: 0 | K78: P1-17 | L78: Staging (Hostinger) | M78: page-templates/page-login.php, page-register.php, page-reset.php, inc/auth/*.php | N78: Register, verify, log in, reset password, log out | O78: Complete account lifecycle works with clear Arabic messages | S78: None | T78: Not Tested | U78: =IF(A78="",0,IF(G78="Completed",1,IF(G78="Not Started",0,MIN(0.99,N(J78))))) -> 0 | V78: =IF(OR(A78="",H78="",I78=""),0,MAX(0,MIN(1,(StatusDate-H78+1)/(I78-H78+1)))) -> 0 | W78: =IF(OR(A78="",I78="",G78="Completed"),"",I78-StatusDate) -> 12 | X78: =IF(A78="","",IF(AND(G78<>"Completed",I78<>"",I78<StatusDate),"OVERDUE","")) | Y78: =IF(OR(A78="",K78=""),"",IF(SUMPRODUCT(($A$6:$A$400<>"")*ISNUMBER(SEARCH($A$6:$A$400,K78))*($G$6:$G$400<>"Completed"))=0,"✓ Ready","⏳ "&SUMPRODUCT(($A$6:$A$400<>"")*ISNUMBER(SEARCH($A$6:$A$400,K78))*($G$6:$G$400<>"Completed"))&" open")) -> ⏳ 1 open | Z78: =IF(A78="","",B78&"|"&COUNTIFS($B$6:B78,B78,$A$6:A78,"?*")) -> Phase 5|4 | AA78: =IF(OR(A78="",I78="",G78="Completed"),"",IF(I78>=StatusDate,I78+ROW()/100000,"")) -> 46318.001 | AB78: =IF(A78="","",IF(AND(G78<>"Completed",OR(G78="Blocked",AND(TRIM(P78)<>"",P78<>"None"))),ROW(),"")) | AC78: =IF(A78="","",IF(G78="Completed","Done",IF(G78="Blocked","Blocked",IF(X78="OVERDUE","Overdue",IF(AND(W78<>"",W78<=2),"Due soon",IF(AND(Y78<>"",LEFT(Y78,1)="⏳",G78<>"Not Started"),"Dependency open",IF(AND(S78<>"None",S78<>"",G78<>"Completed"),"External req.","On track"))))))) -> On track
A79: P5-05 | B79: Phase 5 | C79: Authentication | D79: Google sign-in | E79: OAuth 2.0 flow (state param, token verification), link to existing account by verified email. | F79: P1 | G79: Not Started | H79: 46318 | I79: 46318 | J79: 0 | K79: P5-01, P5-04 | L79: Staging (Hostinger) | M79: inc/auth/social-google.php | N79: New and existing user sign-in; cancel flow | O79: Google sign-in works on staging and is ready for production URIs | S79: Credentials | T79: Not Tested | U79: =IF(A79="",0,IF(G79="Completed",1,IF(G79="Not Started",0,MIN(0.99,N(J79))))) -> 0 | V79: =IF(OR(A79="",H79="",I79=""),0,MAX(0,MIN(1,(StatusDate-H79+1)/(I79-H79+1)))) -> 0 | W79: =IF(OR(A79="",I79="",G79="Completed"),"",I79-StatusDate) -> 12 | X79: =IF(A79="","",IF(AND(G79<>"Completed",I79<>"",I79<StatusDate),"OVERDUE","")) | Y79: =IF(OR(A79="",K79=""),"",IF(SUMPRODUCT(($A$6:$A$400<>"")*ISNUMBER(SEARCH($A$6:$A$400,K79))*($G$6:$G$400<>"Completed"))=0,"✓ Ready","⏳ "&SUMPRODUCT(($A$6:$A$400<>"")*ISNUMBER(SEARCH($A$6:$A$400,K79))*($G$6:$G$400<>"Completed"))&" open")) -> ⏳ 2 open | Z79: =IF(A79="","",B79&"|"&COUNTIFS($B$6:B79,B79,$A$6:A79,"?*")) -> Phase 5|5 | AA79: =IF(OR(A79="",I79="",G79="Completed"),"",IF(I79>=StatusDate,I79+ROW()/100000,"")) -> 46318.001 | AB79: =IF(A79="","",IF(AND(G79<>"Completed",OR(G79="Blocked",AND(TRIM(P79)<>"",P79<>"None"))),ROW(),"")) | AC79: =IF(A79="","",IF(G79="Completed","Done",IF(G79="Blocked","Blocked",IF(X79="OVERDUE","Overdue",IF(AND(W79<>"",W79<=2),"Due soon",IF(AND(Y79<>"",LEFT(Y79,1)="⏳",G79<>"Not Started"),"Dependency open",IF(AND(S79<>"None",S79<>"",G79<>"Completed"),"External req.","On track"))))))) -> External req.
A80: P5-06 | B80: Phase 5 | C80: Authentication | D80: Sign in with Apple | E80: Apple JS/redirect flow, JWT verification, private-relay email handling, account linking. | F80: P2 | G80: Not Started | H80: 46318 | I80: 46318 | J80: 0 | K80: P5-02, P5-04 | L80: Staging (Hostinger) | M80: inc/auth/social-apple.php | N80: Sign in on Safari iOS & desktop; hide-my-email case | O80: Apple sign-in works including private relay emails | S80: Credentials | T80: Not Tested | U80: =IF(A80="",0,IF(G80="Completed",1,IF(G80="Not Started",0,MIN(0.99,N(J80))))) -> 0 | V80: =IF(OR(A80="",H80="",I80=""),0,MAX(0,MIN(1,(StatusDate-H80+1)/(I80-H80+1)))) -> 0 | W80: =IF(OR(A80="",I80="",G80="Completed"),"",I80-StatusDate) -> 12 | X80: =IF(A80="","",IF(AND(G80<>"Completed",I80<>"",I80<StatusDate),"OVERDUE","")) | Y80: =IF(OR(A80="",K80=""),"",IF(SUMPRODUCT(($A$6:$A$400<>"")*ISNUMBER(SEARCH($A$6:$A$400,K80))*($G$6:$G$400<>"Completed"))=0,"✓ Ready","⏳ "&SUMPRODUCT(($A$6:$A$400<>"")*ISNUMBER(SEARCH($A$6:$A$400,K80))*($G$6:$G$400<>"Completed"))&" open")) -> ⏳ 2 open | Z80: =IF(A80="","",B80&"|"&COUNTIFS($B$6:B80,B80,$A$6:A80,"?*")) -> Phase 5|6 | AA80: =IF(OR(A80="",I80="",G80="Completed"),"",IF(I80>=StatusDate,I80+ROW()/100000,"")) -> 46318.001 | AB80: =IF(A80="","",IF(AND(G80<>"Completed",OR(G80="Blocked",AND(TRIM(P80)<>"",P80<>"None"))),ROW(),"")) | AC80: =IF(A80="","",IF(G80="Completed","Done",IF(G80="Blocked","Blocked",IF(X80="OVERDUE","Overdue",IF(AND(W80<>"",W80<=2),"Due soon",IF(AND(Y80<>"",LEFT(Y80,1)="⏳",G80<>"Not Started"),"Dependency open",IF(AND(S80<>"None",S80<>"",G80<>"Completed"),"External req.","On track"))))))) -> External req.
A81: P5-07 | B81: Phase 5 | C81: Subscriptions | D81: Subscription tiers model | E81: Tiers (e.g. Free, Digital, Premium) via roles/capabilities + user meta (plan, start, expiry); tier config editable in admin; pricing page. | F81: P0 | G81: Not Started | H81: 46318 | I81: 46318 | J81: 0 | K81: P5-04 | L81: Staging (Hostinger) | M81: inc/subscriptions/tiers.php, page-templates/page-subscribe.php | N81: Assign each tier manually; check entitlements | O81: Tiers control access across issues and content | S81: None | T81: Not Tested | U81: =IF(A81="",0,IF(G81="Completed",1,IF(G81="Not Started",0,MIN(0.99,N(J81))))) -> 0 | V81: =IF(OR(A81="",H81="",I81=""),0,MAX(0,MIN(1,(StatusDate-H81+1)/(I81-H81+1)))) -> 0 | W81: =IF(OR(A81="",I81="",G81="Completed"),"",I81-StatusDate) -> 12 | X81: =IF(A81="","",IF(AND(G81<>"Completed",I81<>"",I81<StatusDate),"OVERDUE","")) | Y81: =IF(OR(A81="",K81=""),"",IF(SUMPRODUCT(($A$6:$A$400<>"")*ISNUMBER(SEARCH($A$6:$A$400,K81))*($G$6:$G$400<>"Completed"))=0,"✓ Ready","⏳ "&SUMPRODUCT(($A$6:$A$400<>"")*ISNUMBER(SEARCH($A$6:$A$400,K81))*($G$6:$G$400<>"Completed"))&" open")) -> ⏳ 1 open | Z81: =IF(A81="","",B81&"|"&COUNTIFS($B$6:B81,B81,$A$6:A81,"?*")) -> Phase 5|7 | AA81: =IF(OR(A81="",I81="",G81="Completed"),"",IF(I81>=StatusDate,I81+ROW()/100000,"")) -> 46318.001 | AB81: =IF(A81="","",IF(AND(G81<>"Completed",OR(G81="Blocked",AND(TRIM(P81)<>"",P81<>"None"))),ROW(),"")) | AC81: =IF(A81="","",IF(G81="Completed","Done",IF(G81="Blocked","Blocked",IF(X81="OVERDUE","Overdue",IF(AND(W81<>"",W81<=2),"Due soon",IF(AND(Y81<>"",LEFT(Y81,1)="⏳",G81<>"Not Started"),"Dependency open",IF(AND(S81<>"None",S81<>"",G81<>"Completed"),"External req.","On track"))))))) -> On track
A82: P5-08 | B82: Phase 5 | C82: Payments | D82: Payment gateway checkout integration | E82: Hosted checkout (sandbox first), order record, success/failure pages, currency handling; no card data touches the server. | F82: P0 | G82: Not Started | H82: 46318 | I82: 46319 | J82: 0 | K82: P5-03, P5-07 | L82: Staging (Hostinger) | M82: inc/payments/gateway.php | N82: Sandbox: success, decline, cancel | O82: Paid checkout activates correct tier in sandbox | S82: Payment Approval | T82: Not Tested | U82: =IF(A82="",0,IF(G82="Completed",1,IF(G82="Not Started",0,MIN(0.99,N(J82))))) -> 0 | V82: =IF(OR(A82="",H82="",I82=""),0,MAX(0,MIN(1,(StatusDate-H82+1)/(I82-H82+1)))) -> 0 | W82: =IF(OR(A82="",I82="",G82="Completed"),"",I82-StatusDate) -> 13 | X82: =IF(A82="","",IF(AND(G82<>"Completed",I82<>"",I82<StatusDate),"OVERDUE","")) | Y82: =IF(OR(A82="",K82=""),"",IF(SUMPRODUCT(($A$6:$A$400<>"")*ISNUMBER(SEARCH($A$6:$A$400,K82))*($G$6:$G$400<>"Completed"))=0,"✓ Ready","⏳ "&SUMPRODUCT(($A$6:$A$400<>"")*ISNUMBER(SEARCH($A$6:$A$400,K82))*($G$6:$G$400<>"Completed"))&" open")) -> ⏳ 2 open | Z82: =IF(A82="","",B82&"|"&COUNTIFS($B$6:B82,B82,$A$6:A82,"?*")) -> Phase 5|8 | AA82: =IF(OR(A82="",I82="",G82="Completed"),"",IF(I82>=StatusDate,I82+ROW()/100000,"")) -> 46319.001 | AB82: =IF(A82="","",IF(AND(G82<>"Completed",OR(G82="Blocked",AND(TRIM(P82)<>"",P82<>"None"))),ROW(),"")) | AC82: =IF(A82="","",IF(G82="Completed","Done",IF(G82="Blocked","Blocked",IF(X82="OVERDUE","Overdue",IF(AND(W82<>"",W82<=2),"Due soon",IF(AND(Y82<>"",LEFT(Y82,1)="⏳",G82<>"Not Started"),"Dependency open",IF(AND(S82<>"None",S82<>"",G82<>"Completed"),"External req.","On track"))))))) -> External req.
A83: P5-09 | B83: Phase 5 | C83: Payments | D83: Payment webhooks | E83: Webhook endpoint with signature verification, idempotency keys, event logging, status transitions (paid, failed, refunded, renewed). | F83: P0 | G83: Not Started | H83: 46319 | I83: 46319 | J83: 0 | K83: P5-08 | L83: Staging (Hostinger) | M83: inc/payments/webhook.php | N83: Replay same event twice; tampered signature rejected | O83: Subscription state always matches gateway; duplicates ignored | S83: Payment Approval | T83: Not Tested | U83: =IF(A83="",0,IF(G83="Completed",1,IF(G83="Not Started",0,MIN(0.99,N(J83))))) -> 0 | V83: =IF(OR(A83="",H83="",I83=""),0,MAX(0,MIN(1,(StatusDate-H83+1)/(I83-H83+1)))) -> 0 | W83: =IF(OR(A83="",I83="",G83="Completed"),"",I83-StatusDate) -> 13 | X83: =IF(A83="","",IF(AND(G83<>"Completed",I83<>"",I83<StatusDate),"OVERDUE","")) | Y83: =IF(OR(A83="",K83=""),"",IF(SUMPRODUCT(($A$6:$A$400<>"")*ISNUMBER(SEARCH($A$6:$A$400,K83))*($G$6:$G$400<>"Completed"))=0,"✓ Ready","⏳ "&SUMPRODUCT(($A$6:$A$400<>"")*ISNUMBER(SEARCH($A$6:$A$400,K83))*($G$6:$G$400<>"Completed"))&" open")) -> ⏳ 1 open | Z83: =IF(A83="","",B83&"|"&COUNTIFS($B$6:B83,B83,$A$6:A83,"?*")) -> Phase 5|9 | AA83: =IF(OR(A83="",I83="",G83="Completed"),"",IF(I83>=StatusDate,I83+ROW()/100000,"")) -> 46319.001 | AB83: =IF(A83="","",IF(AND(G83<>"Completed",OR(G83="Blocked",AND(TRIM(P83)<>"",P83<>"None"))),ROW(),"")) | AC83: =IF(A83="","",IF(G83="Completed","Done",IF(G83="Blocked","Blocked",IF(X83="OVERDUE","Overdue",IF(AND(W83<>"",W83<=2),"Due soon",IF(AND(Y83<>"",LEFT(Y83,1)="⏳",G83<>"Not Started"),"Dependency open",IF(AND(S83<>"None",S83<>"",G83<>"Completed"),"External req.","On track"))))))) -> External req.
A84: P5-10 | B84: Phase 5 | C84: Subscriptions | D84: Renewal, expiry & notification emails | E84: Daily cron for expiry, grace period, renewal reminders and receipts. | F84: P1 | G84: Not Started | H84: 46319 | I84: 46319 | J84: 0 | K84: P5-09, P5-13 | L84: Staging (Hostinger) | M84: inc/subscriptions/cron.php | N84: Force-expire a test user; check emails | O84: Expired users lose access; reminders sent | S84: None | T84: Not Tested | U84: =IF(A84="",0,IF(G84="Completed",1,IF(G84="Not Started",0,MIN(0.99,N(J84))))) -> 0 | V84: =IF(OR(A84="",H84="",I84=""),0,MAX(0,MIN(1,(StatusDate-H84+1)/(I84-H84+1)))) -> 0 | W84: =IF(OR(A84="",I84="",G84="Completed"),"",I84-StatusDate) -> 13 | X84: =IF(A84="","",IF(AND(G84<>"Completed",I84<>"",I84<StatusDate),"OVERDUE","")) | Y84: =IF(OR(A84="",K84=""),"",IF(SUMPRODUCT(($A$6:$A$400<>"")*ISNUMBER(SEARCH($A$6:$A$400,K84))*($G$6:$G$400<>"Completed"))=0,"✓ Ready","⏳ "&SUMPRODUCT(($A$6:$A$400<>"")*ISNUMBER(SEARCH($A$6:$A$400,K84))*($G$6:$G$400<>"Completed"))&" open")) -> ⏳ 2 open | Z84: =IF(A84="","",B84&"|"&COUNTIFS($B$6:B84,B84,$A$6:A84,"?*")) -> Phase 5|10 | AA84: =IF(OR(A84="",I84="",G84="Completed"),"",IF(I84>=StatusDate,I84+ROW()/100000,"")) -> 46319.001 | AB84: =IF(A84="","",IF(AND(G84<>"Completed",OR(G84="Blocked",AND(TRIM(P84)<>"",P84<>"None"))),ROW(),"")) | AC84: =IF(A84="","",IF(G84="Completed","Done",IF(G84="Blocked","Blocked",IF(X84="OVERDUE","Overdue",IF(AND(W84<>"",W84<=2),"Due soon",IF(AND(Y84<>"",LEFT(Y84,1)="⏳",G84<>"Not Started"),"Dependency open",IF(AND(S84<>"None",S84<>"",G84<>"Completed"),"External req.","On track"))))))) -> On track
A85: P5-11 | B85: Phase 5 | C85: Member Dashboard | D85: Member dashboard | E85: Account page: profile edit, plan & expiry, payment history, downloads, saved issues, logout. | F85: P0 | G85: Not Started | H85: 46319 | I85: 46319 | J85: 0 | K85: P5-04, P5-07 | L85: Staging (Hostinger) | M85: page-templates/page-account.php | N85: Check as free, member and subscriber | O85: Members manage account and see entitlements | S85: None | T85: Not Tested | U85: =IF(A85="",0,IF(G85="Completed",1,IF(G85="Not Started",0,MIN(0.99,N(J85))))) -> 0 | V85: =IF(OR(A85="",H85="",I85=""),0,MAX(0,MIN(1,(StatusDate-H85+1)/(I85-H85+1)))) -> 0 | W85: =IF(OR(A85="",I85="",G85="Completed"),"",I85-StatusDate) -> 13 | X85: =IF(A85="","",IF(AND(G85<>"Completed",I85<>"",I85<StatusDate),"OVERDUE","")) | Y85: =IF(OR(A85="",K85=""),"",IF(SUMPRODUCT(($A$6:$A$400<>"")*ISNUMBER(SEARCH($A$6:$A$400,K85))*($G$6:$G$400<>"Completed"))=0,"✓ Ready","⏳ "&SUMPRODUCT(($A$6:$A$400<>"")*ISNUMBER(SEARCH($A$6:$A$400,K85))*($G$6:$G$400<>"Completed"))&" open")) -> ⏳ 2 open | Z85: =IF(A85="","",B85&"|"&COUNTIFS($B$6:B85,B85,$A$6:A85,"?*")) -> Phase 5|11 | AA85: =IF(OR(A85="",I85="",G85="Completed"),"",IF(I85>=StatusDate,I85+ROW()/100000,"")) -> 46319.001 | AB85: =IF(A85="","",IF(AND(G85<>"Completed",OR(G85="Blocked",AND(TRIM(P85)<>"",P85<>"None"))),ROW(),"")) | AC85: =IF(A85="","",IF(G85="Completed","Done",IF(G85="Blocked","Blocked",IF(X85="OVERDUE","Overdue",IF(AND(W85<>"",W85<=2),"Due soon",IF(AND(Y85<>"",LEFT(Y85,1)="⏳",G85<>"Not Started"),"Dependency open",IF(AND(S85<>"None",S85<>"",G85<>"Completed"),"External req.","On track"))))))) -> On track
A86: P5-12 | B86: Phase 5 | C86: Security | D86: Security hardening & rate limiting | E86: Login/registration/reset rate limiting by IP + account, nonces on all forms, CAPTCHA/Turnstile or honeypot, password policy, generic error messages, sanitize/escape audit of auth code. | F86: P0 | G86: Not Started | H86: 46319 | I86: 46319 | J86: 0 | K86: P5-04 | L86: Staging (Hostinger) | M86: inc/security.php | N86: Brute-force 10 attempts → lockout; CSRF test without nonce | O86: Abuse throttled; no user enumeration; forms CSRF-safe | S86: None | T86: Not Tested | U86: =IF(A86="",0,IF(G86="Completed",1,IF(G86="Not Started",0,MIN(0.99,N(J86))))) -> 0 | V86: =IF(OR(A86="",H86="",I86=""),0,MAX(0,MIN(1,(StatusDate-H86+1)/(I86-H86+1)))) -> 0 | W86: =IF(OR(A86="",I86="",G86="Completed"),"",I86-StatusDate) -> 13 | X86: =IF(A86="","",IF(AND(G86<>"Completed",I86<>"",I86<StatusDate),"OVERDUE","")) | Y86: =IF(OR(A86="",K86=""),"",IF(SUMPRODUCT(($A$6:$A$400<>"")*ISNUMBER(SEARCH($A$6:$A$400,K86))*($G$6:$G$400<>"Completed"))=0,"✓ Ready","⏳ "&SUMPRODUCT(($A$6:$A$400<>"")*ISNUMBER(SEARCH($A$6:$A$400,K86))*($G$6:$G$400<>"Completed"))&" open")) -> ⏳ 1 open | Z86: =IF(A86="","",B86&"|"&COUNTIFS($B$6:B86,B86,$A$6:A86,"?*")) -> Phase 5|12 | AA86: =IF(OR(A86="",I86="",G86="Completed"),"",IF(I86>=StatusDate,I86+ROW()/100000,"")) -> 46319.001 | AB86: =IF(A86="","",IF(AND(G86<>"Completed",OR(G86="Blocked",AND(TRIM(P86)<>"",P86<>"None"))),ROW(),"")) | AC86: =IF(A86="","",IF(G86="Completed","Done",IF(G86="Blocked","Blocked",IF(X86="OVERDUE","Overdue",IF(AND(W86<>"",W86<=2),"Due soon",IF(AND(Y86<>"",LEFT(Y86,1)="⏳",G86<>"Not Started"),"Dependency open",IF(AND(S86<>"None",S86<>"",G86<>"Completed"),"External req.","On track"))))))) -> On track
A87: P5-13 | B87: Phase 5 | C87: Email | D87: SMTP / transactional email setup | E87: Configure authenticated SMTP (SPF/DKIM) for verification, reset, receipts and lead notifications. | F87: P0 | G87: Not Started | H87: 46319 | I87: 46320 | J87: 0 | L87: Staging (Hostinger) | M87: wp-config.php or SMTP plugin settings | N87: Send test emails to Gmail/Outlook; check spam | O87: Transactional emails delivered to inbox | S87: Credentials | T87: Not Tested | U87: =IF(A87="",0,IF(G87="Completed",1,IF(G87="Not Started",0,MIN(0.99,N(J87))))) -> 0 | V87: =IF(OR(A87="",H87="",I87=""),0,MAX(0,MIN(1,(StatusDate-H87+1)/(I87-H87+1)))) -> 0 | W87: =IF(OR(A87="",I87="",G87="Completed"),"",I87-StatusDate) -> 14 | X87: =IF(A87="","",IF(AND(G87<>"Completed",I87<>"",I87<StatusDate),"OVERDUE","")) | Y87: =IF(OR(A87="",K87=""),"",IF(SUMPRODUCT(($A$6:$A$400<>"")*ISNUMBER(SEARCH($A$6:$A$400,K87))*($G$6:$G$400<>"Completed"))=0,"✓ Ready","⏳ "&SUMPRODUCT(($A$6:$A$400<>"")*ISNUMBER(SEARCH($A$6:$A$400,K87))*($G$6:$G$400<>"Completed"))&" open")) | Z87: =IF(A87="","",B87&"|"&COUNTIFS($B$6:B87,B87,$A$6:A87,"?*")) -> Phase 5|13 | AA87: =IF(OR(A87="",I87="",G87="Completed"),"",IF(I87>=StatusDate,I87+ROW()/100000,"")) -> 46320.001 | AB87: =IF(A87="","",IF(AND(G87<>"Completed",OR(G87="Blocked",AND(TRIM(P87)<>"",P87<>"None"))),ROW(),"")) | AC87: =IF(A87="","",IF(G87="Completed","Done",IF(G87="Blocked","Blocked",IF(X87="OVERDUE","Overdue",IF(AND(W87<>"",W87<=2),"Due soon",IF(AND(Y87<>"",LEFT(Y87,1)="⏳",G87<>"Not Started"),"Dependency open",IF(AND(S87<>"None",S87<>"",G87<>"Completed"),"External req.","On track"))))))) -> External req.
A88: P5-14 | B88: Phase 5 | C88: AdOps | D88: Advertising page | E88: page-advertise.php: audience stats, placements, formats, CTA to lead form and media kit. | F88: P1 | G88: Not Started | H88: 46320 | I88: 46320 | J88: 0 | K88: P1-17 | L88: Staging (Hostinger) | M88: page-templates/page-advertise.php | N88: Content review with client; responsive check | O88: Advertising page live with editable content | S88: Client Content | T88: Not Tested | U88: =IF(A88="",0,IF(G88="Completed",1,IF(G88="Not Started",0,MIN(0.99,N(J88))))) -> 0 | V88: =IF(OR(A88="",H88="",I88=""),0,MAX(0,MIN(1,(StatusDate-H88+1)/(I88-H88+1)))) -> 0 | W88: =IF(OR(A88="",I88="",G88="Completed"),"",I88-StatusDate) -> 14 | X88: =IF(A88="","",IF(AND(G88<>"Completed",I88<>"",I88<StatusDate),"OVERDUE","")) | Y88: =IF(OR(A88="",K88=""),"",IF(SUMPRODUCT(($A$6:$A$400<>"")*ISNUMBER(SEARCH($A$6:$A$400,K88))*($G$6:$G$400<>"Completed"))=0,"✓ Ready","⏳ "&SUMPRODUCT(($A$6:$A$400<>"")*ISNUMBER(SEARCH($A$6:$A$400,K88))*($G$6:$G$400<>"Completed"))&" open")) -> ⏳ 1 open | Z88: =IF(A88="","",B88&"|"&COUNTIFS($B$6:B88,B88,$A$6:A88,"?*")) -> Phase 5|14 | AA88: =IF(OR(A88="",I88="",G88="Completed"),"",IF(I88>=StatusDate,I88+ROW()/100000,"")) -> 46320.001 | AB88: =IF(A88="","",IF(AND(G88<>"Completed",OR(G88="Blocked",AND(TRIM(P88)<>"",P88<>"None"))),ROW(),"")) | AC88: =IF(A88="","",IF(G88="Completed","Done",IF(G88="Blocked","Blocked",IF(X88="OVERDUE","Overdue",IF(AND(W88<>"",W88<=2),"Due soon",IF(AND(Y88<>"",LEFT(Y88,1)="⏳",G88<>"Not Started"),"Dependency open",IF(AND(S88<>"None",S88<>"",G88<>"Completed"),"External req.","On track"))))))) -> External req.
A89: P5-15 | B89: Phase 5 | C89: AdOps | D89: Advertising rate calculator | E89: Vanilla JS calculator: placement, size, duration, frequency → estimated price; rates editable in admin (no code). | F89: P1 | G89: Not Started | H89: 46320 | I89: 46320 | J89: 0 | K89: P5-14 | L89: Staging (Hostinger) | M89: assets/js/modules/rate-calculator.js, inc/adops-settings.php | N89: Test edge values; change a rate in admin | O89: Calculator accurate and admin-configurable | S89: Client Content | T89: Not Tested | U89: =IF(A89="",0,IF(G89="Completed",1,IF(G89="Not Started",0,MIN(0.99,N(J89))))) -> 0 | V89: =IF(OR(A89="",H89="",I89=""),0,MAX(0,MIN(1,(StatusDate-H89+1)/(I89-H89+1)))) -> 0 | W89: =IF(OR(A89="",I89="",G89="Completed"),"",I89-StatusDate) -> 14 | X89: =IF(A89="","",IF(AND(G89<>"Completed",I89<>"",I89<StatusDate),"OVERDUE","")) | Y89: =IF(OR(A89="",K89=""),"",IF(SUMPRODUCT(($A$6:$A$400<>"")*ISNUMBER(SEARCH($A$6:$A$400,K89))*($G$6:$G$400<>"Completed"))=0,"✓ Ready","⏳ "&SUMPRODUCT(($A$6:$A$400<>"")*ISNUMBER(SEARCH($A$6:$A$400,K89))*($G$6:$G$400<>"Completed"))&" open")) -> ⏳ 1 open | Z89: =IF(A89="","",B89&"|"&COUNTIFS($B$6:B89,B89,$A$6:A89,"?*")) -> Phase 5|15 | AA89: =IF(OR(A89="",I89="",G89="Completed"),"",IF(I89>=StatusDate,I89+ROW()/100000,"")) -> 46320.001 | AB89: =IF(A89="","",IF(AND(G89<>"Completed",OR(G89="Blocked",AND(TRIM(P89)<>"",P89<>"None"))),ROW(),"")) | AC89: =IF(A89="","",IF(G89="Completed","Done",IF(G89="Blocked","Blocked",IF(X89="OVERDUE","Overdue",IF(AND(W89<>"",W89<=2),"Due soon",IF(AND(Y89<>"",LEFT(Y89,1)="⏳",G89<>"Not Started"),"Dependency open",IF(AND(S89<>"None",S89<>"",G89<>"Completed"),"External req.","On track"))))))) -> External req.
A90: P5-16 | B90: Phase 5 | C90: AdOps | D90: Media kit download | E90: Media kit PDF download, optionally gated behind lead form. | F90: P2 | G90: Not Started | H90: 46320 | I90: 46320 | J90: 0 | K90: P5-14, P5-17 | L90: Staging (Hostinger) | M90: page-templates/page-advertise.php | N90: Download after form submit | O90: Media kit downloadable and tracked | S90: Client Content | T90: Not Tested | U90: =IF(A90="",0,IF(G90="Completed",1,IF(G90="Not Started",0,MIN(0.99,N(J90))))) -> 0 | V90: =IF(OR(A90="",H90="",I90=""),0,MAX(0,MIN(1,(StatusDate-H90+1)/(I90-H90+1)))) -> 0 | W90: =IF(OR(A90="",I90="",G90="Completed"),"",I90-StatusDate) -> 14 | X90: =IF(A90="","",IF(AND(G90<>"Completed",I90<>"",I90<StatusDate),"OVERDUE","")) | Y90: =IF(OR(A90="",K90=""),"",IF(SUMPRODUCT(($A$6:$A$400<>"")*ISNUMBER(SEARCH($A$6:$A$400,K90))*($G$6:$G$400<>"Completed"))=0,"✓ Ready","⏳ "&SUMPRODUCT(($A$6:$A$400<>"")*ISNUMBER(SEARCH($A$6:$A$400,K90))*($G$6:$G$400<>"Completed"))&" open")) -> ⏳ 2 open | Z90: =IF(A90="","",B90&"|"&COUNTIFS($B$6:B90,B90,$A$6:A90,"?*")) -> Phase 5|16 | AA90: =IF(OR(A90="",I90="",G90="Completed"),"",IF(I90>=StatusDate,I90+ROW()/100000,"")) -> 46320.001 | AB90: =IF(A90="","",IF(AND(G90<>"Completed",OR(G90="Blocked",AND(TRIM(P90)<>"",P90<>"None"))),ROW(),"")) | AC90: =IF(A90="","",IF(G90="Completed","Done",IF(G90="Blocked","Blocked",IF(X90="OVERDUE","Overdue",IF(AND(W90<>"",W90<=2),"Due soon",IF(AND(Y90<>"",LEFT(Y90,1)="⏳",G90<>"Not Started"),"Dependency open",IF(AND(S90<>"None",S90<>"",G90<>"Completed"),"External req.","On track"))))))) -> External req.
A91: P5-17 | B91: Phase 5 | C91: Leads | D91: Lead capture forms | E91: Advertising inquiry & general lead forms stored as private 'lead' CPT + email notification; spam protection; admin export CSV. | F91: P0 | G91: Not Started | H91: 46320 | I91: 46320 | J91: 0 | K91: P5-12, P5-13 | L91: Staging (Hostinger) | M91: inc/leads.php | N91: Submit valid/invalid/spam; export CSV | O91: Every lead stored and notified; spam blocked | S91: None | T91: Not Tested | U91: =IF(A91="",0,IF(G91="Completed",1,IF(G91="Not Started",0,MIN(0.99,N(J91))))) -> 0 | V91: =IF(OR(A91="",H91="",I91=""),0,MAX(0,MIN(1,(StatusDate-H91+1)/(I91-H91+1)))) -> 0 | W91: =IF(OR(A91="",I91="",G91="Completed"),"",I91-StatusDate) -> 14 | X91: =IF(A91="","",IF(AND(G91<>"Completed",I91<>"",I91<StatusDate),"OVERDUE","")) | Y91: =IF(OR(A91="",K91=""),"",IF(SUMPRODUCT(($A$6:$A$400<>"")*ISNUMBER(SEARCH($A$6:$A$400,K91))*($G$6:$G$400<>"Completed"))=0,"✓ Ready","⏳ "&SUMPRODUCT(($A$6:$A$400<>"")*ISNUMBER(SEARCH($A$6:$A$400,K91))*($G$6:$G$400<>"Completed"))&" open")) -> ⏳ 2 open | Z91: =IF(A91="","",B91&"|"&COUNTIFS($B$6:B91,B91,$A$6:A91,"?*")) -> Phase 5|17 | AA91: =IF(OR(A91="",I91="",G91="Completed"),"",IF(I91>=StatusDate,I91+ROW()/100000,"")) -> 46320.001 | AB91: =IF(A91="","",IF(AND(G91<>"Completed",OR(G91="Blocked",AND(TRIM(P91)<>"",P91<>"None"))),ROW(),"")) | AC91: =IF(A91="","",IF(G91="Completed","Done",IF(G91="Blocked","Blocked",IF(X91="OVERDUE","Overdue",IF(AND(W91<>"",W91<=2),"Due soon",IF(AND(Y91<>"",LEFT(Y91,1)="⏳",G91<>"Not Started"),"Dependency open",IF(AND(S91<>"None",S91<>"",G91<>"Completed"),"External req.","On track"))))))) -> On track
A92: P5-18 | B92: Phase 5 | C92: Pages | D92: About page | E92: page-about.php: mission, history, team, partners; editable via blocks/ACF-free fields. | F92: P1 | G92: Not Started | H92: 46320 | I92: 46320 | J92: 0 | K92: P1-17 | L92: Staging (Hostinger) | M92: page-templates/page-about.php | N92: Content review; responsive check | O92: About page live and editable | S92: Client Content | T92: Not Tested | U92: =IF(A92="",0,IF(G92="Completed",1,IF(G92="Not Started",0,MIN(0.99,N(J92))))) -> 0 | V92: =IF(OR(A92="",H92="",I92=""),0,MAX(0,MIN(1,(StatusDate-H92+1)/(I92-H92+1)))) -> 0 | W92: =IF(OR(A92="",I92="",G92="Completed"),"",I92-StatusDate) -> 14 | X92: =IF(A92="","",IF(AND(G92<>"Completed",I92<>"",I92<StatusDate),"OVERDUE","")) | Y92: =IF(OR(A92="",K92=""),"",IF(SUMPRODUCT(($A$6:$A$400<>"")*ISNUMBER(SEARCH($A$6:$A$400,K92))*($G$6:$G$400<>"Completed"))=0,"✓ Ready","⏳ "&SUMPRODUCT(($A$6:$A$400<>"")*ISNUMBER(SEARCH($A$6:$A$400,K92))*($G$6:$G$400<>"Completed"))&" open")) -> ⏳ 1 open | Z92: =IF(A92="","",B92&"|"&COUNTIFS($B$6:B92,B92,$A$6:A92,"?*")) -> Phase 5|18 | AA92: =IF(OR(A92="",I92="",G92="Completed"),"",IF(I92>=StatusDate,I92+ROW()/100000,"")) -> 46320.001 | AB92: =IF(A92="","",IF(AND(G92<>"Completed",OR(G92="Blocked",AND(TRIM(P92)<>"",P92<>"None"))),ROW(),"")) | AC92: =IF(A92="","",IF(G92="Completed","Done",IF(G92="Blocked","Blocked",IF(X92="OVERDUE","Overdue",IF(AND(W92<>"",W92<=2),"Due soon",IF(AND(Y92<>"",LEFT(Y92,1)="⏳",G92<>"Not Started"),"Dependency open",IF(AND(S92<>"None",S92<>"",G92<>"Completed"),"External req.","On track"))))))) -> External req.
A93: P5-19 | B93: Phase 5 | C93: Pages | D93: Contact page | E93: page-contact.php: contact form (stored + emailed), details, map embed (lazy), social links. | F93: P0 | G93: Not Started | H93: 46320 | I93: 46320 | J93: 0 | K93: P5-17 | L93: Staging (Hostinger) | M93: page-templates/page-contact.php | N93: Submit form; check stored entry and email | O93: Contact form works end-to-end | S93: None | T93: Not Tested | U93: =IF(A93="",0,IF(G93="Completed",1,IF(G93="Not Started",0,MIN(0.99,N(J93))))) -> 0 | V93: =IF(OR(A93="",H93="",I93=""),0,MAX(0,MIN(1,(StatusDate-H93+1)/(I93-H93+1)))) -> 0 | W93: =IF(OR(A93="",I93="",G93="Completed"),"",I93-StatusDate) -> 14 | X93: =IF(A93="","",IF(AND(G93<>"Completed",I93<>"",I93<StatusDate),"OVERDUE","")) | Y93: =IF(OR(A93="",K93=""),"",IF(SUMPRODUCT(($A$6:$A$400<>"")*ISNUMBER(SEARCH($A$6:$A$400,K93))*($G$6:$G$400<>"Completed"))=0,"✓ Ready","⏳ "&SUMPRODUCT(($A$6:$A$400<>"")*ISNUMBER(SEARCH($A$6:$A$400,K93))*($G$6:$G$400<>"Completed"))&" open")) -> ⏳ 1 open | Z93: =IF(A93="","",B93&"|"&COUNTIFS($B$6:B93,B93,$A$6:A93,"?*")) -> Phase 5|19 | AA93: =IF(OR(A93="",I93="",G93="Completed"),"",IF(I93>=StatusDate,I93+ROW()/100000,"")) -> 46320.001 | AB93: =IF(A93="","",IF(AND(G93<>"Completed",OR(G93="Blocked",AND(TRIM(P93)<>"",P93<>"None"))),ROW(),"")) | AC93: =IF(A93="","",IF(G93="Completed","Done",IF(G93="Blocked","Blocked",IF(X93="OVERDUE","Overdue",IF(AND(W93<>"",W93<=2),"Due soon",IF(AND(Y93<>"",LEFT(Y93,1)="⏳",G93<>"Not Started"),"Dependency open",IF(AND(S93<>"None",S93<>"",G93<>"Completed"),"External req.","On track"))))))) -> On track
A94: P5-20 | B94: Phase 5 | C94: Roles | D94: Editorial roles & permissions | E94: Define roles/capabilities: Editor-in-Chief, Editor, Writer/Contributor, Ad Manager, Subscriber tiers; restrict Customizer/Section Manager to editors+. | F94: P0 | G94: Not Started | H94: 46320 | I94: 46320 | J94: 0 | K94: P2-02 | L94: Staging (Hostinger) | M94: inc/roles.php | N94: Log in as each role; attempt forbidden actions | O94: Each role can do exactly what it needs and nothing more | S94: None | T94: Not Tested | U94: =IF(A94="",0,IF(G94="Completed",1,IF(G94="Not Started",0,MIN(0.99,N(J94))))) -> 0 | V94: =IF(OR(A94="",H94="",I94=""),0,MAX(0,MIN(1,(StatusDate-H94+1)/(I94-H94+1)))) -> 0 | W94: =IF(OR(A94="",I94="",G94="Completed"),"",I94-StatusDate) -> 14 | X94: =IF(A94="","",IF(AND(G94<>"Completed",I94<>"",I94<StatusDate),"OVERDUE","")) | Y94: =IF(OR(A94="",K94=""),"",IF(SUMPRODUCT(($A$6:$A$400<>"")*ISNUMBER(SEARCH($A$6:$A$400,K94))*($G$6:$G$400<>"Completed"))=0,"✓ Ready","⏳ "&SUMPRODUCT(($A$6:$A$400<>"")*ISNUMBER(SEARCH($A$6:$A$400,K94))*($G$6:$G$400<>"Completed"))&" open")) -> ⏳ 1 open | Z94: =IF(A94="","",B94&"|"&COUNTIFS($B$6:B94,B94,$A$6:A94,"?*")) -> Phase 5|20 | AA94: =IF(OR(A94="",I94="",G94="Completed"),"",IF(I94>=StatusDate,I94+ROW()/100000,"")) -> 46320.001 | AB94: =IF(A94="","",IF(AND(G94<>"Completed",OR(G94="Blocked",AND(TRIM(P94)<>"",P94<>"None"))),ROW(),"")) | AC94: =IF(A94="","",IF(G94="Completed","Done",IF(G94="Blocked","Blocked",IF(X94="OVERDUE","Overdue",IF(AND(W94<>"",W94<=2),"Due soon",IF(AND(Y94<>"",LEFT(Y94,1)="⏳",G94<>"Not Started"),"Dependency open",IF(AND(S94<>"None",S94<>"",G94<>"Completed"),"External req.","On track"))))))) -> On track
A95: P6-01 | B95: Phase 6 | C95: Backup | D95: Full production backup (files + DB) before any work | E95: Full backup of production files (incl. large uploads) and database; store off-server; verify archive integrity and restore-test on staging. | F95: P0 | G95: Not Started | H95: 46307 | I95: 46307 | J95: 0 | L95: Production | M95: backups/ (off-server) | N95: Checksum verified; DB dump imports cleanly on staging | O95: Restorable backup exists before any change | S95: Server Access | T95: Not Tested | U95: =IF(A95="",0,IF(G95="Completed",1,IF(G95="Not Started",0,MIN(0.99,N(J95))))) -> 0 | V95: =IF(OR(A95="",H95="",I95=""),0,MAX(0,MIN(1,(StatusDate-H95+1)/(I95-H95+1)))) -> 0 | W95: =IF(OR(A95="",I95="",G95="Completed"),"",I95-StatusDate) -> 1 | X95: =IF(A95="","",IF(AND(G95<>"Completed",I95<>"",I95<StatusDate),"OVERDUE","")) | Y95: =IF(OR(A95="",K95=""),"",IF(SUMPRODUCT(($A$6:$A$400<>"")*ISNUMBER(SEARCH($A$6:$A$400,K95))*($G$6:$G$400<>"Completed"))=0,"✓ Ready","⏳ "&SUMPRODUCT(($A$6:$A$400<>"")*ISNUMBER(SEARCH($A$6:$A$400,K95))*($G$6:$G$400<>"Completed"))&" open")) | Z95: =IF(A95="","",B95&"|"&COUNTIFS($B$6:B95,B95,$A$6:A95,"?*")) -> Phase 6|1 | AA95: =IF(OR(A95="",I95="",G95="Completed"),"",IF(I95>=StatusDate,I95+ROW()/100000,"")) -> 46307.001 | AB95: =IF(A95="","",IF(AND(G95<>"Completed",OR(G95="Blocked",AND(TRIM(P95)<>"",P95<>"None"))),ROW(),"")) | AC95: =IF(A95="","",IF(G95="Completed","Done",IF(G95="Blocked","Blocked",IF(X95="OVERDUE","Overdue",IF(AND(W95<>"",W95<=2),"Due soon",IF(AND(Y95<>"",LEFT(Y95,1)="⏳",G95<>"Not Started"),"Dependency open",IF(AND(S95<>"None",S95<>"",G95<>"Completed"),"External req.","On track"))))))) -> Due soon
A96: P6-02 | B96: Phase 6 | C96: Backup | D96: Verify staging mirrors production | E96: Confirm staging DB/content is a current copy: post count (2,645 articles), media, users, menus, plugins; record content-freeze or delta-sync approach. | F96: P0 | G96: Not Started | H96: 46307 | I96: 46307 | J96: 0 | K96: P6-01 | L96: Staging (Hostinger) | M96: wp-config.php, database | N96: Compare post/term/user counts staging vs production | O96: Staging is a verified mirror; content-delta plan agreed | S96: Server Access | T96: Not Tested | U96: =IF(A96="",0,IF(G96="Completed",1,IF(G96="Not Started",0,MIN(0.99,N(J96))))) -> 0 | V96: =IF(OR(A96="",H96="",I96=""),0,MAX(0,MIN(1,(StatusDate-H96+1)/(I96-H96+1)))) -> 0 | W96: =IF(OR(A96="",I96="",G96="Completed"),"",I96-StatusDate) -> 1 | X96: =IF(A96="","",IF(AND(G96<>"Completed",I96<>"",I96<StatusDate),"OVERDUE","")) | Y96: =IF(OR(A96="",K96=""),"",IF(SUMPRODUCT(($A$6:$A$400<>"")*ISNUMBER(SEARCH($A$6:$A$400,K96))*($G$6:$G$400<>"Completed"))=0,"✓ Ready","⏳ "&SUMPRODUCT(($A$6:$A$400<>"")*ISNUMBER(SEARCH($A$6:$A$400,K96))*($G$6:$G$400<>"Completed"))&" open")) -> ⏳ 1 open | Z96: =IF(A96="","",B96&"|"&COUNTIFS($B$6:B96,B96,$A$6:A96,"?*")) -> Phase 6|2 | AA96: =IF(OR(A96="",I96="",G96="Completed"),"",IF(I96>=StatusDate,I96+ROW()/100000,"")) -> 46307.001 | AB96: =IF(A96="","",IF(AND(G96<>"Completed",OR(G96="Blocked",AND(TRIM(P96)<>"",P96<>"None"))),ROW(),"")) | AC96: =IF(A96="","",IF(G96="Completed","Done",IF(G96="Blocked","Blocked",IF(X96="OVERDUE","Overdue",IF(AND(W96<>"",W96<=2),"Due soon",IF(AND(Y96<>"",LEFT(Y96,1)="⏳",G96<>"Not Started"),"Dependency open",IF(AND(S96<>"None",S96<>"",G96<>"Completed"),"External req.","On track"))))))) -> Due soon
A97: P6-03 | B97: Phase 6 | C97: DB Audit | D97: Database audit | E97: Table sizes, autoloaded options size, revisions, expired transients, orphaned postmeta/termmeta, JNews options and tables; document findings. | F97: P0 | G97: Not Started | H97: 46308 | I97: 46308 | J97: 0 | K97: P6-02 | L97: Staging (Hostinger) | M97: database (phpMyAdmin) | N97: Run audit queries; export results | O97: Audit report saved; risks logged | S97: None | T97: Not Tested | U97: =IF(A97="",0,IF(G97="Completed",1,IF(G97="Not Started",0,MIN(0.99,N(J97))))) -> 0 | V97: =IF(OR(A97="",H97="",I97=""),0,MAX(0,MIN(1,(StatusDate-H97+1)/(I97-H97+1)))) -> 0 | W97: =IF(OR(A97="",I97="",G97="Completed"),"",I97-StatusDate) -> 2 | X97: =IF(A97="","",IF(AND(G97<>"Completed",I97<>"",I97<StatusDate),"OVERDUE","")) | Y97: =IF(OR(A97="",K97=""),"",IF(SUMPRODUCT(($A$6:$A$400<>"")*ISNUMBER(SEARCH($A$6:$A$400,K97))*($G$6:$G$400<>"Completed"))=0,"✓ Ready","⏳ "&SUMPRODUCT(($A$6:$A$400<>"")*ISNUMBER(SEARCH($A$6:$A$400,K97))*($G$6:$G$400<>"Completed"))&" open")) -> ⏳ 1 open | Z97: =IF(A97="","",B97&"|"&COUNTIFS($B$6:B97,B97,$A$6:A97,"?*")) -> Phase 6|3 | AA97: =IF(OR(A97="",I97="",G97="Completed"),"",IF(I97>=StatusDate,I97+ROW()/100000,"")) -> 46308.001 | AB97: =IF(A97="","",IF(AND(G97<>"Completed",OR(G97="Blocked",AND(TRIM(P97)<>"",P97<>"None"))),ROW(),"")) | AC97: =IF(A97="","",IF(G97="Completed","Done",IF(G97="Blocked","Blocked",IF(X97="OVERDUE","Overdue",IF(AND(W97<>"",W97<=2),"Due soon",IF(AND(Y97<>"",LEFT(Y97,1)="⏳",G97<>"Not Started"),"Dependency open",IF(AND(S97<>"None",S97<>"",G97<>"Completed"),"External req.","On track"))))))) -> Due soon
A98: P6-04 | B98: Phase 6 | C98: JNews Review | D98: Legacy JNews dependency review | E98: Inventory JNews shortcodes in post_content, JNews postmeta in use (views, subtitle, video, gallery), widgets, menus, and plugins depending on JNews; decide keep/convert/drop for each. | F98: P0 | G98: Not Started | H98: 46308 | I98: 46308 | J98: 0 | K98: P6-03 | L98: Staging (Hostinger) | M98: database, wp-content/plugins/jnews-* | N98: SQL LIKE search for shortcodes; meta key frequency list | O98: Every JNews dependency has a documented decision | S98: None | T98: Not Tested | U98: =IF(A98="",0,IF(G98="Completed",1,IF(G98="Not Started",0,MIN(0.99,N(J98))))) -> 0 | V98: =IF(OR(A98="",H98="",I98=""),0,MAX(0,MIN(1,(StatusDate-H98+1)/(I98-H98+1)))) -> 0 | W98: =IF(OR(A98="",I98="",G98="Completed"),"",I98-StatusDate) -> 2 | X98: =IF(A98="","",IF(AND(G98<>"Completed",I98<>"",I98<StatusDate),"OVERDUE","")) | Y98: =IF(OR(A98="",K98=""),"",IF(SUMPRODUCT(($A$6:$A$400<>"")*ISNUMBER(SEARCH($A$6:$A$400,K98))*($G$6:$G$400<>"Completed"))=0,"✓ Ready","⏳ "&SUMPRODUCT(($A$6:$A$400<>"")*ISNUMBER(SEARCH($A$6:$A$400,K98))*($G$6:$G$400<>"Completed"))&" open")) -> ⏳ 1 open | Z98: =IF(A98="","",B98&"|"&COUNTIFS($B$6:B98,B98,$A$6:A98,"?*")) -> Phase 6|4 | AA98: =IF(OR(A98="",I98="",G98="Completed"),"",IF(I98>=StatusDate,I98+ROW()/100000,"")) -> 46308.001 | AB98: =IF(A98="","",IF(AND(G98<>"Completed",OR(G98="Blocked",AND(TRIM(P98)<>"",P98<>"None"))),ROW(),"")) | AC98: =IF(A98="","",IF(G98="Completed","Done",IF(G98="Blocked","Blocked",IF(X98="OVERDUE","Overdue",IF(AND(W98<>"",W98<=2),"Due soon",IF(AND(Y98<>"",LEFT(Y98,1)="⏳",G98<>"Not Started"),"Dependency open",IF(AND(S98<>"None",S98<>"",G98<>"Completed"),"External req.","On track"))))))) -> Due soon
A99: P6-05 | B99: Phase 6 | C99: URL Inventory | D99: Export URL inventory (2,645 articles + taxonomies) | E99: Export all article, category, tag, author, page URLs from production sitemaps/DB into url-inventory.csv. | F99: P0 | G99: Not Started | H99: 46308 | I99: 46308 | J99: 0 | K99: P6-01 | L99: Production | M99: url-inventory.csv | N99: Row count = 2,645 articles + taxonomy/page rows | O99: Complete URL inventory saved | S99: None | T99: Not Tested | U99: =IF(A99="",0,IF(G99="Completed",1,IF(G99="Not Started",0,MIN(0.99,N(J99))))) -> 0 | V99: =IF(OR(A99="",H99="",I99=""),0,MAX(0,MIN(1,(StatusDate-H99+1)/(I99-H99+1)))) -> 0 | W99: =IF(OR(A99="",I99="",G99="Completed"),"",I99-StatusDate) -> 2 | X99: =IF(A99="","",IF(AND(G99<>"Completed",I99<>"",I99<StatusDate),"OVERDUE","")) | Y99: =IF(OR(A99="",K99=""),"",IF(SUMPRODUCT(($A$6:$A$400<>"")*ISNUMBER(SEARCH($A$6:$A$400,K99))*($G$6:$G$400<>"Completed"))=0,"✓ Ready","⏳ "&SUMPRODUCT(($A$6:$A$400<>"")*ISNUMBER(SEARCH($A$6:$A$400,K99))*($G$6:$G$400<>"Completed"))&" open")) -> ⏳ 1 open | Z99: =IF(A99="","",B99&"|"&COUNTIFS($B$6:B99,B99,$A$6:A99,"?*")) -> Phase 6|5 | AA99: =IF(OR(A99="",I99="",G99="Completed"),"",IF(I99>=StatusDate,I99+ROW()/100000,"")) -> 46308.001 | AB99: =IF(A99="","",IF(AND(G99<>"Completed",OR(G99="Blocked",AND(TRIM(P99)<>"",P99<>"None"))),ROW(),"")) | AC99: =IF(A99="","",IF(G99="Completed","Done",IF(G99="Blocked","Blocked",IF(X99="OVERDUE","Overdue",IF(AND(W99<>"",W99<=2),"Due soon",IF(AND(Y99<>"",LEFT(Y99,1)="⏳",G99<>"Not Started"),"Dependency open",IF(AND(S99<>"None",S99<>"",G99<>"Completed"),"External req.","On track"))))))) -> Due soon
A100: P6-06 | B100: Phase 6 | C100: SEO Baseline | D100: Capture SEO baseline | E100: Crawl production: titles, meta descriptions, canonicals, H1, robots, hreflang/OG, schema, sitemap; export Search Console coverage & top pages. | F100: P0 | G100: Not Started | H100: 46308 | I100: 46308 | J100: 0 | K100: P6-05 | L100: Production | M100: seo-baseline.csv | N100: Baseline crawl complete; GSC export saved | O100: Baseline available for comparison | S100: Credentials | T100: Not Tested | U100: =IF(A100="",0,IF(G100="Completed",1,IF(G100="Not Started",0,MIN(0.99,N(J100))))) -> 0 | V100: =IF(OR(A100="",H100="",I100=""),0,MAX(0,MIN(1,(StatusDate-H100+1)/(I100-H100+1)))) -> 0 | W100: =IF(OR(A100="",I100="",G100="Completed"),"",I100-StatusDate) -> 2 | X100: =IF(A100="","",IF(AND(G100<>"Completed",I100<>"",I100<StatusDate),"OVERDUE","")) | Y100: =IF(OR(A100="",K100=""),"",IF(SUMPRODUCT(($A$6:$A$400<>"")*ISNUMBER(SEARCH($A$6:$A$400,K100))*($G$6:$G$400<>"Completed"))=0,"✓ Ready","⏳ "&SUMPRODUCT(($A$6:$A$400<>"")*ISNUMBER(SEARCH($A$6:$A$400,K100))*($G$6:$G$400<>"Completed"))&" open")) -> ⏳ 1 open | Z100: =IF(A100="","",B100&"|"&COUNTIFS($B$6:B100,B100,$A$6:A100,"?*")) -> Phase 6|6 | AA100: =IF(OR(A100="",I100="",G100="Completed"),"",IF(I100>=StatusDate,I100+ROW()/100000,"")) -> 46308.001 | AB100: =IF(A100="","",IF(AND(G100<>"Completed",OR(G100="Blocked",AND(TRIM(P100)<>"",P100<>"None"))),ROW(),"")) | AC100: =IF(A100="","",IF(G100="Completed","Done",IF(G100="Blocked","Blocked",IF(X100="OVERDUE","Overdue",IF(AND(W100<>"",W100<=2),"Due soon",IF(AND(Y100<>"",LEFT(Y100,1)="⏳",G100<>"Not Started"),"Dependency open",IF(AND(S100<>"None",S100<>"",G100<>"Completed"),"External req.","On track"))))))) -> Due soon
A101: P6-07 | B101: Phase 6 | C101: DB Optimization | D101: Safe database optimization (staging first) | E101: Limit revisions, delete expired transients, orphan meta, trim autoload; only after backup; replicate on production only during cutover window. | F101: P1 | G101: Not Started | H101: 46321 | I101: 46321 | J101: 0 | K101: P6-03, P6-04 | L101: Staging (Hostinger) | M101: wp-config.php (WP_POST_REVISIONS), database | N101: Before/after sizes; site regression check | O101: DB smaller and faster with no content loss | S101: None | T101: Not Tested | U101: =IF(A101="",0,IF(G101="Completed",1,IF(G101="Not Started",0,MIN(0.99,N(J101))))) -> 0 | V101: =IF(OR(A101="",H101="",I101=""),0,MAX(0,MIN(1,(StatusDate-H101+1)/(I101-H101+1)))) -> 0 | W101: =IF(OR(A101="",I101="",G101="Completed"),"",I101-StatusDate) -> 15 | X101: =IF(A101="","",IF(AND(G101<>"Completed",I101<>"",I101<StatusDate),"OVERDUE","")) | Y101: =IF(OR(A101="",K101=""),"",IF(SUMPRODUCT(($A$6:$A$400<>"")*ISNUMBER(SEARCH($A$6:$A$400,K101))*($G$6:$G$400<>"Completed"))=0,"✓ Ready","⏳ "&SUMPRODUCT(($A$6:$A$400<>"")*ISNUMBER(SEARCH($A$6:$A$400,K101))*($G$6:$G$400<>"Completed"))&" open")) -> ⏳ 2 open | Z101: =IF(A101="","",B101&"|"&COUNTIFS($B$6:B101,B101,$A$6:A101,"?*")) -> Phase 6|7 | AA101: =IF(OR(A101="",I101="",G101="Completed"),"",IF(I101>=StatusDate,I101+ROW()/100000,"")) -> 46321.001 | AB101: =IF(A101="","",IF(AND(G101<>"Completed",OR(G101="Blocked",AND(TRIM(P101)<>"",P101<>"None"))),ROW(),"")) | AC101: =IF(A101="","",IF(G101="Completed","Done",IF(G101="Blocked","Blocked",IF(X101="OVERDUE","Overdue",IF(AND(W101<>"",W101<=2),"Due soon",IF(AND(Y101<>"",LEFT(Y101,1)="⏳",G101<>"Not Started"),"Dependency open",IF(AND(S101<>"None",S101<>"",G101<>"Completed"),"External req.","On track"))))))) -> On track
A102: P6-08 | B102: Phase 6 | C102: URL Validation | D102: Validate all 2,645 article URLs on staging | E102: Crawl/script all inventory URLs against staging (host-swapped): expect 200, same permalink, correct template; list any 404/redirect. | F102: P0 | G102: Not Started | H102: 46321 | I102: 46321 | J102: 0 | K102: P6-05, P3-16 | L102: Staging (Hostinger) | M102: url-inventory.csv | N102: Automated crawl; 0 unexpected 404s | O102: 2,645/2,645 article URLs return 200 with correct content | S102: None | T102: Not Tested | U102: =IF(A102="",0,IF(G102="Completed",1,IF(G102="Not Started",0,MIN(0.99,N(J102))))) -> 0 | V102: =IF(OR(A102="",H102="",I102=""),0,MAX(0,MIN(1,(StatusDate-H102+1)/(I102-H102+1)))) -> 0 | W102: =IF(OR(A102="",I102="",G102="Completed"),"",I102-StatusDate) -> 15 | X102: =IF(A102="","",IF(AND(G102<>"Completed",I102<>"",I102<StatusDate),"OVERDUE","")) | Y102: =IF(OR(A102="",K102=""),"",IF(SUMPRODUCT(($A$6:$A$400<>"")*ISNUMBER(SEARCH($A$6:$A$400,K102))*($G$6:$G$400<>"Completed"))=0,"✓ Ready","⏳ "&SUMPRODUCT(($A$6:$A$400<>"")*ISNUMBER(SEARCH($A$6:$A$400,K102))*($G$6:$G$400<>"Completed"))&" open")) -> ⏳ 2 open | Z102: =IF(A102="","",B102&"|"&COUNTIFS($B$6:B102,B102,$A$6:A102,"?*")) -> Phase 6|8 | AA102: =IF(OR(A102="",I102="",G102="Completed"),"",IF(I102>=StatusDate,I102+ROW()/100000,"")) -> 46321.001 | AB102: =IF(A102="","",IF(AND(G102<>"Completed",OR(G102="Blocked",AND(TRIM(P102)<>"",P102<>"None"))),ROW(),"")) | AC102: =IF(A102="","",IF(G102="Completed","Done",IF(G102="Blocked","Blocked",IF(X102="OVERDUE","Overdue",IF(AND(W102<>"",W102<=2),"Due soon",IF(AND(Y102<>"",LEFT(Y102,1)="⏳",G102<>"Not Started"),"Dependency open",IF(AND(S102<>"None",S102<>"",G102<>"Completed"),"External req.","On track"))))))) -> On track
A103: P6-09 | B103: Phase 6 | C103: SEO | D103: SEO comparison: staging vs baseline | E103: Diff titles, metas, canonicals, H1, schema, robots between staging and baseline; fix regressions. | F103: P0 | G103: Not Started | H103: 46321 | I103: 46322 | J103: 0 | K103: P6-06, P6-08 | L103: Staging (Hostinger) | M103: seo-baseline.csv | N103: Diff report reviewed | O103: No SEO regressions vs baseline | S103: None | T103: Not Tested | U103: =IF(A103="",0,IF(G103="Completed",1,IF(G103="Not Started",0,MIN(0.99,N(J103))))) -> 0 | V103: =IF(OR(A103="",H103="",I103=""),0,MAX(0,MIN(1,(StatusDate-H103+1)/(I103-H103+1)))) -> 0 | W103: =IF(OR(A103="",I103="",G103="Completed"),"",I103-StatusDate) -> 16 | X103: =IF(A103="","",IF(AND(G103<>"Completed",I103<>"",I103<StatusDate),"OVERDUE","")) | Y103: =IF(OR(A103="",K103=""),"",IF(SUMPRODUCT(($A$6:$A$400<>"")*ISNUMBER(SEARCH($A$6:$A$400,K103))*($G$6:$G$400<>"Completed"))=0,"✓ Ready","⏳ "&SUMPRODUCT(($A$6:$A$400<>"")*ISNUMBER(SEARCH($A$6:$A$400,K103))*($G$6:$G$400<>"Completed"))&" open")) -> ⏳ 2 open | Z103: =IF(A103="","",B103&"|"&COUNTIFS($B$6:B103,B103,$A$6:A103,"?*")) -> Phase 6|9 | AA103: =IF(OR(A103="",I103="",G103="Completed"),"",IF(I103>=StatusDate,I103+ROW()/100000,"")) -> 46322.001 | AB103: =IF(A103="","",IF(AND(G103<>"Completed",OR(G103="Blocked",AND(TRIM(P103)<>"",P103<>"None"))),ROW(),"")) | AC103: =IF(A103="","",IF(G103="Completed","Done",IF(G103="Blocked","Blocked",IF(X103="OVERDUE","Overdue",IF(AND(W103<>"",W103<=2),"Due soon",IF(AND(Y103<>"",LEFT(Y103,1)="⏳",G103<>"Not Started"),"Dependency open",IF(AND(S103<>"None",S103<>"",G103<>"Completed"),"External req.","On track"))))))) -> On track
A104: P6-10 | B104: Phase 6 | C104: SEO | D104: 301 redirect map for changed URLs | E104: Map any changed URLs (e.g. JNews-specific pages, issue URLs) to new destinations; implement and test. | F104: P1 | G104: Not Started | H104: 46322 | I104: 46322 | J104: 0 | K104: P6-08 | L104: Staging (Hostinger) | M104: inc/redirects.php or Redirection export | N104: .htaccess / plugin test of each mapping | O104: All changed URLs 301 to correct targets; no chains | S104: None | T104: Not Tested | U104: =IF(A104="",0,IF(G104="Completed",1,IF(G104="Not Started",0,MIN(0.99,N(J104))))) -> 0 | V104: =IF(OR(A104="",H104="",I104=""),0,MAX(0,MIN(1,(StatusDate-H104+1)/(I104-H104+1)))) -> 0 | W104: =IF(OR(A104="",I104="",G104="Completed"),"",I104-StatusDate) -> 16 | X104: =IF(A104="","",IF(AND(G104<>"Completed",I104<>"",I104<StatusDate),"OVERDUE","")) | Y104: =IF(OR(A104="",K104=""),"",IF(SUMPRODUCT(($A$6:$A$400<>"")*ISNUMBER(SEARCH($A$6:$A$400,K104))*($G$6:$G$400<>"Completed"))=0,"✓ Ready","⏳ "&SUMPRODUCT(($A$6:$A$400<>"")*ISNUMBER(SEARCH($A$6:$A$400,K104))*($G$6:$G$400<>"Completed"))&" open")) -> ⏳ 1 open | Z104: =IF(A104="","",B104&"|"&COUNTIFS($B$6:B104,B104,$A$6:A104,"?*")) -> Phase 6|10 | AA104: =IF(OR(A104="",I104="",G104="Completed"),"",IF(I104>=StatusDate,I104+ROW()/100000,"")) -> 46322.001 | AB104: =IF(A104="","",IF(AND(G104<>"Completed",OR(G104="Blocked",AND(TRIM(P104)<>"",P104<>"None"))),ROW(),"")) | AC104: =IF(A104="","",IF(G104="Completed","Done",IF(G104="Blocked","Blocked",IF(X104="OVERDUE","Overdue",IF(AND(W104<>"",W104<=2),"Due soon",IF(AND(Y104<>"",LEFT(Y104,1)="⏳",G104<>"Not Started"),"Dependency open",IF(AND(S104<>"None",S104<>"",G104<>"Completed"),"External req.","On track"))))))) -> On track
A105: P6-11 | B105: Phase 6 | C105: Performance | D105: Performance optimization (Core Web Vitals) | E105: Critical CSS, font preload, image sizes, query counts, defer non-critical JS; targets LCP < 2.5 s, CLS < 0.1, INP < 200 ms on mobile. | F105: P0 | G105: Not Started | H105: 46322 | I105: 46323 | J105: 0 | K105: P2-24, P3-16, P4-12 | L105: Staging (Hostinger) | M105: inc/enqueue.php, assets/* | N105: Lighthouse/PageSpeed on homepage, article, category, issue | O105: Key templates meet Core Web Vitals targets on mobile | S105: None | T105: Not Tested | U105: =IF(A105="",0,IF(G105="Completed",1,IF(G105="Not Started",0,MIN(0.99,N(J105))))) -> 0 | V105: =IF(OR(A105="",H105="",I105=""),0,MAX(0,MIN(1,(StatusDate-H105+1)/(I105-H105+1)))) -> 0 | W105: =IF(OR(A105="",I105="",G105="Completed"),"",I105-StatusDate) -> 17 | X105: =IF(A105="","",IF(AND(G105<>"Completed",I105<>"",I105<StatusDate),"OVERDUE","")) | Y105: =IF(OR(A105="",K105=""),"",IF(SUMPRODUCT(($A$6:$A$400<>"")*ISNUMBER(SEARCH($A$6:$A$400,K105))*($G$6:$G$400<>"Completed"))=0,"✓ Ready","⏳ "&SUMPRODUCT(($A$6:$A$400<>"")*ISNUMBER(SEARCH($A$6:$A$400,K105))*($G$6:$G$400<>"Completed"))&" open")) -> ⏳ 3 open | Z105: =IF(A105="","",B105&"|"&COUNTIFS($B$6:B105,B105,$A$6:A105,"?*")) -> Phase 6|11 | AA105: =IF(OR(A105="",I105="",G105="Completed"),"",IF(I105>=StatusDate,I105+ROW()/100000,"")) -> 46323.001 | AB105: =IF(A105="","",IF(AND(G105<>"Completed",OR(G105="Blocked",AND(TRIM(P105)<>"",P105<>"None"))),ROW(),"")) | AC105: =IF(A105="","",IF(G105="Completed","Done",IF(G105="Blocked","Blocked",IF(X105="OVERDUE","Overdue",IF(AND(W105<>"",W105<=2),"Due soon",IF(AND(Y105<>"",LEFT(Y105,1)="⏳",G105<>"Not Started"),"Dependency open",IF(AND(S105<>"None",S105<>"",G105<>"Completed"),"External req.","On track"))))))) -> On track
A106: P6-12 | B106: Phase 6 | C106: Caching | D106: LiteSpeed Cache configuration | E106: Page cache, object cache (if available), browser cache, CSS/JS minify compatible with theme, image optimization; exclude login/account/checkout/webhook URLs; purge rules for publish. | F106: P0 | G106: Not Started | H106: 46323 | I106: 46323 | J106: 0 | K106: P6-11, P2-08 | L106: Staging (Hostinger) | M106: LiteSpeed Cache settings | N106: Logged-in vs guest caching; checkout not cached; purge on publish | O106: Fast cached pages with no cached private content | S106: Server Access | T106: Not Tested | U106: =IF(A106="",0,IF(G106="Completed",1,IF(G106="Not Started",0,MIN(0.99,N(J106))))) -> 0 | V106: =IF(OR(A106="",H106="",I106=""),0,MAX(0,MIN(1,(StatusDate-H106+1)/(I106-H106+1)))) -> 0 | W106: =IF(OR(A106="",I106="",G106="Completed"),"",I106-StatusDate) -> 17 | X106: =IF(A106="","",IF(AND(G106<>"Completed",I106<>"",I106<StatusDate),"OVERDUE","")) | Y106: =IF(OR(A106="",K106=""),"",IF(SUMPRODUCT(($A$6:$A$400<>"")*ISNUMBER(SEARCH($A$6:$A$400,K106))*($G$6:$G$400<>"Completed"))=0,"✓ Ready","⏳ "&SUMPRODUCT(($A$6:$A$400<>"")*ISNUMBER(SEARCH($A$6:$A$400,K106))*($G$6:$G$400<>"Completed"))&" open")) -> ⏳ 2 open | Z106: =IF(A106="","",B106&"|"&COUNTIFS($B$6:B106,B106,$A$6:A106,"?*")) -> Phase 6|12 | AA106: =IF(OR(A106="",I106="",G106="Completed"),"",IF(I106>=StatusDate,I106+ROW()/100000,"")) -> 46323.001 | AB106: =IF(A106="","",IF(AND(G106<>"Completed",OR(G106="Blocked",AND(TRIM(P106)<>"",P106<>"None"))),ROW(),"")) | AC106: =IF(A106="","",IF(G106="Completed","Done",IF(G106="Blocked","Blocked",IF(X106="OVERDUE","Overdue",IF(AND(W106<>"",W106<=2),"Due soon",IF(AND(Y106<>"",LEFT(Y106,1)="⏳",G106<>"Not Started"),"Dependency open",IF(AND(S106<>"None",S106<>"",G106<>"Completed"),"External req.","On track"))))))) -> External req.
A107: P6-13 | B107: Phase 6 | C107: Testing | D107: Responsive testing | E107: Run QA responsive matrix on all nine templates at 360–1440 px and real devices. | F107: P0 | G107: Not Started | H107: 46323 | I107: 46323 | J107: 0 | K107: P6-11 | L107: Staging (Hostinger) | M107: — | N107: QA sheet: Mobile Responsiveness rows | O107: All templates pass responsive checks | S107: None | T107: Not Tested | U107: =IF(A107="",0,IF(G107="Completed",1,IF(G107="Not Started",0,MIN(0.99,N(J107))))) -> 0 | V107: =IF(OR(A107="",H107="",I107=""),0,MAX(0,MIN(1,(StatusDate-H107+1)/(I107-H107+1)))) -> 0 | W107: =IF(OR(A107="",I107="",G107="Completed"),"",I107-StatusDate) -> 17 | X107: =IF(A107="","",IF(AND(G107<>"Completed",I107<>"",I107<StatusDate),"OVERDUE","")) | Y107: =IF(OR(A107="",K107=""),"",IF(SUMPRODUCT(($A$6:$A$400<>"")*ISNUMBER(SEARCH($A$6:$A$400,K107))*($G$6:$G$400<>"Completed"))=0,"✓ Ready","⏳ "&SUMPRODUCT(($A$6:$A$400<>"")*ISNUMBER(SEARCH($A$6:$A$400,K107))*($G$6:$G$400<>"Completed"))&" open")) -> ⏳ 1 open | Z107: =IF(A107="","",B107&"|"&COUNTIFS($B$6:B107,B107,$A$6:A107,"?*")) -> Phase 6|13 | AA107: =IF(OR(A107="",I107="",G107="Completed"),"",IF(I107>=StatusDate,I107+ROW()/100000,"")) -> 46323.001 | AB107: =IF(A107="","",IF(AND(G107<>"Completed",OR(G107="Blocked",AND(TRIM(P107)<>"",P107<>"None"))),ROW(),"")) | AC107: =IF(A107="","",IF(G107="Completed","Done",IF(G107="Blocked","Blocked",IF(X107="OVERDUE","Overdue",IF(AND(W107<>"",W107<=2),"Due soon",IF(AND(Y107<>"",LEFT(Y107,1)="⏳",G107<>"Not Started"),"Dependency open",IF(AND(S107<>"None",S107<>"",G107<>"Completed"),"External req.","On track"))))))) -> On track
... A116: P6-22 | B116: Phase 6 | C116: Post-launch | D116: Post-launch verification & monitoring | E116: Smoke tests, URL sample crawl, Search Console sitemap resubmit, payments live test, error log and uptime monitoring for 48 h. | F116: P0 | G116: Not Started | H116: 46327 | I116: 46327 | J116: 0 | K116: P6-21 | L116: Production | M116: debug.log, Search Console | N116: Deployment sheet stage 8–9 | O116: No critical issues in first 48 h | S116: None | T116: Not Tested | U116: =IF(A116="",0,IF(G116="Completed",1,IF(G116="Not Started",0,MIN(0.99,N(J116))))) -> 0 | V116: =IF(OR(A116="",H116="",I116=""),0,MAX(0,MIN(1,(StatusDate-H116+1)/(I116-H116+1)))) -> 0 | W116: =IF(OR(A116="",I116="",G116="Completed"),"",I116-StatusDate) -> 21 | X116: =IF(A116="","",IF(AND(G116<>"Completed",I116<>"",I116<StatusDate),"OVERDUE","")) | Y116: =IF(OR(A116="",K116=""),"",IF(SUMPRODUCT(($A$6:$A$400<>"")*ISNUMBER(SEARCH($A$6:$A$400,K116))*($G$6:$G$400<>"Completed"))=0,"✓ Ready","⏳ "&SUMPRODUCT(($A$6:$A$400<>"")*ISNUMBER(SEARCH($A$6:$A$400,K116))*($G$6:$G$400<>"Completed"))&" open")) -> ⏳ 1 open | Z116: =IF(A116="","",B116&"|"&COUNTIFS($B$6:B116,B116,$A$6:A116,"?*")) -> Phase 6|22 | AA116: =IF(OR(A116="",I116="",G116="Completed"),"",IF(I116>=StatusDate,I116+ROW()/100000,"")) -> 46327.001 | AB116: =IF(A116="","",IF(AND(G116<>"Completed",OR(G116="Blocked",AND(TRIM(P116)<>"",P116<>"None"))),ROW(),"")) | AC116: =IF(A116="","",IF(G116="Completed","Done",IF(G116="Blocked","Blocked",IF(X116="OVERDUE","Overdue",IF(AND(W116<>"",W116<=2),"Due soon",IF(AND(Y116<>"",LEFT(Y116,1)="⏳",G116<>"Not Started"),"Dependency open",IF(AND(S116<>"None",S116<>"",G116<>"Completed"),"External req.","On track"))))))) -> On track
U117: =IF(A117="",0,IF(G117="Completed",1,IF(G117="Not Started",0,MIN(0.99,N(J117))))) -> 0 | V117: =IF(OR(A117="",H117="",I117=""),0,MAX(0,MIN(1,(StatusDate-H117+1)/(I117-H117+1)))) -> 0 | W117: =IF(OR(A117="",I117="",G117="Completed"),"",I117-StatusDate) | X117: =IF(A117="","",IF(AND(G117<>"Completed",I117<>"",I117<StatusDate),"OVERDUE","")) | Y117: =IF(OR(A117="",K117=""),"",IF(SUMPRODUCT(($A$6:$A$400<>"")*ISNUMBER(SEARCH($A$6:$A$400,K117))*($G$6:$G$400<>"Completed"))=0,"✓ Ready","⏳ "&SUMPRODUCT(($A$6:$A$400<>"")*ISNUMBER(SEARCH($A$6:$A$400,K117))*($G$6:$G$400<>"Completed"))&" open")) | Z117: =IF(A117="","",B117&"|"&COUNTIFS($B$6:B117,B117,$A$6:A117,"?*")) | AA117: =IF(OR(A117="",I117="",G117="Completed"),"",IF(I117>=StatusDate,I117+ROW()/100000,"")) | AB117: =IF(A117="","",IF(AND(G117<>"Completed",OR(G117="Blocked",AND(TRIM(P117)<>"",P117<>"None"))),ROW(),"")) | AC117: =IF(A117="","",IF(G117="Completed","Done",IF(G117="Blocked","Blocked",IF(X117="OVERDUE","Overdue",IF(AND(W117<>"",W117<=2),"Due soon",IF(AND(Y117<>"",LEFT(Y117,1)="⏳",G117<>"Not Started"),"Dependency open",IF(AND(S117<>"None",S117<>"",G117<>"Completed"),"External req.","On track")))))))
U118: =IF(A118="",0,IF(G118="Completed",1,IF(G118="Not Started",0,MIN(0.99,N(J118))))) -> 0 | V118: =IF(OR(A118="",H118="",I118=""),0,MAX(0,MIN(1,(StatusDate-H118+1)/(I118-H118+1)))) -> 0 | W118: =IF(OR(A118="",I118="",G118="Completed"),"",I118-StatusDate) | X118: =IF(A118="","",IF(AND(G118<>"Completed",I118<>"",I118<StatusDate),"OVERDUE","")) | Y118: =IF(OR(A118="",K118=""),"",IF(SUMPRODUCT(($A$6:$A$400<>"")*ISNUMBER(SEARCH($A$6:$A$400,K118))*($G$6:$G$400<>"Completed"))=0,"✓ Ready","⏳ "&SUMPRODUCT(($A$6:$A$400<>"")*ISNUMBER(SEARCH($A$6:$A$400,K118))*($G$6:$G$400<>"Completed"))&" open")) | Z118: =IF(A118="","",B118&"|"&COUNTIFS($B$6:B118,B118,$A$6:A118,"?*")) | AA118: =IF(OR(A118="",I118="",G118="Completed"),"",IF(I118>=StatusDate,I118+ROW()/100000,"")) | AB118: =IF(A118="","",IF(AND(G118<>"Completed",OR(G118="Blocked",AND(TRIM(P118)<>"",P118<>"None"))),ROW(),"")) | AC118: =IF(A118="","",IF(G118="Completed","Done",IF(G118="Blocked","Blocked",IF(X118="OVERDUE","Overdue",IF(AND(W118<>"",W118<=2),"Due soon",IF(AND(Y118<>"",LEFT(Y118,1)="⏳",G118<>"Not Started"),"Dependency open",IF(AND(S118<>"None",S118<>"",G118<>"Completed"),"External req.","On track")))))))
U119: =IF(A119="",0,IF(G119="Completed",1,IF(G119="Not Started",0,MIN(0.99,N(J119))))) -> 0 | V119: =IF(OR(A119="",H119="",I119=""),0,MAX(0,MIN(1,(StatusDate-H119+1)/(I119-H119+1)))) -> 0 | W119: =IF(OR(A119="",I119="",G119="Completed"),"",I119-StatusDate) | X119: =IF(A119="","",IF(AND(G119<>"Completed",I119<>"",I119<StatusDate),"OVERDUE","")) | Y119: =IF(OR(A119="",K119=""),"",IF(SUMPRODUCT(($A$6:$A$400<>"")*ISNUMBER(SEARCH($A$6:$A$400,K119))*($G$6:$G$400<>"Completed"))=0,"✓ Ready","⏳ "&SUMPRODUCT(($A$6:$A$400<>"")*ISNUMBER(SEARCH($A$6:$A$400,K119))*($G$6:$G$400<>"Completed"))&" open")) | Z119: =IF(A119="","",B119&"|"&COUNTIFS($B$6:B119,B119,$A$6:A119,"?*")) | AA119: =IF(OR(A119="",I119="",G119="Completed"),"",IF(I119>=StatusDate,I119+ROW()/100000,"")) | AB119: =IF(A119="","",IF(AND(G119<>"Completed",OR(G119="Blocked",AND(TRIM(P119)<>"",P119<>"None"))),ROW(),"")) | AC119: =IF(A119="","",IF(G119="Completed","Done",IF(G119="Blocked","Blocked",IF(X119="OVERDUE","Overdue",IF(AND(W119<>"",W119<=2),"Due soon",IF(AND(Y119<>"",LEFT(Y119,1)="⏳",G119<>"Not Started"),"Dependency open",IF(AND(S119<>"None",S119<>"",G119<>"Completed"),"External req.","On track")))))))
U120: =IF(A120="",0,IF(G120="Completed",1,IF(G120="Not Started",0,MIN(0.99,N(J120))))) -> 0 | V120: =IF(OR(A120="",H120="",I120=""),0,MAX(0,MIN(1,(StatusDate-H120+1)/(I120-H120+1)))) -> 0 | W120: =IF(OR(A120="",I120="",G120="Completed"),"",I120-StatusDate) | X120: =IF(A120="","",IF(AND(G120<>"Completed",I120<>"",I120<StatusDate),"OVERDUE","")) | Y120: =IF(OR(A120="",K120=""),"",IF(SUMPRODUCT(($A$6:$A$400<>"")*ISNUMBER(SEARCH($A$6:$A$400,K120))*($G$6:$G$400<>"Completed"))=0,"✓ Ready","⏳ "&SUMPRODUCT(($A$6:$A$400<>"")*ISNUMBER(SEARCH($A$6:$A$400,K120))*($G$6:$G$400<>"Completed"))&" open")) | Z120: =IF(A120="","",B120&"|"&COUNTIFS($B$6:B120,B120,$A$6:A120,"?*")) | AA120: =IF(OR(A120="",I120="",G120="Completed"),"",IF(I120>=StatusDate,I120+ROW()/100000,"")) | AB120: =IF(A120="","",IF(AND(G120<>"Completed",OR(G120="Blocked",AND(TRIM(P120)<>"",P120<>"None"))),ROW(),"")) | AC120: =IF(A120="","",IF(G120="Completed","Done",IF(G120="Blocked","Blocked",IF(X120="OVERDUE","Overdue",IF(AND(W120<>"",W120<=2),"Due soon",IF(AND(Y120<>"",LEFT(Y120,1)="⏳",G120<>"Not Started"),"Dependency open",IF(AND(S120<>"None",S120<>"",G120<>"Completed"),"External req.","On track")))))))
U121: =IF(A121="",0,IF(G121="Completed",1,IF(G121="Not Started",0,MIN(0.99,N(J121))))) -> 0 | V121: =IF(OR(A121="",H121="",I121=""),0,MAX(0,MIN(1,(StatusDate-H121+1)/(I121-H121+1)))) -> 0 | W121: =IF(OR(A121="",I121="",G121="Completed"),"",I121-StatusDate) | X121: =IF(A121="","",IF(AND(G121<>"Completed",I121<>"",I121<StatusDate),"OVERDUE","")) | Y121: =IF(OR(A121="",K121=""),"",IF(SUMPRODUCT(($A$6:$A$400<>"")*ISNUMBER(SEARCH($A$6:$A$400,K121))*($G$6:$G$400<>"Completed"))=0,"✓ Ready","⏳ "&SUMPRODUCT(($A$6:$A$400<>"")*ISNUMBER(SEARCH($A$6:$A$400,K121))*($G$6:$G$400<>"Completed"))&" open")) | Z121: =IF(A121="","",B121&"|"&COUNTIFS($B$6:B121,B121,$A$6:A121,"?*")) | AA121: =IF(OR(A121="",I121="",G121="Completed"),"",IF(I121>=StatusDate,I121+ROW()/100000,"")) | AB121: =IF(A121="","",IF(AND(G121<>"Completed",OR(G121="Blocked",AND(TRIM(P121)<>"",P121<>"None"))),ROW(),"")) | AC121: =IF(A121="","",IF(G121="Completed","Done",IF(G121="Blocked","Blocked",IF(X121="OVERDUE","Overdue",IF(AND(W121<>"",W121<=2),"Due soon",IF(AND(Y121<>"",LEFT(Y121,1)="⏳",G121<>"Not Started"),"Dependency open",IF(AND(S121<>"None",S121<>"",G121<>"Completed"),"External req.","On track")))))))
U122: =IF(A122="",0,IF(G122="Completed",1,IF(G122="Not Started",0,MIN(0.99,N(J122))))) -> 0 | V122: =IF(OR(A122="",H122="",I122=""),0,MAX(0,MIN(1,(StatusDate-H122+1)/(I122-H122+1)))) -> 0 | W122: =IF(OR(A122="",I122="",G122="Completed"),"",I122-StatusDate) | X122: =IF(A122="","",IF(AND(G122<>"Completed",I122<>"",I122<StatusDate),"OVERDUE","")) | Y122: =IF(OR(A122="",K122=""),"",IF(SUMPRODUCT(($A$6:$A$400<>"")*ISNUMBER(SEARCH($A$6:$A$400,K122))*($G$6:$G$400<>"Completed"))=0,"✓ Ready","⏳ "&SUMPRODUCT(($A$6:$A$400<>"")*ISNUMBER(SEARCH($A$6:$A$400,K122))*($G$6:$G$400<>"Completed"))&" open")) | Z122: =IF(A122="","",B122&"|"&COUNTIFS($B$6:B122,B122,$A$6:A122,"?*")) | AA122: =IF(OR(A122="",I122="",G122="Completed"),"",IF(I122>=StatusDate,I122+ROW()/100000,"")) | AB122: =IF(A122="","",IF(AND(G122<>"Completed",OR(G122="Blocked",AND(TRIM(P122)<>"",P122<>"None"))),ROW(),"")) | AC122: =IF(A122="","",IF(G122="Completed","Done",IF(G122="Blocked","Blocked",IF(X122="OVERDUE","Overdue",IF(AND(W122<>"",W122<=2),"Due soon",IF(AND(Y122<>"",LEFT(Y122,1)="⏳",G122<>"Not Started"),"Dependency open",IF(AND(S122<>"None",S122<>"",G122<>"Completed"),"External req.","On track")))))))
U123: =IF(A123="",0,IF(G123="Completed",1,IF(G123="Not Started",0,MIN(0.99,N(J123))))) -> 0 | V123: =IF(OR(A123="",H123="",I123=""),0,MAX(0,MIN(1,(StatusDate-H123+1)/(I123-H123+1)))) -> 0 | W123: =IF(OR(A123="",I123="",G123="Completed"),"",I123-StatusDate) | X123: =IF(A123="","",IF(AND(G123<>"Completed",I123<>"",I123<StatusDate),"OVERDUE","")) | Y123: =IF(OR(A123="",K123=""),"",IF(SUMPRODUCT(($A$6:$A$400<>"")*ISNUMBER(SEARCH($A$6:$A$400,K123))*($G$6:$G$400<>"Completed"))=0,"✓ Ready","⏳ "&SUMPRODUCT(($A$6:$A$400<>"")*ISNUMBER(SEARCH($A$6:$A$400,K123))*($G$6:$G$400<>"Completed"))&" open")) | Z123: =IF(A123="","",B123&"|"&COUNTIFS($B$6:B123,B123,$A$6:A123,"?*")) | AA123: =IF(OR(A123="",I123="",G123="Completed"),"",IF(I123>=StatusDate,I123+ROW()/100000,"")) | AB123: =IF(A123="","",IF(AND(G123<>"Completed",OR(G123="Blocked",AND(TRIM(P123)<>"",P123<>"None"))),ROW(),"")) | AC123: =IF(A123="","",IF(G123="Completed","Done",IF(G123="Blocked","Blocked",IF(X123="OVERDUE","Overdue",IF(AND(W123<>"",W123<=2),"Due soon",IF(AND(Y123<>"",LEFT(Y123,1)="⏳",G123<>"Not Started"),"Dependency open",IF(AND(S123<>"None",S123<>"",G123<>"Completed"),"External req.","On track")))))))
U124: =IF(A124="",0,IF(G124="Completed",1,IF(G124="Not Started",0,MIN(0.99,N(J124))))) -> 0 | V124: =IF(OR(A124="",H124="",I124=""),0,MAX(0,MIN(1,(StatusDate-H124+1)/(I124-H124+1)))) -> 0 | W124: =IF(OR(A124="",I124="",G124="Completed"),"",I124-StatusDate) | X124: =IF(A124="","",IF(AND(G124<>"Completed",I124<>"",I124<StatusDate),"OVERDUE","")) | Y124: =IF(OR(A124="",K124=""),"",IF(SUMPRODUCT(($A$6:$A$400<>"")*ISNUMBER(SEARCH($A$6:$A$400,K124))*($G$6:$G$400<>"Completed"))=0,"✓ Ready","⏳ "&SUMPRODUCT(($A$6:$A$400<>"")*ISNUMBER(SEARCH($A$6:$A$400,K124))*($G$6:$G$400<>"Completed"))&" open")) | Z124: =IF(A124="","",B124&"|"&COUNTIFS($B$6:B124,B124,$A$6:A124,"?*")) | AA124: =IF(OR(A124="",I124="",G124="Completed"),"",IF(I124>=StatusDate,I124+ROW()/100000,"")) | AB124: =IF(A124="","",IF(AND(G124<>"Completed",OR(G124="Blocked",AND(TRIM(P124)<>"",P124<>"None"))),ROW(),"")) | AC124: =IF(A124="","",IF(G124="Completed","Done",IF(G124="Blocked","Blocked",IF(X124="OVERDUE","Overdue",IF(AND(W124<>"",W124<=2),"Due soon",IF(AND(Y124<>"",LEFT(Y124,1)="⏳",G124<>"Not Started"),"Dependency open",IF(AND(S124<>"None",S124<>"",G124<>"Completed"),"External req.","On track")))))))
U125: =IF(A125="",0,IF(G125="Completed",1,IF(G125="Not Started",0,MIN(0.99,N(J125))))) -> 0 | V125: =IF(OR(A125="",H125="",I125=""),0,MAX(0,MIN(1,(StatusDate-H125+1)/(I125-H125+1)))) -> 0 | W125: =IF(OR(A125="",I125="",G125="Completed"),"",I125-StatusDate) | X125: =IF(A125="","",IF(AND(G125<>"Completed",I125<>"",I125<StatusDate),"OVERDUE","")) | Y125: =IF(OR(A125="",K125=""),"",IF(SUMPRODUCT(($A$6:$A$400<>"")*ISNUMBER(SEARCH($A$6:$A$400,K125))*($G$6:$G$400<>"Completed"))=0,"✓ Ready","⏳ "&SUMPRODUCT(($A$6:$A$400<>"")*ISNUMBER(SEARCH($A$6:$A$400,K125))*($G$6:$G$400<>"Completed"))&" open")) | Z125: =IF(A125="","",B125&"|"&COUNTIFS($B$6:B125,B125,$A$6:A125,"?*")) | AA125: =IF(OR(A125="",I125="",G125="Completed"),"",IF(I125>=StatusDate,I125+ROW()/100000,"")) | AB125: =IF(A125="","",IF(AND(G125<>"Completed",OR(G125="Blocked",AND(TRIM(P125)<>"",P125<>"None"))),ROW(),"")) | AC125: =IF(A125="","",IF(G125="Completed","Done",IF(G125="Blocked","Blocked",IF(X125="OVERDUE","Overdue",IF(AND(W125<>"",W125<=2),"Due soon",IF(AND(Y125<>"",LEFT(Y125,1)="⏳",G125<>"Not Started"),"Dependency open",IF(AND(S125<>"None",S125<>"",G125<>"Completed"),"External req.","On track")))))))
U126: =IF(A126="",0,IF(G126="Completed",1,IF(G126="Not Started",0,MIN(0.99,N(J126))))) -> 0 | V126: =IF(OR(A126="",H126="",I126=""),0,MAX(0,MIN(1,(StatusDate-H126+1)/(I126-H126+1)))) -> 0 | W126: =IF(OR(A126="",I126="",G126="Completed"),"",I126-StatusDate) | X126: =IF(A126="","",IF(AND(G126<>"Completed",I126<>"",I126<StatusDate),"OVERDUE","")) | Y126: =IF(OR(A126="",K126=""),"",IF(SUMPRODUCT(($A$6:$A$400<>"")*ISNUMBER(SEARCH($A$6:$A$400,K126))*($G$6:$G$400<>"Completed"))=0,"✓ Ready","⏳ "&SUMPRODUCT(($A$6:$A$400<>"")*ISNUMBER(SEARCH($A$6:$A$400,K126))*($G$6:$G$400<>"Completed"))&" open")) | Z126: =IF(A126="","",B126&"|"&COUNTIFS($B$6:B126,B126,$A$6:A126,"?*")) | AA126: =IF(OR(A126="",I126="",G126="Completed"),"",IF(I126>=StatusDate,I126+ROW()/100000,"")) | AB126: =IF(A126="","",IF(AND(G126<>"Completed",OR(G126="Blocked",AND(TRIM(P126)<>"",P126<>"None"))),ROW(),"")) | AC126: =IF(A126="","",IF(G126="Completed","Done",IF(G126="Blocked","Blocked",IF(X126="OVERDUE","Overdue",IF(AND(W126<>"",W126<=2),"Due soon",IF(AND(Y126<>"",LEFT(Y126,1)="⏳",G126<>"Not Started"),"Dependency open",IF(AND(S126<>"None",S126<>"",G126<>"Completed"),"External req.","On track")))))))
U127: =IF(A127="",0,IF(G127="Completed",1,IF(G127="Not Started",0,MIN(0.99,N(J127))))) -> 0 | V127: =IF(OR(A127="",H127="",I127=""),0,MAX(0,MIN(1,(StatusDate-H127+1)/(I127-H127+1)))) -> 0 | W127: =IF(OR(A127="",I127="",G127="Completed"),"",I127-StatusDate) | X127: =IF(A127="","",IF(AND(G127<>"Completed",I127<>"",I127<StatusDate),"OVERDUE","")) | Y127: =IF(OR(A127="",K127=""),"",IF(SUMPRODUCT(($A$6:$A$400<>"")*ISNUMBER(SEARCH($A$6:$A$400,K127))*($G$6:$G$400<>"Completed"))=0,"✓ Ready","⏳ "&SUMPRODUCT(($A$6:$A$400<>"")*ISNUMBER(SEARCH($A$6:$A$400,K127))*($G$6:$G$400<>"Completed"))&" open")) | Z127: =IF(A127="","",B127&"|"&COUNTIFS($B$6:B127,B127,$A$6:A127,"?*")) | AA127: =IF(OR(A127="",I127="",G127="Completed"),"",IF(I127>=StatusDate,I127+ROW()/100000,"")) | AB127: =IF(A127="","",IF(AND(G127<>"Completed",OR(G127="Blocked",AND(TRIM(P127)<>"",P127<>"None"))),ROW(),"")) | AC127: =IF(A127="","",IF(G127="Completed","Done",IF(G127="Blocked","Blocked",IF(X127="OVERDUE","Overdue",IF(AND(W127<>"",W127<=2),"Due soon",IF(AND(Y127<>"",LEFT(Y127,1)="⏳",G127<>"Not Started"),"Dependency open",IF(AND(S127<>"None",S127<>"",G127<>"Completed"),"External req.","On track")))))))
U128: =IF(A128="",0,IF(G128="Completed",1,IF(G128="Not Started",0,MIN(0.99,N(J128))))) -> 0 | V128: =IF(OR(A128="",H128="",I128=""),0,MAX(0,MIN(1,(StatusDate-H128+1)/(I128-H128+1)))) -> 0 | W128: =IF(OR(A128="",I128="",G128="Completed"),"",I128-StatusDate) | X128: =IF(A128="","",IF(AND(G128<>"Completed",I128<>"",I128<StatusDate),"OVERDUE","")) | Y128: =IF(OR(A128="",K128=""),"",IF(SUMPRODUCT(($A$6:$A$400<>"")*ISNUMBER(SEARCH($A$6:$A$400,K128))*($G$6:$G$400<>"Completed"))=0,"✓ Ready","⏳ "&SUMPRODUCT(($A$6:$A$400<>"")*ISNUMBER(SEARCH($A$6:$A$400,K128))*($G$6:$G$400<>"Completed"))&" open")) | Z128: =IF(A128="","",B128&"|"&COUNTIFS($B$6:B128,B128,$A$6:A128,"?*")) | AA128: =IF(OR(A128="",I128="",G128="Completed"),"",IF(I128>=StatusDate,I128+ROW()/100000,"")) | AB128: =IF(A128="","",IF(AND(G128<>"Completed",OR(G128="Blocked",AND(TRIM(P128)<>"",P128<>"None"))),ROW(),"")) | AC128: =IF(A128="","",IF(G128="Completed","Done",IF(G128="Blocked","Blocked",IF(X128="OVERDUE","Overdue",IF(AND(W128<>"",W128<=2),"Due soon",IF(AND(Y128<>"",LEFT(Y128,1)="⏳",G128<>"Not Started"),"Dependency open",IF(AND(S128<>"None",S128<>"",G128<>"Completed"),"External req.","On track")))))))
... U146: =IF(A146="",0,IF(G146="Completed",1,IF(G146="Not Started",0,MIN(0.99,N(J146))))) -> 0 | V146: =IF(OR(A146="",H146="",I146=""),0,MAX(0,MIN(1,(StatusDate-H146+1)/(I146-H146+1)))) -> 0 | W146: =IF(OR(A146="",I146="",G146="Completed"),"",I146-StatusDate) | X146: =IF(A146="","",IF(AND(G146<>"Completed",I146<>"",I146<StatusDate),"OVERDUE","")) | Y146: =IF(OR(A146="",K146=""),"",IF(SUMPRODUCT(($A$6:$A$400<>"")*ISNUMBER(SEARCH($A$6:$A$400,K146))*($G$6:$G$400<>"Completed"))=0,"✓ Ready","⏳ "&SUMPRODUCT(($A$6:$A$400<>"")*ISNUMBER(SEARCH($A$6:$A$400,K146))*($G$6:$G$400<>"Completed"))&" open")) | Z146: =IF(A146="","",B146&"|"&COUNTIFS($B$6:B146,B146,$A$6:A146,"?*")) | AA146: =IF(OR(A146="",I146="",G146="Completed"),"",IF(I146>=StatusDate,I146+ROW()/100000,"")) | AB146: =IF(A146="","",IF(AND(G146<>"Completed",OR(G146="Blocked",AND(TRIM(P146)<>"",P146<>"None"))),ROW(),"")) | AC146: =IF(A146="","",IF(G146="Completed","Done",IF(G146="Blocked","Blocked",IF(X146="OVERDUE","Overdue",IF(AND(W146<>"",W146<=2),"Due soon",IF(AND(Y146<>"",LEFT(Y146,1)="⏳",G146<>"Not Started"),"Dependency open",IF(AND(S146<>"None",S146<>"",G146<>"Completed"),"External req.","On track")))))))

Sheet P1 Theme Foundation
A1: PHASE 1 — THEME FOUNDATION & ASSET PIPELINE
A2: Window 12 Oct – 14 Oct 2026 · Status is read live from the Master Tracker (edit there)
A3: ← Dashboard | D3: Open Master Tracker → | F3: Staging ↗
A5: COMPLETION | D5: PLANNED | E5: TASKS | G5: DONE | H5: IN PROGRESS | J5: BLOCKED | L5: OVERDUE | M5: IN REVIEW / TEST | N5: OPEN P0 | O5: DEADLINE | P5: PHASE STATUS
A6: =IFERROR(SUMPRODUCT(('Master Tracker'!$B$6:$B$400="Phase 1")*'Master Tracker'!$U$6:$U$400)/COUNTIFS('Master Tracker'!$B$6:$B$400,"Phase 1",'Master Tracker'!$A$6:$A$400,"?*"),0) -> 0.11764706 | D6: =IFERROR(SUMPRODUCT(('Master Tracker'!$B$6:$B$400="Phase 1")*'Master Tracker'!$V$6:$V$400)/COUNTIFS('Master Tracker'!$B$6:$B$400,"Phase 1",'Master Tracker'!$A$6:$A$400,"?*"),0) -> 0 | E6: =COUNTIFS('Master Tracker'!$B$6:$B$400,"Phase 1",'Master Tracker'!$A$6:$A$400,"?*") -> 17 | G6: =COUNTIFS('Master Tracker'!$B$6:$B$400,"Phase 1",'Master Tracker'!$G$6:$G$400,"Completed") -> 2 | H6: =COUNTIFS('Master Tracker'!$B$6:$B$400,"Phase 1",'Master Tracker'!$G$6:$G$400,"In Progress") -> 0 | J6: =COUNTIFS('Master Tracker'!$B$6:$B$400,"Phase 1",'Master Tracker'!$G$6:$G$400,"Blocked") -> 0 | L6: =COUNTIFS('Master Tracker'!$B$6:$B$400,"Phase 1",'Master Tracker'!$X$6:$X$400,"OVERDUE") -> 0 | M6: =COUNTIFS('Master Tracker'!$B$6:$B$400,"Phase 1",'Master Tracker'!$G$6:$G$400,"In Review")+COUNTIFS('Master Tracker'!$B$6:$B$400,"Phase 1",'Master Tracker'!$G$6:$G$400,"Testing") -> 0 | N6: =COUNTIFS('Master Tracker'!$B$6:$B$400,"Phase 1",'Master Tracker'!$F$6:$F$400,"P0",'Master Tracker'!$G$6:$G$400,"<>Completed",'Master Tracker'!$A$6:$A$400,"?*") -> 12 | O6: =_xlfn.MAXIFS('Master Tracker'!$I$6:$I$400,'Master Tracker'!$B$6:$B$400,"Phase 1") -> 46309 | P6: =IF(E6=0,"—",IF(G6=E6,"Complete",IF(J6>0,"Blocked",IF(L6>0,"Behind",IF(A6+0.1<D6,"Behind",IF(A6>0,"On Track","Not Started")))))) -> On Track
A7: ="Progress "&REPT("█",ROUND(A6*50,0))&REPT("░",50-ROUND(A6*50,0))&" "&TEXT(A6,"0%")&" (planned "&TEXT(D6,"0%")&")" -> Progress ██████░░░░░░░░░░░░░░░░░░░░░░░░░░░░░░░░░░░░░░░░░░░░ 12% (planned 0%)
A9: PHASE GOAL
A10: Build a clean, dependency-free custom WordPress theme (replacing JNews) with a modular PHP template system, a token-based CSS architecture, Vanilla JS modules, first-class Arabic RTL typography, responsive layouts, and performance primitives (query caching, Arabic date helpers) that every later phase reuses.
A12: DELIVERABLES | J12: REQUIRED WORDPRESS FILES
A13: ▸ Custom theme 'altijara' activated on staging | J13: ▸ style.css
A14: ▸ Theme initialization (supports, menus, image sizes, text domain) | J14: ▸ functions.php
A15: ▸ Base PHP template hierarchy + reusable components | J15: ▸ inc/setup.php
A16: ▸ CSS token architecture & Vanilla JS module system | J16: ▸ inc/enqueue.php
A17: ▸ RTL Arabic typography and responsive grid | J17: ▸ inc/cache.php
A18: ▸ Header / navigation / footer | J18: ▸ inc/helpers-date.php
A19: ▸ Query caching layer + Arabic date helpers | J19: ▸ inc/media.php
A20: ▸ Git repository of theme (backup of staging work) | J20: ▸ inc/widgets.php
J21: ▸ header.php / footer.php
J22: ▸ index.php, front-page.php, single.php, page.php
J23: ▸ archive.php, category.php, tag.php, author.php, search.php, 404.php
J24: ▸ template-parts/components/*.php
J25: ▸ assets/css/*.css, assets/js/*.js, assets/fonts/*
A27: TECHNICAL IMPLEMENTATION STEPS
A28: 1 | B28: Audit staging access (hPanel, SFTP/SSH, phpMyAdmin), block indexing, enable debug log
A29: 2 | B29: Scaffold /wp-content/themes/altijara/ and commit to Git
A30: 3 | B30: Write inc/setup.php (theme supports, menus, image sizes)
A31: 4 | B31: Write inc/enqueue.php with filemtime versioning and conditional loading
A32: 5 | B32: Create template hierarchy skeletons and template-parts/components
A33: 6 | B33: Build tokens.css → base → layout → components → utilities using logical properties
A34: 7 | B34: Build main.js module loader (nav, drawer, search) without jQuery
A35: 8 | B35: Self-host Arabic WOFF2 fonts, set dir=rtl / lang=ar
A36: 9 | B36: Implement inc/cache.php with publish-time invalidation
A37: 10 | B37: Implement inc/helpers-date.php; verify with Query Monitor and debug.log
A39: DETAILED TASK CHECKLIST (live from Master Tracker — change Status / % there)
A40: # | B40: Task ID | C40: Module | D40: Task | E40: Priority | F40: Status | G40: Start | H40: Due | I40: Complete | J40: Dependencies | K40: Dep. check | L40: WordPress files | M40: Acceptance criteria | N40: Testing checklist | O40: Test result | P40: Alert
A41: 1 | B41: =IF($S41="","",IF(INDEX('Master Tracker'!$A$6:$A$400,$S41)="","",INDEX('Master Tracker'!$A$6:$A$400,$S41))) -> P1-01 | C41: =IF($S41="","",IF(INDEX('Master Tracker'!$C$6:$C$400,$S41)="","",INDEX('Master Tracker'!$C$6:$C$400,$S41))) -> Staging Setup | D41: =IF($S41="","",IF(INDEX('Master Tracker'!$D$6:$D$400,$S41)="","",INDEX('Master Tracker'!$D$6:$D$400,$S41))) -> Staging environment readiness audit | E41: =IF($S41="","",IF(INDEX('Master Tracker'!$F$6:$F$400,$S41)="","",INDEX('Master Tracker'!$F$6:$F$400,$S41))) -> P0 | F41: =IF($S41="","",IF(INDEX('Master Tracker'!$G$6:$G$400,$S41)="","",INDEX('Master Tracker'!$G$6:$G$400,$S41))) -> Completed | G41: =IF($S41="","",IF(INDEX('Master Tracker'!$H$6:$H$400,$S41)="","",INDEX('Master Tracker'!$H$6:$H$400,$S41))) -> 46307 | H41: =IF($S41="","",IF(INDEX('Master Tracker'!$I$6:$I$400,$S41)="","",INDEX('Master Tracker'!$I$6:$I$400,$S41))) -> 46307 | I41: =IF($S41="","",IF(INDEX('Master Tracker'!$U$6:$U$400,$S41)="","",INDEX('Master Tracker'!$U$6:$U$400,$S41))) -> 1 | J41: =IF($S41="","",IF(INDEX('Master Tracker'!$K$6:$K$400,$S41)="","",INDEX('Master Tracker'!$K$6:$K$400,$S41))) -> P6-02 | K41: =IF($S41="","",IF(INDEX('Master Tracker'!$Y$6:$Y$400,$S41)="","",INDEX('Master Tracker'!$Y$6:$Y$400,$S41))) -> ⏳ 1 open | L41: =IF($S41="","",IF(INDEX('Master Tracker'!$M$6:$M$400,$S41)="","",INDEX('Master Tracker'!$M$6:$M$400,$S41))) -> wp-config.php, .htaccess | M41: =IF($S41="","",IF(INDEX('Master Tracker'!$O$6:$O$400,$S41)="","",INDEX('Master Tracker'!$O$6:$O$400,$S41))) -> Staging is reachable only by the team, not indexed, debug logging active, versions documented in Notes | N41: =IF($S41="","",IF(INDEX('Master Tracker'!$N$6:$N$400,$S41)="","",INDEX('Master Tracker'!$N$6:$N$400,$S41))) -> Log in via hPanel, SFTP and phpMyAdmin; confirm noindex header; send test mail is trapped | O41: =IF($S41="","",IF(INDEX('Master Tracker'!$T$6:$T$400,$S41)="","",INDEX('Master Tracker'!$T$6:$T$400,$S41))) -> Not Tested | P41: =IF($S41="","",IF(INDEX('Master Tracker'!$AC$6:$AC$400,$S41)="","",INDEX('Master Tracker'!$AC$6:$AC$400,$S41))) -> Done | S41: =IFERROR(MATCH("Phase 1|"&A41,'Master Tracker'!$Z$6:$Z$400,0),"") -> 1
A42: 2 | B42: =IF($S42="","",IF(INDEX('Master Tracker'!$A$6:$A$400,$S42)="","",INDEX('Master Tracker'!$A$6:$A$400,$S42))) -> P1-02 | C42: =IF($S42="","",IF(INDEX('Master Tracker'!$C$6:$C$400,$S42)="","",INDEX('Master Tracker'!$C$6:$C$400,$S42))) -> Theme Scaffold | D42: =IF($S42="","",IF(INDEX('Master Tracker'!$D$6:$D$400,$S42)="","",INDEX('Master Tracker'!$D$6:$D$400,$S42))) -> Create custom theme structure + Git repo | E42: =IF($S42="","",IF(INDEX('Master Tracker'!$F$6:$F$400,$S42)="","",INDEX('Master Tracker'!$F$6:$F$400,$S42))) -> P0 | F42: =IF($S42="","",IF(INDEX('Master Tracker'!$G$6:$G$400,$S42)="","",INDEX('Master Tracker'!$G$6:$G$400,$S42))) -> Completed | G42: =IF($S42="","",IF(INDEX('Master Tracker'!$H$6:$H$400,$S42)="","",INDEX('Master Tracker'!$H$6:$H$400,$S42))) -> 46307 | H42: =IF($S42="","",IF(INDEX('Master Tracker'!$I$6:$I$400,$S42)="","",INDEX('Master Tracker'!$I$6:$I$400,$S42))) -> 46307 | I42: =IF($S42="","",IF(INDEX('Master Tracker'!$U$6:$U$400,$S42)="","",INDEX('Master Tracker'!$U$6:$U$400,$S42))) -> 1 | J42: =IF($S42="","",IF(INDEX('Master Tracker'!$K$6:$K$400,$S42)="","",INDEX('Master Tracker'!$K$6:$K$400,$S42))) -> P1-01 | K42: =IF($S42="","",IF(INDEX('Master Tracker'!$Y$6:$Y$400,$S42)="","",INDEX('Master Tracker'!$Y$6:$Y$400,$S42))) -> ✓ Ready | L42: =IF($S42="","",IF(INDEX('Master Tracker'!$M$6:$M$400,$S42)="","",INDEX('Master Tracker'!$M$6:$M$400,$S42))) -> style.css, functions.php, inc/, template-parts/, assets/ | M42: =IF($S42="","",IF(INDEX('Master Tracker'!$O$6:$O$400,$S42)="","",INDEX('Master Tracker'!$O$6:$O$400,$S42))) -> Folder structure in place, theme activates cleanly on staging, repository holds initial commit | N42: =IF($S42="","",IF(INDEX('Master Tracker'!$N$6:$N$400,$S42)="","",INDEX('Master Tracker'!$N$6:$N$400,$S42))) -> Theme listed in Appearance > Themes; activates with no PHP notices; first commit pushed | O42: =IF($S42="","",IF(INDEX('Master Tracker'!$T$6:$T$400,$S42)="","",INDEX('Master Tracker'!$T$6:$T$400,$S42))) -> Not Tested | P42: =IF($S42="","",IF(INDEX('Master Tracker'!$AC$6:$AC$400,$S42)="","",INDEX('Master Tracker'!$AC$6:$AC$400,$S42))) -> Done | S42: =IFERROR(MATCH("Phase 1|"&A42,'Master Tracker'!$Z$6:$Z$400,0),"") -> 2
A43: 3 | B43: =IF($S43="","",IF(INDEX('Master Tracker'!$A$6:$A$400,$S43)="","",INDEX('Master Tracker'!$A$6:$A$400,$S43))) -> P1-03 | C43: =IF($S43="","",IF(INDEX('Master Tracker'!$C$6:$C$400,$S43)="","",INDEX('Master Tracker'!$C$6:$C$400,$S43))) -> Theme Initialization | D43: =IF($S43="","",IF(INDEX('Master Tracker'!$D$6:$D$400,$S43)="","",INDEX('Master Tracker'!$D$6:$D$400,$S43))) -> Theme setup: supports, menus, image sizes | E43: =IF($S43="","",IF(INDEX('Master Tracker'!$F$6:$F$400,$S43)="","",INDEX('Master Tracker'!$F$6:$F$400,$S43))) -> P0 | F43: =IF($S43="","",IF(INDEX('Master Tracker'!$G$6:$G$400,$S43)="","",INDEX('Master Tracker'!$G$6:$G$400,$S43))) -> Not Started | G43: =IF($S43="","",IF(INDEX('Master Tracker'!$H$6:$H$400,$S43)="","",INDEX('Master Tracker'!$H$6:$H$400,$S43))) -> 46307 | H43: =IF($S43="","",IF(INDEX('Master Tracker'!$I$6:$I$400,$S43)="","",INDEX('Master Tracker'!$I$6:$I$400,$S43))) -> 46307 | I43: =IF($S43="","",IF(INDEX('Master Tracker'!$U$6:$U$400,$S43)="","",INDEX('Master Tracker'!$U$6:$U$400,$S43))) -> 0 | J43: =IF($S43="","",IF(INDEX('Master Tracker'!$K$6:$K$400,$S43)="","",INDEX('Master Tracker'!$K$6:$K$400,$S43))) -> P1-02 | K43: =IF($S43="","",IF(INDEX('Master Tracker'!$Y$6:$Y$400,$S43)="","",INDEX('Master Tracker'!$Y$6:$Y$400,$S43))) -> ✓ Ready | L43: =IF($S43="","",IF(INDEX('Master Tracker'!$M$6:$M$400,$S43)="","",INDEX('Master Tracker'!$M$6:$M$400,$S43))) -> inc/setup.php, functions.php | M43: =IF($S43="","",IF(INDEX('Master Tracker'!$O$6:$O$400,$S43)="","",INDEX('Master Tracker'!$O$6:$O$400,$S43))) -> All supports, menus and image sizes registered; no duplicate title tags | N43: =IF($S43="","",IF(INDEX('Master Tracker'!$N$6:$N$400,$S43)="","",INDEX('Master Tracker'!$N$6:$N$400,$S43))) -> Menus appear in Appearance > Menus; new upload generates all image sizes; single <title> tag | O43: =IF($S43="","",IF(INDEX('Master Tracker'!$T$6:$T$400,$S43)="","",INDEX('Master Tracker'!$T$6:$T$400,$S43))) -> Not Tested | P43: =IF($S43="","",IF(INDEX('Master Tracker'!$AC$6:$AC$400,$S43)="","",INDEX('Master Tracker'!$AC$6:$AC$400,$S43))) -> Due soon | S43: =IFERROR(MATCH("Phase 1|"&A43,'Master Tracker'!$Z$6:$Z$400,0),"") -> 3
A44: 4 | B44: =IF($S44="","",IF(INDEX('Master Tracker'!$A$6:$A$400,$S44)="","",INDEX('Master Tracker'!$A$6:$A$400,$S44))) -> P1-04 | C44: =IF($S44="","",IF(INDEX('Master Tracker'!$C$6:$C$400,$S44)="","",INDEX('Master Tracker'!$C$6:$C$400,$S44))) -> Asset Pipeline | D44: =IF($S44="","",IF(INDEX('Master Tracker'!$D$6:$D$400,$S44)="","",INDEX('Master Tracker'!$D$6:$D$400,$S44))) -> Asset enqueue, versioning & conditional loading | E44: =IF($S44="","",IF(INDEX('Master Tracker'!$F$6:$F$400,$S44)="","",INDEX('Master Tracker'!$F$6:$F$400,$S44))) -> P0 | F44: =IF($S44="","",IF(INDEX('Master Tracker'!$G$6:$G$400,$S44)="","",INDEX('Master Tracker'!$G$6:$G$400,$S44))) -> Not Started | G44: =IF($S44="","",IF(INDEX('Master Tracker'!$H$6:$H$400,$S44)="","",INDEX('Master Tracker'!$H$6:$H$400,$S44))) -> 46307 | H44: =IF($S44="","",IF(INDEX('Master Tracker'!$I$6:$I$400,$S44)="","",INDEX('Master Tracker'!$I$6:$I$400,$S44))) -> 46307 | I44: =IF($S44="","",IF(INDEX('Master Tracker'!$U$6:$U$400,$S44)="","",INDEX('Master Tracker'!$U$6:$U$400,$S44))) -> 0 | J44: =IF($S44="","",IF(INDEX('Master Tracker'!$K$6:$K$400,$S44)="","",INDEX('Master Tracker'!$K$6:$K$400,$S44))) -> P1-02 | K44: =IF($S44="","",IF(INDEX('Master Tracker'!$Y$6:$Y$400,$S44)="","",INDEX('Master Tracker'!$Y$6:$Y$400,$S44))) -> ✓ Ready | L44: =IF($S44="","",IF(INDEX('Master Tracker'!$M$6:$M$400,$S44)="","",INDEX('Master Tracker'!$M$6:$M$400,$S44))) -> inc/enqueue.php, assets/css/*, assets/js/* | M44: =IF($S44="","",IF(INDEX('Master Tracker'!$O$6:$O$400,$S44)="","",INDEX('Master Tracker'!$O$6:$O$400,$S44))) -> All assets versioned and loaded only where needed; zero console errors | N44: =IF($S44="","",IF(INDEX('Master Tracker'!$N$6:$N$400,$S44)="","",INDEX('Master Tracker'!$N$6:$N$400,$S44))) -> View source: versioned URLs, deferred scripts; Network tab shows no 404s and no jQuery on homepage | O44: =IF($S44="","",IF(INDEX('Master Tracker'!$T$6:$T$400,$S44)="","",INDEX('Master Tracker'!$T$6:$T$400,$S44))) -> Not Tested | P44: =IF($S44="","",IF(INDEX('Master Tracker'!$AC$6:$AC$400,$S44)="","",INDEX('Master Tracker'!$AC$6:$AC$400,$S44))) -> Due soon | S44: =IFERROR(MATCH("Phase 1|"&A44,'Master Tracker'!$Z$6:$Z$400,0),"") -> 4
A45: 5 | B45: =IF($S45="","",IF(INDEX('Master Tracker'!$A$6:$A$400,$S45)="","",INDEX('Master Tracker'!$A$6:$A$400,$S45))) -> P1-05 | C45: =IF($S45="","",IF(INDEX('Master Tracker'!$C$6:$C$400,$S45)="","",INDEX('Master Tracker'!$C$6:$C$400,$S45))) -> PHP Templates | D45: =IF($S45="","",IF(INDEX('Master Tracker'!$D$6:$D$400,$S45)="","",INDEX('Master Tracker'!$D$6:$D$400,$S45))) -> Base template hierarchy | E45: =IF($S45="","",IF(INDEX('Master Tracker'!$F$6:$F$400,$S45)="","",INDEX('Master Tracker'!$F$6:$F$400,$S45))) -> P0 | F45: =IF($S45="","",IF(INDEX('Master Tracker'!$G$6:$G$400,$S45)="","",INDEX('Master Tracker'!$G$6:$G$400,$S45))) -> Not Started | G45: =IF($S45="","",IF(INDEX('Master Tracker'!$H$6:$H$400,$S45)="","",INDEX('Master Tracker'!$H$6:$H$400,$S45))) -> 46307 | H45: =IF($S45="","",IF(INDEX('Master Tracker'!$I$6:$I$400,$S45)="","",INDEX('Master Tracker'!$I$6:$I$400,$S45))) -> 46307 | I45: =IF($S45="","",IF(INDEX('Master Tracker'!$U$6:$U$400,$S45)="","",INDEX('Master Tracker'!$U$6:$U$400,$S45))) -> 0 | J45: =IF($S45="","",IF(INDEX('Master Tracker'!$K$6:$K$400,$S45)="","",INDEX('Master Tracker'!$K$6:$K$400,$S45))) -> P1-03 | K45: =IF($S45="","",IF(INDEX('Master Tracker'!$Y$6:$Y$400,$S45)="","",INDEX('Master Tracker'!$Y$6:$Y$400,$S45))) -> ⏳ 1 open | L45: =IF($S45="","",IF(INDEX('Master Tracker'!$M$6:$M$400,$S45)="","",INDEX('Master Tracker'!$M$6:$M$400,$S45))) -> header.php, footer.php, index.php, front-page.php, single.php, page.php, archive.php, category.php, tag.php, author.php, search.php, 404.php | M45: =IF($S45="","",IF(INDEX('Master Tracker'!$O$6:$O$400,$S45)="","",INDEX('Master Tracker'!$O$6:$O$400,$S45))) -> Every WordPress route resolves to a theme template with header/footer; no fallback errors | N45: =IF($S45="","",IF(INDEX('Master Tracker'!$N$6:$N$400,$S45)="","",INDEX('Master Tracker'!$N$6:$N$400,$S45))) -> Visit each route type; Query Monitor confirms expected template file | O45: =IF($S45="","",IF(INDEX('Master Tracker'!$T$6:$T$400,$S45)="","",INDEX('Master Tracker'!$T$6:$T$400,$S45))) -> Not Tested | P45: =IF($S45="","",IF(INDEX('Master Tracker'!$AC$6:$AC$400,$S45)="","",INDEX('Master Tracker'!$AC$6:$AC$400,$S45))) -> Due soon | S45: =IFERROR(MATCH("Phase 1|"&A45,'Master Tracker'!$Z$6:$Z$400,0),"") -> 5
A46: 6 | B46: =IF($S46="","",IF(INDEX('Master Tracker'!$A$6:$A$400,$S46)="","",INDEX('Master Tracker'!$A$6:$A$400,$S46))) -> P1-06 | C46: =IF($S46="","",IF(INDEX('Master Tracker'!$C$6:$C$400,$S46)="","",INDEX('Master Tracker'!$C$6:$C$400,$S46))) -> Components | D46: =IF($S46="","",IF(INDEX('Master Tracker'!$D$6:$D$400,$S46)="","",INDEX('Master Tracker'!$D$6:$D$400,$S46))) -> Reusable template-part components | E46: =IF($S46="","",IF(INDEX('Master Tracker'!$F$6:$F$400,$S46)="","",INDEX('Master Tracker'!$F$6:$F$400,$S46))) -> P0 | F46: =IF($S46="","",IF(INDEX('Master Tracker'!$G$6:$G$400,$S46)="","",INDEX('Master Tracker'!$G$6:$G$400,$S46))) -> Not Started | G46: =IF($S46="","",IF(INDEX('Master Tracker'!$H$6:$H$400,$S46)="","",INDEX('Master Tracker'!$H$6:$H$400,$S46))) -> 46307 | H46: =IF($S46="","",IF(INDEX('Master Tracker'!$I$6:$I$400,$S46)="","",INDEX('Master Tracker'!$I$6:$I$400,$S46))) -> 46307 | I46: =IF($S46="","",IF(INDEX('Master Tracker'!$U$6:$U$400,$S46)="","",INDEX('Master Tracker'!$U$6:$U$400,$S46))) -> 0 | J46: =IF($S46="","",IF(INDEX('Master Tracker'!$K$6:$K$400,$S46)="","",INDEX('Master Tracker'!$K$6:$K$400,$S46))) -> P1-05 | K46: =IF($S46="","",IF(INDEX('Master Tracker'!$Y$6:$Y$400,$S46)="","",INDEX('Master Tracker'!$Y$6:$Y$400,$S46))) -> ⏳ 1 open | L46: =IF($S46="","",IF(INDEX('Master Tracker'!$M$6:$M$400,$S46)="","",INDEX('Master Tracker'!$M$6:$M$400,$S46))) -> template-parts/components/*.php | M46: =IF($S46="","",IF(INDEX('Master Tracker'!$O$6:$O$400,$S46)="","",INDEX('Master Tracker'!$O$6:$O$400,$S46))) -> Components reused by homepage and archives with no duplicated markup; all output escaped | N46: =IF($S46="","",IF(INDEX('Master Tracker'!$N$6:$N$400,$S46)="","",INDEX('Master Tracker'!$N$6:$N$400,$S46))) -> Render every component on a test page with real posts; test missing image/excerpt; check escaping | O46: =IF($S46="","",IF(INDEX('Master Tracker'!$T$6:$T$400,$S46)="","",INDEX('Master Tracker'!$T$6:$T$400,$S46))) -> Not Tested | P46: =IF($S46="","",IF(INDEX('Master Tracker'!$AC$6:$AC$400,$S46)="","",INDEX('Master Tracker'!$AC$6:$AC$400,$S46))) -> Due soon | S46: =IFERROR(MATCH("Phase 1|"&A46,'Master Tracker'!$Z$6:$Z$400,0),"") -> 6
A47: 7 | B47: =IF($S47="","",IF(INDEX('Master Tracker'!$A$6:$A$400,$S47)="","",INDEX('Master Tracker'!$A$6:$A$400,$S47))) -> P1-07 | C47: =IF($S47="","",IF(INDEX('Master Tracker'!$C$6:$C$400,$S47)="","",INDEX('Master Tracker'!$C$6:$C$400,$S47))) -> CSS Architecture | D47: =IF($S47="","",IF(INDEX('Master Tracker'!$D$6:$D$400,$S47)="","",INDEX('Master Tracker'!$D$6:$D$400,$S47))) -> CSS architecture & design tokens | E47: =IF($S47="","",IF(INDEX('Master Tracker'!$F$6:$F$400,$S47)="","",INDEX('Master Tracker'!$F$6:$F$400,$S47))) -> P0 | F47: =IF($S47="","",IF(INDEX('Master Tracker'!$G$6:$G$400,$S47)="","",INDEX('Master Tracker'!$G$6:$G$400,$S47))) -> Not Started | G47: =IF($S47="","",IF(INDEX('Master Tracker'!$H$6:$H$400,$S47)="","",INDEX('Master Tracker'!$H$6:$H$400,$S47))) -> 46307 | H47: =IF($S47="","",IF(INDEX('Master Tracker'!$I$6:$I$400,$S47)="","",INDEX('Master Tracker'!$I$6:$I$400,$S47))) -> 46308 | I47: =IF($S47="","",IF(INDEX('Master Tracker'!$U$6:$U$400,$S47)="","",INDEX('Master Tracker'!$U$6:$U$400,$S47))) -> 0 | J47: =IF($S47="","",IF(INDEX('Master Tracker'!$K$6:$K$400,$S47)="","",INDEX('Master Tracker'!$K$6:$K$400,$S47))) -> P1-04 | K47: =IF($S47="","",IF(INDEX('Master Tracker'!$Y$6:$Y$400,$S47)="","",INDEX('Master Tracker'!$Y$6:$Y$400,$S47))) -> ⏳ 1 open | L47: =IF($S47="","",IF(INDEX('Master Tracker'!$M$6:$M$400,$S47)="","",INDEX('Master Tracker'!$M$6:$M$400,$S47))) -> assets/css/tokens.css, base.css, layout.css, components.css, utilities.css | M47: =IF($S47="","",IF(INDEX('Master Tracker'!$O$6:$O$400,$S47)="","",INDEX('Master Tracker'!$O$6:$O$400,$S47))) -> Single token source; consistent styling; total CSS within agreed budget (target < 100 KB uncompressed) | N47: =IF($S47="","",IF(INDEX('Master Tracker'!$N$6:$N$400,$S47)="","",INDEX('Master Tracker'!$N$6:$N$400,$S47))) -> Inspect computed styles use tokens; RTL correct without separate override file; CSS size checked | O47: =IF($S47="","",IF(INDEX('Master Tracker'!$T$6:$T$400,$S47)="","",INDEX('Master Tracker'!$T$6:$T$400,$S47))) -> Not Tested | P47: =IF($S47="","",IF(INDEX('Master Tracker'!$AC$6:$AC$400,$S47)="","",INDEX('Master Tracker'!$AC$6:$AC$400,$S47))) -> Due soon | S47: =IFERROR(MATCH("Phase 1|"&A47,'Master Tracker'!$Z$6:$Z$400,0),"") -> 7
A48: 8 | B48: =IF($S48="","",IF(INDEX('Master Tracker'!$A$6:$A$400,$S48)="","",INDEX('Master Tracker'!$A$6:$A$400,$S48))) -> P1-08 | C48: =IF($S48="","",IF(INDEX('Master Tracker'!$C$6:$C$400,$S48)="","",INDEX('Master Tracker'!$C$6:$C$400,$S48))) -> Vanilla JS | D48: =IF($S48="","",IF(INDEX('Master Tracker'!$D$6:$D$400,$S48)="","",INDEX('Master Tracker'!$D$6:$D$400,$S48))) -> Vanilla JS module architecture | E48: =IF($S48="","",IF(INDEX('Master Tracker'!$F$6:$F$400,$S48)="","",INDEX('Master Tracker'!$F$6:$F$400,$S48))) -> P0 | F48: =IF($S48="","",IF(INDEX('Master Tracker'!$G$6:$G$400,$S48)="","",INDEX('Master Tracker'!$G$6:$G$400,$S48))) -> Not Started | G48: =IF($S48="","",IF(INDEX('Master Tracker'!$H$6:$H$400,$S48)="","",INDEX('Master Tracker'!$H$6:$H$400,$S48))) -> 46308 | H48: =IF($S48="","",IF(INDEX('Master Tracker'!$I$6:$I$400,$S48)="","",INDEX('Master Tracker'!$I$6:$I$400,$S48))) -> 46308 | I48: =IF($S48="","",IF(INDEX('Master Tracker'!$U$6:$U$400,$S48)="","",INDEX('Master Tracker'!$U$6:$U$400,$S48))) -> 0 | J48: =IF($S48="","",IF(INDEX('Master Tracker'!$K$6:$K$400,$S48)="","",INDEX('Master Tracker'!$K$6:$K$400,$S48))) -> P1-04 | K48: =IF($S48="","",IF(INDEX('Master Tracker'!$Y$6:$Y$400,$S48)="","",INDEX('Master Tracker'!$Y$6:$Y$400,$S48))) -> ⏳ 1 open | L48: =IF($S48="","",IF(INDEX('Master Tracker'!$M$6:$M$400,$S48)="","",INDEX('Master Tracker'!$M$6:$M$400,$S48))) -> assets/js/main.js, assets/js/modules/*.js | M48: =IF($S48="","",IF(INDEX('Master Tracker'!$O$6:$O$400,$S48)="","",INDEX('Master Tracker'!$O$6:$O$400,$S48))) -> All interactions implemented in Vanilla JS; zero console errors; scripts deferred | N48: =IF($S48="","",IF(INDEX('Master Tracker'!$N$6:$N$400,$S48)="","",INDEX('Master Tracker'!$N$6:$N$400,$S48))) -> Console clean on Chrome & Safari; page usable with JS disabled | O48: =IF($S48="","",IF(INDEX('Master Tracker'!$T$6:$T$400,$S48)="","",INDEX('Master Tracker'!$T$6:$T$400,$S48))) -> Not Tested | P48: =IF($S48="","",IF(INDEX('Master Tracker'!$AC$6:$AC$400,$S48)="","",INDEX('Master Tracker'!$AC$6:$AC$400,$S48))) -> Due soon | S48: =IFERROR(MATCH("Phase 1|"&A48,'Master Tracker'!$Z$6:$Z$400,0),"") -> 8
A49: 9 | B49: =IF($S49="","",IF(INDEX('Master Tracker'!$A$6:$A$400,$S49)="","",INDEX('Master Tracker'!$A$6:$A$400,$S49))) -> P1-09 | C49: =IF($S49="","",IF(INDEX('Master Tracker'!$C$6:$C$400,$S49)="","",INDEX('Master Tracker'!$C$6:$C$400,$S49))) -> RTL Typography | D49: =IF($S49="","",IF(INDEX('Master Tracker'!$D$6:$D$400,$S49)="","",INDEX('Master Tracker'!$D$6:$D$400,$S49))) -> RTL layout & Arabic typography | E49: =IF($S49="","",IF(INDEX('Master Tracker'!$F$6:$F$400,$S49)="","",INDEX('Master Tracker'!$F$6:$F$400,$S49))) -> P0 | F49: =IF($S49="","",IF(INDEX('Master Tracker'!$G$6:$G$400,$S49)="","",INDEX('Master Tracker'!$G$6:$G$400,$S49))) -> Not Started | G49: =IF($S49="","",IF(INDEX('Master Tracker'!$H$6:$H$400,$S49)="","",INDEX('Master Tracker'!$H$6:$H$400,$S49))) -> 46308 | H49: =IF($S49="","",IF(INDEX('Master Tracker'!$I$6:$I$400,$S49)="","",INDEX('Master Tracker'!$I$6:$I$400,$S49))) -> 46308 | I49: =IF($S49="","",IF(INDEX('Master Tracker'!$U$6:$U$400,$S49)="","",INDEX('Master Tracker'!$U$6:$U$400,$S49))) -> 0 | J49: =IF($S49="","",IF(INDEX('Master Tracker'!$K$6:$K$400,$S49)="","",INDEX('Master Tracker'!$K$6:$K$400,$S49))) -> P1-07 | K49: =IF($S49="","",IF(INDEX('Master Tracker'!$Y$6:$Y$400,$S49)="","",INDEX('Master Tracker'!$Y$6:$Y$400,$S49))) -> ⏳ 1 open | L49: =IF($S49="","",IF(INDEX('Master Tracker'!$M$6:$M$400,$S49)="","",INDEX('Master Tracker'!$M$6:$M$400,$S49))) -> assets/fonts/*, assets/css/base.css, header.php | M49: =IF($S49="","",IF(INDEX('Master Tracker'!$O$6:$O$400,$S49)="","",INDEX('Master Tracker'!$O$6:$O$400,$S49))) -> Correct RTL direction site-wide; fonts self-hosted; no layout shift from font swap | N49: =IF($S49="","",IF(INDEX('Master Tracker'!$N$6:$N$400,$S49)="","",INDEX('Master Tracker'!$N$6:$N$400,$S49))) -> Headlines/body render in Arabic font on iOS, Android, desktop; no invisible text flash; mixed strings align | O49: =IF($S49="","",IF(INDEX('Master Tracker'!$T$6:$T$400,$S49)="","",INDEX('Master Tracker'!$T$6:$T$400,$S49))) -> Not Tested | P49: =IF($S49="","",IF(INDEX('Master Tracker'!$AC$6:$AC$400,$S49)="","",INDEX('Master Tracker'!$AC$6:$AC$400,$S49))) -> Due soon | S49: =IFERROR(MATCH("Phase 1|"&A49,'Master Tracker'!$Z$6:$Z$400,0),"") -> 9
A50: 10 | B50: =IF($S50="","",IF(INDEX('Master Tracker'!$A$6:$A$400,$S50)="","",INDEX('Master Tracker'!$A$6:$A$400,$S50))) -> P1-10 | C50: =IF($S50="","",IF(INDEX('Master Tracker'!$C$6:$C$400,$S50)="","",INDEX('Master Tracker'!$C$6:$C$400,$S50))) -> Responsive Design | D50: =IF($S50="","",IF(INDEX('Master Tracker'!$D$6:$D$400,$S50)="","",INDEX('Master Tracker'!$D$6:$D$400,$S50))) -> Responsive grid & breakpoints | E50: =IF($S50="","",IF(INDEX('Master Tracker'!$F$6:$F$400,$S50)="","",INDEX('Master Tracker'!$F$6:$F$400,$S50))) -> P0 | F50: =IF($S50="","",IF(INDEX('Master Tracker'!$G$6:$G$400,$S50)="","",INDEX('Master Tracker'!$G$6:$G$400,$S50))) -> Not Started | G50: =IF($S50="","",IF(INDEX('Master Tracker'!$H$6:$H$400,$S50)="","",INDEX('Master Tracker'!$H$6:$H$400,$S50))) -> 46308 | H50: =IF($S50="","",IF(INDEX('Master Tracker'!$I$6:$I$400,$S50)="","",INDEX('Master Tracker'!$I$6:$I$400,$S50))) -> 46308 | I50: =IF($S50="","",IF(INDEX('Master Tracker'!$U$6:$U$400,$S50)="","",INDEX('Master Tracker'!$U$6:$U$400,$S50))) -> 0 | J50: =IF($S50="","",IF(INDEX('Master Tracker'!$K$6:$K$400,$S50)="","",INDEX('Master Tracker'!$K$6:$K$400,$S50))) -> P1-07 | K50: =IF($S50="","",IF(INDEX('Master Tracker'!$Y$6:$Y$400,$S50)="","",INDEX('Master Tracker'!$Y$6:$Y$400,$S50))) -> ⏳ 1 open | L50: =IF($S50="","",IF(INDEX('Master Tracker'!$M$6:$M$400,$S50)="","",INDEX('Master Tracker'!$M$6:$M$400,$S50))) -> assets/css/layout.css | M50: =IF($S50="","",IF(INDEX('Master Tracker'!$O$6:$O$400,$S50)="","",INDEX('Master Tracker'!$O$6:$O$400,$S50))) -> All layouts usable at 360 px; no overflow; correctly sized images | N50: =IF($S50="","",IF(INDEX('Master Tracker'!$N$6:$N$400,$S50)="","",INDEX('Master Tracker'!$N$6:$N$400,$S50))) -> Test 360, 414, 768, 1024, 1440 px widths; no horizontal scroll | O50: =IF($S50="","",IF(INDEX('Master Tracker'!$T$6:$T$400,$S50)="","",INDEX('Master Tracker'!$T$6:$T$400,$S50))) -> Not Tested | P50: =IF($S50="","",IF(INDEX('Master Tracker'!$AC$6:$AC$400,$S50)="","",INDEX('Master Tracker'!$AC$6:$AC$400,$S50))) -> Due soon | S50: =IFERROR(MATCH("Phase 1|"&A50,'Master Tracker'!$Z$6:$Z$400,0),"") -> 10
A51: 11 | B51: =IF($S51="","",IF(INDEX('Master Tracker'!$A$6:$A$400,$S51)="","",INDEX('Master Tracker'!$A$6:$A$400,$S51))) -> P1-11 | C51: =IF($S51="","",IF(INDEX('Master Tracker'!$C$6:$C$400,$S51)="","",INDEX('Master Tracker'!$C$6:$C$400,$S51))) -> Header & Navigation | D51: =IF($S51="","",IF(INDEX('Master Tracker'!$D$6:$D$400,$S51)="","",INDEX('Master Tracker'!$D$6:$D$400,$S51))) -> Header, navigation, mobile drawer & search | E51: =IF($S51="","",IF(INDEX('Master Tracker'!$F$6:$F$400,$S51)="","",INDEX('Master Tracker'!$F$6:$F$400,$S51))) -> P0 | F51: =IF($S51="","",IF(INDEX('Master Tracker'!$G$6:$G$400,$S51)="","",INDEX('Master Tracker'!$G$6:$G$400,$S51))) -> Not Started | G51: =IF($S51="","",IF(INDEX('Master Tracker'!$H$6:$H$400,$S51)="","",INDEX('Master Tracker'!$H$6:$H$400,$S51))) -> 46308 | H51: =IF($S51="","",IF(INDEX('Master Tracker'!$I$6:$I$400,$S51)="","",INDEX('Master Tracker'!$I$6:$I$400,$S51))) -> 46309 | I51: =IF($S51="","",IF(INDEX('Master Tracker'!$U$6:$U$400,$S51)="","",INDEX('Master Tracker'!$U$6:$U$400,$S51))) -> 0 | J51: =IF($S51="","",IF(INDEX('Master Tracker'!$K$6:$K$400,$S51)="","",INDEX('Master Tracker'!$K$6:$K$400,$S51))) -> P1-06, P1-08, P1-15 | K51: =IF($S51="","",IF(INDEX('Master Tracker'!$Y$6:$Y$400,$S51)="","",INDEX('Master Tracker'!$Y$6:$Y$400,$S51))) -> ⏳ 3 open | L51: =IF($S51="","",IF(INDEX('Master Tracker'!$M$6:$M$400,$S51)="","",INDEX('Master Tracker'!$M$6:$M$400,$S51))) -> header.php, template-parts/header/*.php, assets/js/modules/nav.js | M51: =IF($S51="","",IF(INDEX('Master Tracker'!$O$6:$O$400,$S51)="","",INDEX('Master Tracker'!$O$6:$O$400,$S51))) -> Navigation works on touch and keyboard; fully managed from WordPress menus | N51: =IF($S51="","",IF(INDEX('Master Tracker'!$N$6:$N$400,$S51)="","",INDEX('Master Tracker'!$N$6:$N$400,$S51))) -> Drawer opens/closes, Esc closes, focus trapped; search submits; menu edited in WP admin updates header | O51: =IF($S51="","",IF(INDEX('Master Tracker'!$T$6:$T$400,$S51)="","",INDEX('Master Tracker'!$T$6:$T$400,$S51))) -> Not Tested | P51: =IF($S51="","",IF(INDEX('Master Tracker'!$AC$6:$AC$400,$S51)="","",INDEX('Master Tracker'!$AC$6:$AC$400,$S51))) -> On track | S51: =IFERROR(MATCH("Phase 1|"&A51,'Master Tracker'!$Z$6:$Z$400,0),"") -> 11
A52: 12 | B52: =IF($S52="","",IF(INDEX('Master Tracker'!$A$6:$A$400,$S52)="","",INDEX('Master Tracker'!$A$6:$A$400,$S52))) -> P1-12 | C52: =IF($S52="","",IF(INDEX('Master Tracker'!$C$6:$C$400,$S52)="","",INDEX('Master Tracker'!$C$6:$C$400,$S52))) -> Footer | D52: =IF($S52="","",IF(INDEX('Master Tracker'!$D$6:$D$400,$S52)="","",INDEX('Master Tracker'!$D$6:$D$400,$S52))) -> Footer with editable menus & social links | E52: =IF($S52="","",IF(INDEX('Master Tracker'!$F$6:$F$400,$S52)="","",INDEX('Master Tracker'!$F$6:$F$400,$S52))) -> P1 | F52: =IF($S52="","",IF(INDEX('Master Tracker'!$G$6:$G$400,$S52)="","",INDEX('Master Tracker'!$G$6:$G$400,$S52))) -> Not Started | G52: =IF($S52="","",IF(INDEX('Master Tracker'!$H$6:$H$400,$S52)="","",INDEX('Master Tracker'!$H$6:$H$400,$S52))) -> 46309 | H52: =IF($S52="","",IF(INDEX('Master Tracker'!$I$6:$I$400,$S52)="","",INDEX('Master Tracker'!$I$6:$I$400,$S52))) -> 46309 | I52: =IF($S52="","",IF(INDEX('Master Tracker'!$U$6:$U$400,$S52)="","",INDEX('Master Tracker'!$U$6:$U$400,$S52))) -> 0 | J52: =IF($S52="","",IF(INDEX('Master Tracker'!$K$6:$K$400,$S52)="","",INDEX('Master Tracker'!$K$6:$K$400,$S52))) -> P1-06 | K52: =IF($S52="","",IF(INDEX('Master Tracker'!$Y$6:$Y$400,$S52)="","",INDEX('Master Tracker'!$Y$6:$Y$400,$S52))) -> ⏳ 1 open | L52: =IF($S52="","",IF(INDEX('Master Tracker'!$M$6:$M$400,$S52)="","",INDEX('Master Tracker'!$M$6:$M$400,$S52))) -> footer.php, template-parts/footer/*.php | M52: =IF($S52="","",IF(INDEX('Master Tracker'!$O$6:$O$400,$S52)="","",INDEX('Master Tracker'!$O$6:$O$400,$S52))) -> Footer content editable without code | N52: =IF($S52="","",IF(INDEX('Master Tracker'!$N$6:$N$400,$S52)="","",INDEX('Master Tracker'!$N$6:$N$400,$S52))) -> All links resolve; social URLs editable in Customizer | O52: =IF($S52="","",IF(INDEX('Master Tracker'!$T$6:$T$400,$S52)="","",INDEX('Master Tracker'!$T$6:$T$400,$S52))) -> Not Tested | P52: =IF($S52="","",IF(INDEX('Master Tracker'!$AC$6:$AC$400,$S52)="","",INDEX('Master Tracker'!$AC$6:$AC$400,$S52))) -> On track | S52: =IFERROR(MATCH("Phase 1|"&A52,'Master Tracker'!$Z$6:$Z$400,0),"") -> 12
... A65: 25 | B65: =IF($S65="","",IF(INDEX('Master Tracker'!$A$6:$A$400,$S65)="","",INDEX('Master Tracker'!$A$6:$A$400,$S65))) | C65: =IF($S65="","",IF(INDEX('Master Tracker'!$C$6:$C$400,$S65)="","",INDEX('Master Tracker'!$C$6:$C$400,$S65))) | D65: =IF($S65="","",IF(INDEX('Master Tracker'!$D$6:$D$400,$S65)="","",INDEX('Master Tracker'!$D$6:$D$400,$S65))) | E65: =IF($S65="","",IF(INDEX('Master Tracker'!$F$6:$F$400,$S65)="","",INDEX('Master Tracker'!$F$6:$F$400,$S65))) | F65: =IF($S65="","",IF(INDEX('Master Tracker'!$G$6:$G$400,$S65)="","",INDEX('Master Tracker'!$G$6:$G$400,$S65))) | G65: =IF($S65="","",IF(INDEX('Master Tracker'!$H$6:$H$400,$S65)="","",INDEX('Master Tracker'!$H$6:$H$400,$S65))) | H65: =IF($S65="","",IF(INDEX('Master Tracker'!$I$6:$I$400,$S65)="","",INDEX('Master Tracker'!$I$6:$I$400,$S65))) | I65: =IF($S65="","",IF(INDEX('Master Tracker'!$U$6:$U$400,$S65)="","",INDEX('Master Tracker'!$U$6:$U$400,$S65))) | J65: =IF($S65="","",IF(INDEX('Master Tracker'!$K$6:$K$400,$S65)="","",INDEX('Master Tracker'!$K$6:$K$400,$S65))) | K65: =IF($S65="","",IF(INDEX('Master Tracker'!$Y$6:$Y$400,$S65)="","",INDEX('Master Tracker'!$Y$6:$Y$400,$S65))) | L65: =IF($S65="","",IF(INDEX('Master Tracker'!$M$6:$M$400,$S65)="","",INDEX('Master Tracker'!$M$6:$M$400,$S65))) | M65: =IF($S65="","",IF(INDEX('Master Tracker'!$O$6:$O$400,$S65)="","",INDEX('Master Tracker'!$O$6:$O$400,$S65))) | N65: =IF($S65="","",IF(INDEX('Master Tracker'!$N$6:$N$400,$S65)="","",INDEX('Master Tracker'!$N$6:$N$400,$S65))) | O65: =IF($S65="","",IF(INDEX('Master Tracker'!$T$6:$T$400,$S65)="","",INDEX('Master Tracker'!$T$6:$T$400,$S65))) | P65: =IF($S65="","",IF(INDEX('Master Tracker'!$AC$6:$AC$400,$S65)="","",INDEX('Master Tracker'!$AC$6:$AC$400,$S65))) | S65: =IFERROR(MATCH("Phase 1|"&A65,'Master Tracker'!$Z$6:$Z$400,0),"")

Sheet P2 Homepage & Sections
A1: PHASE 2 — HOMEPAGE & DYNAMIC SECTION MANAGER
A2: Window 15 Oct – 17 Oct 2026 · Status is read live from the Master Tracker (edit there)
A3: ← Dashboard | D3: Open Master Tracker → | F3: Staging ↗
A5: COMPLETION | D5: PLANNED | E5: TASKS | G5: DONE | H5: IN PROGRESS | J5: BLOCKED | L5: OVERDUE | M5: IN REVIEW / TEST | N5: OPEN P0 | O5: DEADLINE | P5: PHASE STATUS
A6: =IFERROR(SUMPRODUCT(('Master Tracker'!$B$6:$B$400="Phase 2")*'Master Tracker'!$U$6:$U$400)/COUNTIFS('Master Tracker'!$B$6:$B$400,"Phase 2",'Master Tracker'!$A$6:$A$400,"?*"),0) -> 0 | D6: =IFERROR(SUMPRODUCT(('Master Tracker'!$B$6:$B$400="Phase 2")*'Master Tracker'!$V$6:$V$400)/COUNTIFS('Master Tracker'!$B$6:$B$400,"Phase 2",'Master Tracker'!$A$6:$A$400,"?*"),0) -> 0 | E6: =COUNTIFS('Master Tracker'!$B$6:$B$400,"Phase 2",'Master Tracker'!$A$6:$A$400,"?*") -> 24 | G6: =COUNTIFS('Master Tracker'!$B$6:$B$400,"Phase 2",'Master Tracker'!$G$6:$G$400,"Completed") -> 0 | H6: =COUNTIFS('Master Tracker'!$B$6:$B$400,"Phase 2",'Master Tracker'!$G$6:$G$400,"In Progress") -> 0 | J6: =COUNTIFS('Master Tracker'!$B$6:$B$400,"Phase 2",'Master Tracker'!$G$6:$G$400,"Blocked") -> 0 | L6: =COUNTIFS('Master Tracker'!$B$6:$B$400,"Phase 2",'Master Tracker'!$X$6:$X$400,"OVERDUE") -> 0 | M6: =COUNTIFS('Master Tracker'!$B$6:$B$400,"Phase 2",'Master Tracker'!$G$6:$G$400,"In Review")+COUNTIFS('Master Tracker'!$B$6:$B$400,"Phase 2",'Master Tracker'!$G$6:$G$400,"Testing") -> 0 | N6: =COUNTIFS('Master Tracker'!$B$6:$B$400,"Phase 2",'Master Tracker'!$F$6:$F$400,"P0",'Master Tracker'!$G$6:$G$400,"<>Completed",'Master Tracker'!$A$6:$A$400,"?*") -> 11 | O6: =_xlfn.MAXIFS('Master Tracker'!$I$6:$I$400,'Master Tracker'!$B$6:$B$400,"Phase 2") -> 46312 | P6: =IF(E6=0,"—",IF(G6=E6,"Complete",IF(J6>0,"Blocked",IF(L6>0,"Behind",IF(A6+0.1<D6,"Behind",IF(A6>0,"On Track","Not Started")))))) -> Not Started
A7: ="Progress "&REPT("█",ROUND(A6*50,0))&REPT("░",50-ROUND(A6*50,0))&" "&TEXT(A6,"0%")&" (planned "&TEXT(D6,"0%")&")" -> Progress ░░░░░░░░░░░░░░░░░░░░░░░░░░░░░░░░░░░░░░░░░░░░░░░░░░ 0% (planned 0%)
A9: PHASE GOAL
A10: Deliver a fully dynamic magazine homepage whose every section (source, count, order, offset, layout, visibility, cache) is controlled by editors through the WordPress Customizer Section Manager — no code changes needed to re-arrange the homepage.
A12: DELIVERABLES | J12: REQUIRED WORDPRESS FILES
A13: ▸ Section Manager engine with per-section schema | J13: ▸ front-page.php
A14: ▸ Customizer 'Homepage Sections' panel with sanitized controls | J14: ▸ inc/section-manager/registry.php
A15: ▸ Category/tag selectors, manual post picker, count/sort/offset controls | J15: ▸ inc/section-manager/query-builder.php
A16: ▸ Layout switching, visibility toggles, ordering, de-duplication | J16: ▸ inc/section-manager/render.php
A17: ▸ Section cache controls + LiteSpeed purge | J17: ▸ inc/customizer/panel-homepage.php
A18: ▸ Hero, breaking ticker, cover slider, chamber, opinion, reports, article grids | J18: ▸ inc/customizer/controls/*.php
A19: ▸ Business, Real Estate, Automotive, Technology, Healthcare, Tourism sections | J19: ▸ assets/js/customizer-controls.js
A20: ▸ Most-read widget and homepage ad slots | J20: ▸ assets/js/modules/ticker.js, slider.js
J21: ▸ template-parts/sections/*.php
J22: ▸ inc/most-read.php
J23: ▸ inc/widgets/most-read-widget.php
A25: TECHNICAL IMPLEMENTATION STEPS
A26: 1 | B26: Define section schema & registry in inc/section-manager/
A27: 2 | B27: Build WP_Query args builder (source, count, orderby, offset, exclusions)
A28: 3 | B28: Register Customizer panel/sections/settings with sanitize callbacks
A29: 4 | B29: Create custom controls: term multi-select, post picker (REST), sortable order
A30: 5 | B30: Map layouts to template-parts components
A31: 6 | B31: Wrap every section query in altijara_cached_query with TTL
A32: 7 | B32: Add purge button + auto-purge on publish + LiteSpeed purge action
A33: 8 | B33: Build hero, ticker (Vanilla JS), cover slider (CPT-driven)
A34: 9 | B34: Configure each sector section via Section Manager
A35: 10 | B35: Implement view counter + most-read widget; measure queries with Query Monitor
A37: DETAILED TASK CHECKLIST (live from Master Tracker — change Status / % there)
A38: # | B38: Task ID | C38: Module | D38: Task | E38: Priority | F38: Status | G38: Start | H38: Due | I38: Complete | J38: Dependencies | K38: Dep. check | L38: WordPress files | M38: Acceptance criteria | N38: Testing checklist | O38: Test result | P38: Alert
A39: 1 | B39: =IF($S39="","",IF(INDEX('Master Tracker'!$A$6:$A$400,$S39)="","",INDEX('Master Tracker'!$A$6:$A$400,$S39))) -> P2-01 | C39: =IF($S39="","",IF(INDEX('Master Tracker'!$C$6:$C$400,$S39)="","",INDEX('Master Tracker'!$C$6:$C$400,$S39))) -> Section Manager | D39: =IF($S39="","",IF(INDEX('Master Tracker'!$D$6:$D$400,$S39)="","",INDEX('Master Tracker'!$D$6:$D$400,$S39))) -> Section Manager engine & schema | E39: =IF($S39="","",IF(INDEX('Master Tracker'!$F$6:$F$400,$S39)="","",INDEX('Master Tracker'!$F$6:$F$400,$S39))) -> P0 | F39: =IF($S39="","",IF(INDEX('Master Tracker'!$G$6:$G$400,$S39)="","",INDEX('Master Tracker'!$G$6:$G$400,$S39))) -> Not Started | G39: =IF($S39="","",IF(INDEX('Master Tracker'!$H$6:$H$400,$S39)="","",INDEX('Master Tracker'!$H$6:$H$400,$S39))) -> 46310 | H39: =IF($S39="","",IF(INDEX('Master Tracker'!$I$6:$I$400,$S39)="","",INDEX('Master Tracker'!$I$6:$I$400,$S39))) -> 46310 | I39: =IF($S39="","",IF(INDEX('Master Tracker'!$U$6:$U$400,$S39)="","",INDEX('Master Tracker'!$U$6:$U$400,$S39))) -> 0 | J39: =IF($S39="","",IF(INDEX('Master Tracker'!$K$6:$K$400,$S39)="","",INDEX('Master Tracker'!$K$6:$K$400,$S39))) -> P1-06, P1-14 | K39: =IF($S39="","",IF(INDEX('Master Tracker'!$Y$6:$Y$400,$S39)="","",INDEX('Master Tracker'!$Y$6:$Y$400,$S39))) -> ⏳ 2 open | L39: =IF($S39="","",IF(INDEX('Master Tracker'!$M$6:$M$400,$S39)="","",INDEX('Master Tracker'!$M$6:$M$400,$S39))) -> inc/section-manager/registry.php, query-builder.php, render.php | M39: =IF($S39="","",IF(INDEX('Master Tracker'!$O$6:$O$400,$S39)="","",INDEX('Master Tracker'!$O$6:$O$400,$S39))) -> Every homepage section is rendered from the registry; no hard-coded queries in front-page.php | N39: =IF($S39="","",IF(INDEX('Master Tracker'!$N$6:$N$400,$S39)="","",INDEX('Master Tracker'!$N$6:$N$400,$S39))) -> Register a test section; change schema values; output changes accordingly | O39: =IF($S39="","",IF(INDEX('Master Tracker'!$T$6:$T$400,$S39)="","",INDEX('Master Tracker'!$T$6:$T$400,$S39))) -> Not Tested | P39: =IF($S39="","",IF(INDEX('Master Tracker'!$AC$6:$AC$400,$S39)="","",INDEX('Master Tracker'!$AC$6:$AC$400,$S39))) -> On track | S39: =IFERROR(MATCH("Phase 2|"&A39,'Master Tracker'!$Z$6:$Z$400,0),"") -> 18
A40: 2 | B40: =IF($S40="","",IF(INDEX('Master Tracker'!$A$6:$A$400,$S40)="","",INDEX('Master Tracker'!$A$6:$A$400,$S40))) -> P2-02 | C40: =IF($S40="","",IF(INDEX('Master Tracker'!$C$6:$C$400,$S40)="","",INDEX('Master Tracker'!$C$6:$C$400,$S40))) -> Customizer | D40: =IF($S40="","",IF(INDEX('Master Tracker'!$D$6:$D$400,$S40)="","",INDEX('Master Tracker'!$D$6:$D$400,$S40))) -> Customizer 'Homepage Sections' panel | E40: =IF($S40="","",IF(INDEX('Master Tracker'!$F$6:$F$400,$S40)="","",INDEX('Master Tracker'!$F$6:$F$400,$S40))) -> P0 | F40: =IF($S40="","",IF(INDEX('Master Tracker'!$G$6:$G$400,$S40)="","",INDEX('Master Tracker'!$G$6:$G$400,$S40))) -> Not Started | G40: =IF($S40="","",IF(INDEX('Master Tracker'!$H$6:$H$400,$S40)="","",INDEX('Master Tracker'!$H$6:$H$400,$S40))) -> 46310 | H40: =IF($S40="","",IF(INDEX('Master Tracker'!$I$6:$I$400,$S40)="","",INDEX('Master Tracker'!$I$6:$I$400,$S40))) -> 46310 | I40: =IF($S40="","",IF(INDEX('Master Tracker'!$U$6:$U$400,$S40)="","",INDEX('Master Tracker'!$U$6:$U$400,$S40))) -> 0 | J40: =IF($S40="","",IF(INDEX('Master Tracker'!$K$6:$K$400,$S40)="","",INDEX('Master Tracker'!$K$6:$K$400,$S40))) -> P2-01 | K40: =IF($S40="","",IF(INDEX('Master Tracker'!$Y$6:$Y$400,$S40)="","",INDEX('Master Tracker'!$Y$6:$Y$400,$S40))) -> ⏳ 1 open | L40: =IF($S40="","",IF(INDEX('Master Tracker'!$M$6:$M$400,$S40)="","",INDEX('Master Tracker'!$M$6:$M$400,$S40))) -> inc/customizer/panel-homepage.php, assets/js/customizer-preview.js | M40: =IF($S40="","",IF(INDEX('Master Tracker'!$O$6:$O$400,$S40)="","",INDEX('Master Tracker'!$O$6:$O$400,$S40))) -> All sections configurable in Customizer with live preview and sanitized values | N40: =IF($S40="","",IF(INDEX('Master Tracker'!$N$6:$N$400,$S40)="","",INDEX('Master Tracker'!$N$6:$N$400,$S40))) -> Editor (non-admin) changes a section in Customizer and publishes; invalid values rejected | O40: =IF($S40="","",IF(INDEX('Master Tracker'!$T$6:$T$400,$S40)="","",INDEX('Master Tracker'!$T$6:$T$400,$S40))) -> Not Tested | P40: =IF($S40="","",IF(INDEX('Master Tracker'!$AC$6:$AC$400,$S40)="","",INDEX('Master Tracker'!$AC$6:$AC$400,$S40))) -> On track | S40: =IFERROR(MATCH("Phase 2|"&A40,'Master Tracker'!$Z$6:$Z$400,0),"") -> 19
A41: 3 | B41: =IF($S41="","",IF(INDEX('Master Tracker'!$A$6:$A$400,$S41)="","",INDEX('Master Tracker'!$A$6:$A$400,$S41))) -> P2-03 | C41: =IF($S41="","",IF(INDEX('Master Tracker'!$C$6:$C$400,$S41)="","",INDEX('Master Tracker'!$C$6:$C$400,$S41))) -> Customizer Controls | D41: =IF($S41="","",IF(INDEX('Master Tracker'!$D$6:$D$400,$S41)="","",INDEX('Master Tracker'!$D$6:$D$400,$S41))) -> Dynamic category / tag selection | E41: =IF($S41="","",IF(INDEX('Master Tracker'!$F$6:$F$400,$S41)="","",INDEX('Master Tracker'!$F$6:$F$400,$S41))) -> P0 | F41: =IF($S41="","",IF(INDEX('Master Tracker'!$G$6:$G$400,$S41)="","",INDEX('Master Tracker'!$G$6:$G$400,$S41))) -> Not Started | G41: =IF($S41="","",IF(INDEX('Master Tracker'!$H$6:$H$400,$S41)="","",INDEX('Master Tracker'!$H$6:$H$400,$S41))) -> 46310 | H41: =IF($S41="","",IF(INDEX('Master Tracker'!$I$6:$I$400,$S41)="","",INDEX('Master Tracker'!$I$6:$I$400,$S41))) -> 46310 | I41: =IF($S41="","",IF(INDEX('Master Tracker'!$U$6:$U$400,$S41)="","",INDEX('Master Tracker'!$U$6:$U$400,$S41))) -> 0 | J41: =IF($S41="","",IF(INDEX('Master Tracker'!$K$6:$K$400,$S41)="","",INDEX('Master Tracker'!$K$6:$K$400,$S41))) -> P2-02 | K41: =IF($S41="","",IF(INDEX('Master Tracker'!$Y$6:$Y$400,$S41)="","",INDEX('Master Tracker'!$Y$6:$Y$400,$S41))) -> ⏳ 1 open | L41: =IF($S41="","",IF(INDEX('Master Tracker'!$M$6:$M$400,$S41)="","",INDEX('Master Tracker'!$M$6:$M$400,$S41))) -> inc/customizer/controls/term-select.php, assets/js/customizer-controls.js | M41: =IF($S41="","",IF(INDEX('Master Tracker'!$O$6:$O$400,$S41)="","",INDEX('Master Tracker'!$O$6:$O$400,$S41))) -> Sections can be sourced from any category/tag combination by ID | N41: =IF($S41="","",IF(INDEX('Master Tracker'!$N$6:$N$400,$S41)="","",INDEX('Master Tracker'!$N$6:$N$400,$S41))) -> Select 2 categories + 1 tag; rename a category; section still pulls correctly | O41: =IF($S41="","",IF(INDEX('Master Tracker'!$T$6:$T$400,$S41)="","",INDEX('Master Tracker'!$T$6:$T$400,$S41))) -> Not Tested | P41: =IF($S41="","",IF(INDEX('Master Tracker'!$AC$6:$AC$400,$S41)="","",INDEX('Master Tracker'!$AC$6:$AC$400,$S41))) -> On track | S41: =IFERROR(MATCH("Phase 2|"&A41,'Master Tracker'!$Z$6:$Z$400,0),"") -> 20
A42: 4 | B42: =IF($S42="","",IF(INDEX('Master Tracker'!$A$6:$A$400,$S42)="","",INDEX('Master Tracker'!$A$6:$A$400,$S42))) -> P2-04 | C42: =IF($S42="","",IF(INDEX('Master Tracker'!$C$6:$C$400,$S42)="","",INDEX('Master Tracker'!$C$6:$C$400,$S42))) -> Customizer Controls | D42: =IF($S42="","",IF(INDEX('Master Tracker'!$D$6:$D$400,$S42)="","",INDEX('Master Tracker'!$D$6:$D$400,$S42))) -> Post count, sorting & offset controls | E42: =IF($S42="","",IF(INDEX('Master Tracker'!$F$6:$F$400,$S42)="","",INDEX('Master Tracker'!$F$6:$F$400,$S42))) -> P0 | F42: =IF($S42="","",IF(INDEX('Master Tracker'!$G$6:$G$400,$S42)="","",INDEX('Master Tracker'!$G$6:$G$400,$S42))) -> Not Started | G42: =IF($S42="","",IF(INDEX('Master Tracker'!$H$6:$H$400,$S42)="","",INDEX('Master Tracker'!$H$6:$H$400,$S42))) -> 46310 | H42: =IF($S42="","",IF(INDEX('Master Tracker'!$I$6:$I$400,$S42)="","",INDEX('Master Tracker'!$I$6:$I$400,$S42))) -> 46310 | I42: =IF($S42="","",IF(INDEX('Master Tracker'!$U$6:$U$400,$S42)="","",INDEX('Master Tracker'!$U$6:$U$400,$S42))) -> 0 | J42: =IF($S42="","",IF(INDEX('Master Tracker'!$K$6:$K$400,$S42)="","",INDEX('Master Tracker'!$K$6:$K$400,$S42))) -> P2-03 | K42: =IF($S42="","",IF(INDEX('Master Tracker'!$Y$6:$Y$400,$S42)="","",INDEX('Master Tracker'!$Y$6:$Y$400,$S42))) -> ⏳ 1 open | L42: =IF($S42="","",IF(INDEX('Master Tracker'!$M$6:$M$400,$S42)="","",INDEX('Master Tracker'!$M$6:$M$400,$S42))) -> inc/section-manager/query-builder.php | M42: =IF($S42="","",IF(INDEX('Master Tracker'!$O$6:$O$400,$S42)="","",INDEX('Master Tracker'!$O$6:$O$400,$S42))) -> Count, sorting and offset behave exactly as configured | N42: =IF($S42="","",IF(INDEX('Master Tracker'!$N$6:$N$400,$S42)="","",INDEX('Master Tracker'!$N$6:$N$400,$S42))) -> Change count, order and offset; verify returned posts in Query Monitor | O42: =IF($S42="","",IF(INDEX('Master Tracker'!$T$6:$T$400,$S42)="","",INDEX('Master Tracker'!$T$6:$T$400,$S42))) -> Not Tested | P42: =IF($S42="","",IF(INDEX('Master Tracker'!$AC$6:$AC$400,$S42)="","",INDEX('Master Tracker'!$AC$6:$AC$400,$S42))) -> On track | S42: =IFERROR(MATCH("Phase 2|"&A42,'Master Tracker'!$Z$6:$Z$400,0),"") -> 21
A43: 5 | B43: =IF($S43="","",IF(INDEX('Master Tracker'!$A$6:$A$400,$S43)="","",INDEX('Master Tracker'!$A$6:$A$400,$S43))) -> P2-05 | C43: =IF($S43="","",IF(INDEX('Master Tracker'!$C$6:$C$400,$S43)="","",INDEX('Master Tracker'!$C$6:$C$400,$S43))) -> Customizer Controls | D43: =IF($S43="","",IF(INDEX('Master Tracker'!$D$6:$D$400,$S43)="","",INDEX('Master Tracker'!$D$6:$D$400,$S43))) -> Manual post selection (post picker) | E43: =IF($S43="","",IF(INDEX('Master Tracker'!$F$6:$F$400,$S43)="","",INDEX('Master Tracker'!$F$6:$F$400,$S43))) -> P1 | F43: =IF($S43="","",IF(INDEX('Master Tracker'!$G$6:$G$400,$S43)="","",INDEX('Master Tracker'!$G$6:$G$400,$S43))) -> Not Started | G43: =IF($S43="","",IF(INDEX('Master Tracker'!$H$6:$H$400,$S43)="","",INDEX('Master Tracker'!$H$6:$H$400,$S43))) -> 46310 | H43: =IF($S43="","",IF(INDEX('Master Tracker'!$I$6:$I$400,$S43)="","",INDEX('Master Tracker'!$I$6:$I$400,$S43))) -> 46310 | I43: =IF($S43="","",IF(INDEX('Master Tracker'!$U$6:$U$400,$S43)="","",INDEX('Master Tracker'!$U$6:$U$400,$S43))) -> 0 | J43: =IF($S43="","",IF(INDEX('Master Tracker'!$K$6:$K$400,$S43)="","",INDEX('Master Tracker'!$K$6:$K$400,$S43))) -> P2-02 | K43: =IF($S43="","",IF(INDEX('Master Tracker'!$Y$6:$Y$400,$S43)="","",INDEX('Master Tracker'!$Y$6:$Y$400,$S43))) -> ⏳ 1 open | L43: =IF($S43="","",IF(INDEX('Master Tracker'!$M$6:$M$400,$S43)="","",INDEX('Master Tracker'!$M$6:$M$400,$S43))) -> inc/customizer/controls/post-picker.php, assets/js/customizer-controls.js | M43: =IF($S43="","",IF(INDEX('Master Tracker'!$O$6:$O$400,$S43)="","",INDEX('Master Tracker'!$O$6:$O$400,$S43))) -> Editors can pin specific posts in a chosen order | N43: =IF($S43="","",IF(INDEX('Master Tracker'!$N$6:$N$400,$S43)="","",INDEX('Master Tracker'!$N$6:$N$400,$S43))) -> Pick 4 posts, reorder, publish; homepage shows them in chosen order | O43: =IF($S43="","",IF(INDEX('Master Tracker'!$T$6:$T$400,$S43)="","",INDEX('Master Tracker'!$T$6:$T$400,$S43))) -> Not Tested | P43: =IF($S43="","",IF(INDEX('Master Tracker'!$AC$6:$AC$400,$S43)="","",INDEX('Master Tracker'!$AC$6:$AC$400,$S43))) -> On track | S43: =IFERROR(MATCH("Phase 2|"&A43,'Master Tracker'!$Z$6:$Z$400,0),"") -> 22
A44: 6 | B44: =IF($S44="","",IF(INDEX('Master Tracker'!$A$6:$A$400,$S44)="","",INDEX('Master Tracker'!$A$6:$A$400,$S44))) -> P2-06 | C44: =IF($S44="","",IF(INDEX('Master Tracker'!$C$6:$C$400,$S44)="","",INDEX('Master Tracker'!$C$6:$C$400,$S44))) -> Customizer Controls | D44: =IF($S44="","",IF(INDEX('Master Tracker'!$D$6:$D$400,$S44)="","",INDEX('Master Tracker'!$D$6:$D$400,$S44))) -> Layout switching per section | E44: =IF($S44="","",IF(INDEX('Master Tracker'!$F$6:$F$400,$S44)="","",INDEX('Master Tracker'!$F$6:$F$400,$S44))) -> P1 | F44: =IF($S44="","",IF(INDEX('Master Tracker'!$G$6:$G$400,$S44)="","",INDEX('Master Tracker'!$G$6:$G$400,$S44))) -> Not Started | G44: =IF($S44="","",IF(INDEX('Master Tracker'!$H$6:$H$400,$S44)="","",INDEX('Master Tracker'!$H$6:$H$400,$S44))) -> 46310 | H44: =IF($S44="","",IF(INDEX('Master Tracker'!$I$6:$I$400,$S44)="","",INDEX('Master Tracker'!$I$6:$I$400,$S44))) -> 46310 | I44: =IF($S44="","",IF(INDEX('Master Tracker'!$U$6:$U$400,$S44)="","",INDEX('Master Tracker'!$U$6:$U$400,$S44))) -> 0 | J44: =IF($S44="","",IF(INDEX('Master Tracker'!$K$6:$K$400,$S44)="","",INDEX('Master Tracker'!$K$6:$K$400,$S44))) -> P2-01 | K44: =IF($S44="","",IF(INDEX('Master Tracker'!$Y$6:$Y$400,$S44)="","",INDEX('Master Tracker'!$Y$6:$Y$400,$S44))) -> ⏳ 1 open | L44: =IF($S44="","",IF(INDEX('Master Tracker'!$M$6:$M$400,$S44)="","",INDEX('Master Tracker'!$M$6:$M$400,$S44))) -> template-parts/sections/*.php | M44: =IF($S44="","",IF(INDEX('Master Tracker'!$O$6:$O$400,$S44)="","",INDEX('Master Tracker'!$O$6:$O$400,$S44))) -> Each layout renders correctly and responsively | N44: =IF($S44="","",IF(INDEX('Master Tracker'!$N$6:$N$400,$S44)="","",INDEX('Master Tracker'!$N$6:$N$400,$S44))) -> Switch each section through every layout at 360 px and 1440 px | O44: =IF($S44="","",IF(INDEX('Master Tracker'!$T$6:$T$400,$S44)="","",INDEX('Master Tracker'!$T$6:$T$400,$S44))) -> Not Tested | P44: =IF($S44="","",IF(INDEX('Master Tracker'!$AC$6:$AC$400,$S44)="","",INDEX('Master Tracker'!$AC$6:$AC$400,$S44))) -> On track | S44: =IFERROR(MATCH("Phase 2|"&A44,'Master Tracker'!$Z$6:$Z$400,0),"") -> 23
A45: 7 | B45: =IF($S45="","",IF(INDEX('Master Tracker'!$A$6:$A$400,$S45)="","",INDEX('Master Tracker'!$A$6:$A$400,$S45))) -> P2-07 | C45: =IF($S45="","",IF(INDEX('Master Tracker'!$C$6:$C$400,$S45)="","",INDEX('Master Tracker'!$C$6:$C$400,$S45))) -> Customizer Controls | D45: =IF($S45="","",IF(INDEX('Master Tracker'!$D$6:$D$400,$S45)="","",INDEX('Master Tracker'!$D$6:$D$400,$S45))) -> Section visibility, ordering & de-duplication | E45: =IF($S45="","",IF(INDEX('Master Tracker'!$F$6:$F$400,$S45)="","",INDEX('Master Tracker'!$F$6:$F$400,$S45))) -> P0 | F45: =IF($S45="","",IF(INDEX('Master Tracker'!$G$6:$G$400,$S45)="","",INDEX('Master Tracker'!$G$6:$G$400,$S45))) -> Not Started | G45: =IF($S45="","",IF(INDEX('Master Tracker'!$H$6:$H$400,$S45)="","",INDEX('Master Tracker'!$H$6:$H$400,$S45))) -> 46310 | H45: =IF($S45="","",IF(INDEX('Master Tracker'!$I$6:$I$400,$S45)="","",INDEX('Master Tracker'!$I$6:$I$400,$S45))) -> 46311 | I45: =IF($S45="","",IF(INDEX('Master Tracker'!$U$6:$U$400,$S45)="","",INDEX('Master Tracker'!$U$6:$U$400,$S45))) -> 0 | J45: =IF($S45="","",IF(INDEX('Master Tracker'!$K$6:$K$400,$S45)="","",INDEX('Master Tracker'!$K$6:$K$400,$S45))) -> P2-02 | K45: =IF($S45="","",IF(INDEX('Master Tracker'!$Y$6:$Y$400,$S45)="","",INDEX('Master Tracker'!$Y$6:$Y$400,$S45))) -> ⏳ 1 open | L45: =IF($S45="","",IF(INDEX('Master Tracker'!$M$6:$M$400,$S45)="","",INDEX('Master Tracker'!$M$6:$M$400,$S45))) -> inc/section-manager/render.php, inc/customizer/controls/sortable.php | M45: =IF($S45="","",IF(INDEX('Master Tracker'!$O$6:$O$400,$S45)="","",INDEX('Master Tracker'!$O$6:$O$400,$S45))) -> Visibility, order and de-duplication controlled from Customizer | N45: =IF($S45="","",IF(INDEX('Master Tracker'!$N$6:$N$400,$S45)="","",INDEX('Master Tracker'!$N$6:$N$400,$S45))) -> Hide a section, reorder two sections, confirm no duplicate posts across sections | O45: =IF($S45="","",IF(INDEX('Master Tracker'!$T$6:$T$400,$S45)="","",INDEX('Master Tracker'!$T$6:$T$400,$S45))) -> Not Tested | P45: =IF($S45="","",IF(INDEX('Master Tracker'!$AC$6:$AC$400,$S45)="","",INDEX('Master Tracker'!$AC$6:$AC$400,$S45))) -> On track | S45: =IFERROR(MATCH("Phase 2|"&A45,'Master Tracker'!$Z$6:$Z$400,0),"") -> 24
A46: 8 | B46: =IF($S46="","",IF(INDEX('Master Tracker'!$A$6:$A$400,$S46)="","",INDEX('Master Tracker'!$A$6:$A$400,$S46))) -> P2-08 | C46: =IF($S46="","",IF(INDEX('Master Tracker'!$C$6:$C$400,$S46)="","",INDEX('Master Tracker'!$C$6:$C$400,$S46))) -> Cache Controls | D46: =IF($S46="","",IF(INDEX('Master Tracker'!$D$6:$D$400,$S46)="","",INDEX('Master Tracker'!$D$6:$D$400,$S46))) -> Section cache controls + LiteSpeed purge | E46: =IF($S46="","",IF(INDEX('Master Tracker'!$F$6:$F$400,$S46)="","",INDEX('Master Tracker'!$F$6:$F$400,$S46))) -> P0 | F46: =IF($S46="","",IF(INDEX('Master Tracker'!$G$6:$G$400,$S46)="","",INDEX('Master Tracker'!$G$6:$G$400,$S46))) -> Not Started | G46: =IF($S46="","",IF(INDEX('Master Tracker'!$H$6:$H$400,$S46)="","",INDEX('Master Tracker'!$H$6:$H$400,$S46))) -> 46311 | H46: =IF($S46="","",IF(INDEX('Master Tracker'!$I$6:$I$400,$S46)="","",INDEX('Master Tracker'!$I$6:$I$400,$S46))) -> 46311 | I46: =IF($S46="","",IF(INDEX('Master Tracker'!$U$6:$U$400,$S46)="","",INDEX('Master Tracker'!$U$6:$U$400,$S46))) -> 0 | J46: =IF($S46="","",IF(INDEX('Master Tracker'!$K$6:$K$400,$S46)="","",INDEX('Master Tracker'!$K$6:$K$400,$S46))) -> P1-14, P2-01 | K46: =IF($S46="","",IF(INDEX('Master Tracker'!$Y$6:$Y$400,$S46)="","",INDEX('Master Tracker'!$Y$6:$Y$400,$S46))) -> ⏳ 2 open | L46: =IF($S46="","",IF(INDEX('Master Tracker'!$M$6:$M$400,$S46)="","",INDEX('Master Tracker'!$M$6:$M$400,$S46))) -> inc/section-manager/cache.php | M46: =IF($S46="","",IF(INDEX('Master Tracker'!$O$6:$O$400,$S46)="","",INDEX('Master Tracker'!$O$6:$O$400,$S46))) -> Homepage never serves stale sections after publish; manual purge available | N46: =IF($S46="","",IF(INDEX('Master Tracker'!$N$6:$N$400,$S46)="","",INDEX('Master Tracker'!$N$6:$N$400,$S46))) -> Publish a post → appears on homepage after purge; purge button works only for editors+ | O46: =IF($S46="","",IF(INDEX('Master Tracker'!$T$6:$T$400,$S46)="","",INDEX('Master Tracker'!$T$6:$T$400,$S46))) -> Not Tested | P46: =IF($S46="","",IF(INDEX('Master Tracker'!$AC$6:$AC$400,$S46)="","",INDEX('Master Tracker'!$AC$6:$AC$400,$S46))) -> On track | S46: =IFERROR(MATCH("Phase 2|"&A46,'Master Tracker'!$Z$6:$Z$400,0),"") -> 25
A47: 9 | B47: =IF($S47="","",IF(INDEX('Master Tracker'!$A$6:$A$400,$S47)="","",INDEX('Master Tracker'!$A$6:$A$400,$S47))) -> P2-09 | C47: =IF($S47="","",IF(INDEX('Master Tracker'!$C$6:$C$400,$S47)="","",INDEX('Master Tracker'!$C$6:$C$400,$S47))) -> Homepage Sections | D47: =IF($S47="","",IF(INDEX('Master Tracker'!$D$6:$D$400,$S47)="","",INDEX('Master Tracker'!$D$6:$D$400,$S47))) -> Homepage hero | E47: =IF($S47="","",IF(INDEX('Master Tracker'!$F$6:$F$400,$S47)="","",INDEX('Master Tracker'!$F$6:$F$400,$S47))) -> P0 | F47: =IF($S47="","",IF(INDEX('Master Tracker'!$G$6:$G$400,$S47)="","",INDEX('Master Tracker'!$G$6:$G$400,$S47))) -> Not Started | G47: =IF($S47="","",IF(INDEX('Master Tracker'!$H$6:$H$400,$S47)="","",INDEX('Master Tracker'!$H$6:$H$400,$S47))) -> 46311 | H47: =IF($S47="","",IF(INDEX('Master Tracker'!$I$6:$I$400,$S47)="","",INDEX('Master Tracker'!$I$6:$I$400,$S47))) -> 46311 | I47: =IF($S47="","",IF(INDEX('Master Tracker'!$U$6:$U$400,$S47)="","",INDEX('Master Tracker'!$U$6:$U$400,$S47))) -> 0 | J47: =IF($S47="","",IF(INDEX('Master Tracker'!$K$6:$K$400,$S47)="","",INDEX('Master Tracker'!$K$6:$K$400,$S47))) -> P2-01 | K47: =IF($S47="","",IF(INDEX('Master Tracker'!$Y$6:$Y$400,$S47)="","",INDEX('Master Tracker'!$Y$6:$Y$400,$S47))) -> ⏳ 1 open | L47: =IF($S47="","",IF(INDEX('Master Tracker'!$M$6:$M$400,$S47)="","",INDEX('Master Tracker'!$M$6:$M$400,$S47))) -> template-parts/sections/hero.php | M47: =IF($S47="","",IF(INDEX('Master Tracker'!$O$6:$O$400,$S47)="","",INDEX('Master Tracker'!$O$6:$O$400,$S47))) -> Hero is editor-controlled and renders well on all breakpoints | N47: =IF($S47="","",IF(INDEX('Master Tracker'!$N$6:$N$400,$S47)="","",INDEX('Master Tracker'!$N$6:$N$400,$S47))) -> Change hero source; check mobile crop and title wrapping in Arabic | O47: =IF($S47="","",IF(INDEX('Master Tracker'!$T$6:$T$400,$S47)="","",INDEX('Master Tracker'!$T$6:$T$400,$S47))) -> Not Tested | P47: =IF($S47="","",IF(INDEX('Master Tracker'!$AC$6:$AC$400,$S47)="","",INDEX('Master Tracker'!$AC$6:$AC$400,$S47))) -> On track | S47: =IFERROR(MATCH("Phase 2|"&A47,'Master Tracker'!$Z$6:$Z$400,0),"") -> 26
A48: 10 | B48: =IF($S48="","",IF(INDEX('Master Tracker'!$A$6:$A$400,$S48)="","",INDEX('Master Tracker'!$A$6:$A$400,$S48))) -> P2-10 | C48: =IF($S48="","",IF(INDEX('Master Tracker'!$C$6:$C$400,$S48)="","",INDEX('Master Tracker'!$C$6:$C$400,$S48))) -> Homepage Sections | D48: =IF($S48="","",IF(INDEX('Master Tracker'!$D$6:$D$400,$S48)="","",INDEX('Master Tracker'!$D$6:$D$400,$S48))) -> Breaking news ticker | E48: =IF($S48="","",IF(INDEX('Master Tracker'!$F$6:$F$400,$S48)="","",INDEX('Master Tracker'!$F$6:$F$400,$S48))) -> P0 | F48: =IF($S48="","",IF(INDEX('Master Tracker'!$G$6:$G$400,$S48)="","",INDEX('Master Tracker'!$G$6:$G$400,$S48))) -> Not Started | G48: =IF($S48="","",IF(INDEX('Master Tracker'!$H$6:$H$400,$S48)="","",INDEX('Master Tracker'!$H$6:$H$400,$S48))) -> 46311 | H48: =IF($S48="","",IF(INDEX('Master Tracker'!$I$6:$I$400,$S48)="","",INDEX('Master Tracker'!$I$6:$I$400,$S48))) -> 46311 | I48: =IF($S48="","",IF(INDEX('Master Tracker'!$U$6:$U$400,$S48)="","",INDEX('Master Tracker'!$U$6:$U$400,$S48))) -> 0 | J48: =IF($S48="","",IF(INDEX('Master Tracker'!$K$6:$K$400,$S48)="","",INDEX('Master Tracker'!$K$6:$K$400,$S48))) -> P2-01 | K48: =IF($S48="","",IF(INDEX('Master Tracker'!$Y$6:$Y$400,$S48)="","",INDEX('Master Tracker'!$Y$6:$Y$400,$S48))) -> ⏳ 1 open | L48: =IF($S48="","",IF(INDEX('Master Tracker'!$M$6:$M$400,$S48)="","",INDEX('Master Tracker'!$M$6:$M$400,$S48))) -> template-parts/sections/ticker.php, assets/js/modules/ticker.js | M48: =IF($S48="","",IF(INDEX('Master Tracker'!$O$6:$O$400,$S48)="","",INDEX('Master Tracker'!$O$6:$O$400,$S48))) -> Ticker updates from WordPress, scrolls RTL and is accessible | N48: =IF($S48="","",IF(INDEX('Master Tracker'!$N$6:$N$400,$S48)="","",INDEX('Master Tracker'!$N$6:$N$400,$S48))) -> Add/remove breaking tag; test RTL scroll direction, hover pause, reduced motion | O48: =IF($S48="","",IF(INDEX('Master Tracker'!$T$6:$T$400,$S48)="","",INDEX('Master Tracker'!$T$6:$T$400,$S48))) -> Not Tested | P48: =IF($S48="","",IF(INDEX('Master Tracker'!$AC$6:$AC$400,$S48)="","",INDEX('Master Tracker'!$AC$6:$AC$400,$S48))) -> On track | S48: =IFERROR(MATCH("Phase 2|"&A48,'Master Tracker'!$Z$6:$Z$400,0),"") -> 27
